{"qid": "q151", "query_text": "Apakah seorang investor yang menanggung risiko besar dan biaya tinggi dalam membangun infrastruktur jalan tol dapat menuntut ganti rugi jika pemerintah membatalkan perjanjiannya sebelum masa kerja selesai?", "case_name": "15_PUU-XVI_2018.pdf", "n_gt": 2, "gt_doc_ids": ["1236", "1246"], "gt_ranks": {"1246": 12, "1236": 143}, "ranked_docs": [{"rank": 1, "doc_id": "1603q", "title": "Pasal 1603q", "bm25_score": 23.8426, "is_relevant": false, "per_token": [{"token": "rugi", "contribution": 7.1942, "idf": 4.6556, "tf": 7, "in_doc": true}, {"token": "ganti", "contribution": 7.0342, "idf": 4.5521, "tf": 7, "in_doc": true}, {"token": "kerja", "contribution": 6.3686, "idf": 4.7509, "tf": 5, "in_doc": true}, {"token": "tinggi", "contribution": 2.6378, "idf": 5.6184, "tf": 1, "in_doc": true}, {"token": "besar", "contribution": 2.4401, "idf": 5.1972, "tf": 1, "in_doc": true}, {"token": "dalam", "contribution": 2.0905, "idf": 1.7403, "tf": 4, "in_doc": true}, {"token": "jika", "contribution": 2.0401, "idf": 2.5807, "tf": 2, "in_doc": true}, {"token": "dan", "contribution": 1.8725, "idf": 1.5588, "tf": 4, "in_doc": true}, {"token": "dapat", "contribution": 1.0365, "idf": 2.2077, "tf": 1, "in_doc": true}, {"token": "apakah", "contribution": 0.0, "idf": 0.0, "tf": 0, "in_doc": false}, {"token": "seorang", "contribution": 0.0, "idf": 0.0, "tf": 0, "in_doc": false}, {"token": "investor", "contribution": 0.0, "idf": 0.0, "tf": 0, "in_doc": false}, {"token": "yang", "contribution": 0.0, "idf": 0.0, "tf": 8, "in_doc": true}, {"token": "menanggung", "contribution": 0.0, "idf": 0.0, "tf": 0, "in_doc": false}, {"token": "risiko", "contribution": 0.0, "idf": 0.0, "tf": 0, "in_doc": false}, {"token": "biaya", "contribution": 0.0, "idf": 0.0, "tf": 0, "in_doc": false}, {"token": "membangun", "contribution": 0.0, "idf": 0.0, "tf": 0, "in_doc": false}, {"token": "infrastruktur", "contribution": 0.0, "idf": 0.0, "tf": 0, "in_doc": false}, {"token": "jalan", "contribution": 0.0, "idf": 0.0, "tf": 0, "in_doc": false}, {"token": "tol", "contribution": 0.0, "idf": 0.0, "tf": 0, "in_doc": false}], "doc_highlights": [{"start": 13, "end": 18, "token": "ganti", "intensity": 0.978, "score": 7.0342}, {"start": 19, "end": 23, "token": "rugi", "intensity": 1.0, "score": 7.1942}, {"start": 51, "end": 54, "token": "dan", "intensity": 0.26, "score": 1.8725}, {"start": 61, "end": 66, "token": "dalam", "intensity": 0.291, "score": 2.0905}, {"start": 86, "end": 91, "token": "kerja", "intensity": 0.885, "score": 6.3686}, {"start": 255, "end": 260, "token": "kerja", "intensity": 0.885, "score": 6.3686}, {"start": 299, "end": 304, "token": "dalam", "intensity": 0.291, "score": 2.0905}, {"start": 318, "end": 323, "token": "kerja", "intensity": 0.885, "score": 6.3686}, {"start": 355, "end": 360, "token": "ganti", "intensity": 0.978, "score": 7.0342}, {"start": 361, "end": 365, "token": "rugi", "intensity": 1.0, "score": 7.1942}, {"start": 429, "end": 434, "token": "kerja", "intensity": 0.885, "score": 6.3686}, {"start": 466, "end": 469, "token": "dan", "intensity": 0.26, "score": 1.8725}, {"start": 601, "end": 604, "token": "dan", "intensity": 0.26, "score": 1.8725}, {"start": 607, "end": 611, "token": "jika", "intensity": 0.284, "score": 2.0401}, {"start": 781, "end": 786, "token": "ganti", "intensity": 0.978, "score": 7.0342}, {"start": 787, "end": 791, "token": "rugi", "intensity": 1.0, "score": 7.1942}, {"start": 836, "end": 841, "token": "dalam", "intensity": 0.291, "score": 2.0905}, {"start": 873, "end": 878, "token": "dapat", "intensity": 0.144, "score": 1.0365}, {"start": 896, "end": 901, "token": "ganti", "intensity": 0.978, "score": 7.0342}, {"start": 902, "end": 906, "token": "rugi", "intensity": 1.0, "score": 7.1942}, {"start": 918, "end": 923, "token": "besar", "intensity": 0.339, "score": 2.4401}, {"start": 973, "end": 978, "token": "ganti", "intensity": 0.978, "score": 7.0342}, {"start": 979, "end": 983, "token": "rugi", "intensity": 1.0, "score": 7.1942}, {"start": 1014, "end": 1017, "token": "dan", "intensity": 0.26, "score": 1.8725}, {"start": 1036, "end": 1041, "token": "dalam", "intensity": 0.291, "score": 2.0905}, {"start": 1068, "end": 1072, "token": "jika", "intensity": 0.284, "score": 2.0401}, {"start": 1093, "end": 1098, "token": "ganti", "intensity": 0.978, "score": 7.0342}, {"start": 1099, "end": 1103, "token": "rugi", "intensity": 1.0, "score": 7.1942}, {"start": 1116, "end": 1122, "token": "tinggi", "intensity": 0.367, "score": 2.6378}, {"start": 1129, "end": 1134, "token": "ganti", "intensity": 0.978, "score": 7.0342}, {"start": 1135, "end": 1139, "token": "rugi", "intensity": 1.0, "score": 7.1942}, {"start": 1239, "end": 1244, "token": "kerja", "intensity": 0.885, "score": 6.3686}], "query_highlights": [{"start": 47, "end": 52, "token": "besar", "intensity": 0.339, "score": 2.4401}, {"start": 53, "end": 56, "token": "dan", "intensity": 0.26, "score": 1.8725}, {"start": 63, "end": 69, "token": "tinggi", "intensity": 0.367, "score": 2.6378}, {"start": 70, "end": 75, "token": "dalam", "intensity": 0.291, "score": 2.0905}, {"start": 110, "end": 115, "token": "dapat", "intensity": 0.144, "score": 1.0365}, {"start": 125, "end": 130, "token": "ganti", "intensity": 0.978, "score": 7.0342}, {"start": 131, "end": 135, "token": "rugi", "intensity": 1.0, "score": 7.1942}, {"start": 136, "end": 140, "token": "jika", "intensity": 0.284, "score": 2.0401}, {"start": 191, "end": 196, "token": "kerja", "intensity": 0.885, "score": 6.3686}]}, {"rank": 2, "doc_id": "1603r", "title": "Pasal 1603r", "bm25_score": 22.3568, "is_relevant": false, "per_token": [{"token": "kerja", "contribution": 7.1546, "idf": 4.7509, "tf": 3, "in_doc": true}, {"token": "rugi", "contribution": 7.011, "idf": 4.6556, "tf": 3, "in_doc": true}, {"token": "ganti", "contribution": 6.8551, "idf": 4.5521, "tf": 3, "in_doc": true}, {"token": "jika", "contribution": 3.2419, "idf": 2.5807, "tf": 2, "in_doc": true}, {"token": "menuntut", "contribution": 2.944, "idf": 3.5096, "tf": 1, "in_doc": true}, {"token": "dapat", "contribution": 1.8519, "idf": 2.2077, "tf": 1, "in_doc": true}, {"token": "dalam", "contribution": 1.4598, "idf": 1.7403, "tf": 1, "in_doc": true}, {"token": "apakah", "contribution": 0.0, "idf": 0.0, "tf": 0, "in_doc": false}, {"token": "seorang", "contribution": 0.0, "idf": 0.0, "tf": 0, "in_doc": false}, {"token": "investor", "contribution": 0.0, "idf": 0.0, "tf": 0, "in_doc": false}, {"token": "yang", "contribution": 0.0, "idf": 0.0, "tf": 5, "in_doc": true}, {"token": "menanggung", "contribution": 0.0, "idf": 0.0, "tf": 0, "in_doc": false}, {"token": "risiko", "contribution": 0.0, "idf": 0.0, "tf": 0, "in_doc": false}, {"token": "besar", "contribution": 0.0, "idf": 0.0, "tf": 0, "in_doc": false}, {"token": "dan", "contribution": 0.0, "idf": 0.0, "tf": 0, "in_doc": false}, {"token": "biaya", "contribution": 0.0, "idf": 0.0, "tf": 0, "in_doc": false}, {"token": "tinggi", "contribution": 0.0, "idf": 0.0, "tf": 0, "in_doc": false}, {"token": "membangun", "contribution": 0.0, "idf": 0.0, "tf": 0, "in_doc": false}, {"token": "infrastruktur", "contribution": 0.0, "idf": 0.0, "tf": 0, "in_doc": false}, {"token": "jalan", "contribution": 0.0, "idf": 0.0, "tf": 0, "in_doc": false}], "doc_highlights": [{"start": 13, "end": 17, "token": "jika", "intensity": 0.453, "score": 3.2419}, {"start": 55, "end": 60, "token": "kerja", "intensity": 1.0, "score": 7.1546}, {"start": 97, "end": 102, "token": "kerja", "intensity": 1.0, "score": 7.1546}, {"start": 195, "end": 200, "token": "kerja", "intensity": 1.0, "score": 7.1546}, {"start": 218, "end": 223, "token": "ganti", "intensity": 0.958, "score": 6.8551}, {"start": 224, "end": 228, "token": "rugi", "intensity": 0.98, "score": 7.011}, {"start": 335, "end": 339, "token": "jika", "intensity": 0.453, "score": 3.2419}, {"start": 356, "end": 361, "token": "dalam", "intensity": 0.204, "score": 1.4598}, {"start": 429, "end": 434, "token": "dapat", "intensity": 0.259, "score": 1.8519}, {"start": 465, "end": 470, "token": "ganti", "intensity": 0.958, "score": 6.8551}, {"start": 471, "end": 475, "token": "rugi", "intensity": 0.98, "score": 7.011}, {"start": 502, "end": 510, "token": "menuntut", "intensity": 0.411, "score": 2.944}, {"start": 511, "end": 516, "token": "ganti", "intensity": 0.958, "score": 6.8551}, {"start": 517, "end": 521, "token": "rugi", "intensity": 0.98, "score": 7.011}], "query_highlights": [{"start": 70, "end": 75, "token": "dalam", "intensity": 0.204, "score": 1.4598}, {"start": 110, "end": 115, "token": "dapat", "intensity": 0.259, "score": 1.8519}, {"start": 116, "end": 124, "token": "menuntut", "intensity": 0.411, "score": 2.944}, {"start": 125, "end": 130, "token": "ganti", "intensity": 0.958, "score": 6.8551}, {"start": 131, "end": 135, "token": "rugi", "intensity": 0.98, "score": 7.011}, {"start": 136, "end": 140, "token": "jika", "intensity": 0.453, "score": 3.2419}, {"start": 191, "end": 196, "token": "kerja", "intensity": 1.0, "score": 7.1546}]}, {"rank": 3, "doc_id": "1603s", "title": "Pasal 1603s", "bm25_score": 22.0944, "is_relevant": false, "per_token": [{"token": "kerja", "contribution": 7.7106, "idf": 4.7509, "tf": 15, "in_doc": true}, {"token": "masa", "contribution": 7.1429, "idf": 6.717, "tf": 6, "in_doc": true}, {"token": "rugi", "contribution": 3.1441, "idf": 4.6556, "tf": 3, "in_doc": true}, {"token": "ganti", "contribution": 3.0741, "idf": 4.5521, "tf": 3, "in_doc": true}, {"token": "jika", "contribution": 2.9898, "idf": 2.5807, "tf": 7, "in_doc": true}, {"token": "menuntut", "contribution": 2.3702, "idf": 3.5096, "tf": 3, "in_doc": true}, {"token": "dalam", "contribution": 2.0161, "idf": 1.7403, "tf": 7, "in_doc": true}, {"token": "dan", "contribution": 1.4867, "idf": 1.5588, "tf": 5, "in_doc": true}, {"token": "dapat", "contribution": 0.6061, "idf": 2.2077, "tf": 1, "in_doc": true}, {"token": "apakah", "contribution": 0.0, "idf": 0.0, "tf": 0, "in_doc": false}, {"token": "seorang", "contribution": 0.0, "idf": 0.0, "tf": 0, "in_doc": false}, {"token": "investor", "contribution": 0.0, "idf": 0.0, "tf": 0, "in_doc": false}, {"token": "yang", "contribution": 0.0, "idf": 0.0, "tf": 16, "in_doc": true}, {"token": "menanggung", "contribution": 0.0, "idf": 0.0, "tf": 0, "in_doc": false}, {"token": "risiko", "contribution": 0.0, "idf": 0.0, "tf": 0, "in_doc": false}, {"token": "besar", "contribution": 0.0, "idf": 0.0, "tf": 0, "in_doc": false}, {"token": "biaya", "contribution": 0.0, "idf": 0.0, "tf": 0, "in_doc": false}, {"token": "tinggi", "contribution": 0.0, "idf": 0.0, "tf": 0, "in_doc": false}, {"token": "membangun", "contribution": 0.0, "idf": 0.0, "tf": 0, "in_doc": false}, {"token": "infrastruktur", "contribution": 0.0, "idf": 0.0, "tf": 0, "in_doc": false}], "doc_highlights": [{"start": 13, "end": 18, "token": "dalam", "intensity": 0.261, "score": 2.0161}, {"start": 103, "end": 111, "token": "menuntut", "intensity": 0.307, "score": 2.3702}, {"start": 152, "end": 157, "token": "ganti", "intensity": 0.399, "score": 3.0741}, {"start": 158, "end": 162, "token": "rugi", "intensity": 0.408, "score": 3.1441}, {"start": 202, "end": 206, "token": "jika", "intensity": 0.388, "score": 2.9898}, {"start": 331, "end": 336, "token": "kerja", "intensity": 1.0, "score": 7.7106}, {"start": 373, "end": 378, "token": "kerja", "intensity": 1.0, "score": 7.7106}, {"start": 471, "end": 476, "token": "kerja", "intensity": 1.0, "score": 7.7106}, {"start": 477, "end": 480, "token": "dan", "intensity": 0.193, "score": 1.4867}, {"start": 536, "end": 540, "token": "jika", "intensity": 0.388, "score": 2.9898}, {"start": 569, "end": 574, "token": "kerja", "intensity": 1.0, "score": 7.7106}, {"start": 647, "end": 651, "token": "masa", "intensity": 0.926, "score": 7.1429}, {"start": 652, "end": 657, "token": "kerja", "intensity": 1.0, "score": 7.7106}, {"start": 692, "end": 697, "token": "dalam", "intensity": 0.261, "score": 2.0161}, {"start": 763, "end": 771, "token": "menuntut", "intensity": 0.307, "score": 2.3702}, {"start": 781, "end": 786, "token": "dapat", "intensity": 0.079, "score": 0.6061}, {"start": 868, "end": 876, "token": "menuntut", "intensity": 0.307, "score": 2.3702}, {"start": 883, "end": 888, "token": "ganti", "intensity": 0.399, "score": 3.0741}, {"start": 889, "end": 893, "token": "rugi", "intensity": 0.408, "score": 3.1441}, {"start": 973, "end": 976, "token": "dan", "intensity": 0.193, "score": 1.4867}, {"start": 977, "end": 981, "token": "jika", "intensity": 0.388, "score": 2.9898}, {"start": 982, "end": 987, "token": "dalam", "intensity": 0.261, "score": 2.0161}, {"start": 1189, "end": 1194, "token": "kerja", "intensity": 1.0, "score": 7.7106}, {"start": 1196, "end": 1200, "token": "jika", "intensity": 0.388, "score": 2.9898}, {"start": 1263, "end": 1266, "token": "dan", "intensity": 0.193, "score": 1.4867}, {"start": 1267, "end": 1271, "token": "masa", "intensity": 0.926, "score": 7.1429}, {"start": 1272, "end": 1277, "token": "kerja", "intensity": 1.0, "score": 7.7106}, {"start": 1294, "end": 1299, "token": "dalam", "intensity": 0.261, "score": 2.0161}, {"start": 1377, "end": 1382, "token": "kerja", "intensity": 1.0, "score": 7.7106}, {"start": 1573, "end": 1578, "token": "ganti", "intensity": 0.399, "score": 3.0741}, {"start": 1579, "end": 1583, "token": "rugi", "intensity": 0.408, "score": 3.1441}, {"start": 1653, "end": 1657, "token": "masa", "intensity": 0.926, "score": 7.1429}, {"start": 1658, "end": 1663, "token": "kerja", "intensity": 1.0, "score": 7.7106}, {"start": 1750, "end": 1755, "token": "kerja", "intensity": 1.0, "score": 7.7106}, {"start": 1756, "end": 1759, "token": "dan", "intensity": 0.193, "score": 1.4867}, {"start": 1760, "end": 1764, "token": "masa", "intensity": 0.926, "score": 7.1429}, {"start": 1765, "end": 1770, "token": "kerja", "intensity": 1.0, "score": 7.7106}, {"start": 1817, "end": 1822, "token": "dalam", "intensity": 0.261, "score": 2.0161}, {"start": 1834, "end": 1838, "token": "masa", "intensity": 0.926, "score": 7.1429}, {"start": 1839, "end": 1844, "token": "kerja", "intensity": 1.0, "score": 7.7106}, {"start": 1871, "end": 1876, "token": "kerja", "intensity": 1.0, "score": 7.7106}, {"start": 1943, "end": 1947, "token": "jika", "intensity": 0.388, "score": 2.9898}, {"start": 1980, "end": 1984, "token": "masa", "intensity": 0.926, "score": 7.1429}, {"start": 1985, "end": 1990, "token": "kerja", "intensity": 1.0, "score": 7.7106}, {"start": 2043, "end": 2048, "token": "kerja", "intensity": 1.0, "score": 7.7106}, {"start": 2107, "end": 2111, "token": "jika", "intensity": 0.388, "score": 2.9898}, {"start": 2221, "end": 2226, "token": "dalam", "intensity": 0.261, "score": 2.0161}, {"start": 2387, "end": 2391, "token": "jika", "intensity": 0.388, "score": 2.9898}, {"start": 2458, "end": 2461, "token": "dan", "intensity": 0.193, "score": 1.4867}, {"start": 2530, "end": 2535, "token": "dalam", "intensity": 0.261, "score": 2.0161}], "query_highlights": [{"start": 53, "end": 56, "token": "dan", "intensity": 0.193, "score": 1.4867}, {"start": 70, "end": 75, "token": "dalam", "intensity": 0.261, "score": 2.0161}, {"start": 110, "end": 115, "token": "dapat", "intensity": 0.079, "score": 0.6061}, {"start": 116, "end": 124, "token": "menuntut", "intensity": 0.307, "score": 2.3702}, {"start": 125, "end": 130, "token": "ganti", "intensity": 0.399, "score": 3.0741}, {"start": 131, "end": 135, "token": "rugi", "intensity": 0.408, "score": 3.1441}, {"start": 136, "end": 140, "token": "jika", "intensity": 0.388, "score": 2.9898}, {"start": 186, "end": 190, "token": "masa", "intensity": 0.926, "score": 7.1429}, {"start": 191, "end": 196, "token": "kerja", "intensity": 1.0, "score": 7.7106}]}, {"rank": 4, "doc_id": "1702", "title": "Pasal 1702", "bm25_score": 16.9639, "is_relevant": false, "per_token": [{"token": "menuntut", "contribution": 4.7901, "idf": 3.5096, "tf": 2, "in_doc": true}, {"token": "rugi", "contribution": 4.3699, "idf": 4.6556, "tf": 1, "in_doc": true}, {"token": "ganti", "contribution": 4.2727, "idf": 4.5521, "tf": 1, "in_doc": true}, {"token": "seorang", "contribution": 4.0207, "idf": 2.9459, "tf": 2, "in_doc": true}, {"token": "jika", "contribution": 3.5222, "idf": 2.5807, "tf": 2, "in_doc": true}, {"token": "dapat", "contribution": 3.0132, "idf": 2.2077, "tf": 2, "in_doc": true}, {"token": "dan", "contribution": 1.4631, "idf": 1.5588, "tf": 1, "in_doc": true}, {"token": "apakah", "contribution": 0.0, "idf": 0.0, "tf": 0, "in_doc": false}, {"token": "investor", "contribution": 0.0, "idf": 0.0, "tf": 0, "in_doc": false}, {"token": "yang", "contribution": 0.0, "idf": 0.0, "tf": 2, "in_doc": true}, {"token": "menanggung", "contribution": 0.0, "idf": 0.0, "tf": 0, "in_doc": false}, {"token": "risiko", "contribution": 0.0, "idf": 0.0, "tf": 0, "in_doc": false}, {"token": "besar", "contribution": 0.0, "idf": 0.0, "tf": 0, "in_doc": false}, {"token": "biaya", "contribution": 0.0, "idf": 0.0, "tf": 0, "in_doc": false}, {"token": "tinggi", "contribution": 0.0, "idf": 0.0, "tf": 0, "in_doc": false}, {"token": "dalam", "contribution": 0.0, "idf": 0.0, "tf": 0, "in_doc": false}, {"token": "membangun", "contribution": 0.0, "idf": 0.0, "tf": 0, "in_doc": false}, {"token": "infrastruktur", "contribution": 0.0, "idf": 0.0, "tf": 0, "in_doc": false}, {"token": "jalan", "contribution": 0.0, "idf": 0.0, "tf": 0, "in_doc": false}, {"token": "tol", "contribution": 0.0, "idf": 0.0, "tf": 0, "in_doc": false}], "doc_highlights": [{"start": 12, "end": 16, "token": "jika", "intensity": 0.735, "score": 3.5222}, {"start": 49, "end": 56, "token": "seorang", "intensity": 0.839, "score": 4.0207}, {"start": 76, "end": 83, "token": "seorang", "intensity": 0.839, "score": 4.0207}, {"start": 201, "end": 206, "token": "dapat", "intensity": 0.629, "score": 3.0132}, {"start": 207, "end": 215, "token": "menuntut", "intensity": 1.0, "score": 4.7901}, {"start": 248, "end": 252, "token": "jika", "intensity": 0.735, "score": 3.5222}, {"start": 327, "end": 332, "token": "dapat", "intensity": 0.629, "score": 3.0132}, {"start": 333, "end": 341, "token": "menuntut", "intensity": 1.0, "score": 4.7901}, {"start": 342, "end": 347, "token": "ganti", "intensity": 0.892, "score": 4.2727}, {"start": 348, "end": 352, "token": "rugi", "intensity": 0.912, "score": 4.3699}, {"start": 394, "end": 397, "token": "dan", "intensity": 0.305, "score": 1.4631}], "query_highlights": [{"start": 7, "end": 14, "token": "seorang", "intensity": 0.839, "score": 4.0207}, {"start": 53, "end": 56, "token": "dan", "intensity": 0.305, "score": 1.4631}, {"start": 110, "end": 115, "token": "dapat", "intensity": 0.629, "score": 3.0132}, {"start": 116, "end": 124, "token": "menuntut", "intensity": 1.0, "score": 4.7901}, {"start": 125, "end": 130, "token": "ganti", "intensity": 0.892, "score": 4.2727}, {"start": 131, "end": 135, "token": "rugi", "intensity": 0.912, "score": 4.3699}, {"start": 136, "end": 140, "token": "jika", "intensity": 0.735, "score": 3.5222}]}, {"rank": 5, "doc_id": "1553", "title": "Pasal 1553", "bm25_score": 16.7423, "is_relevant": false, "per_token": [{"token": "masa", "contribution": 6.4585, "idf": 6.717, "tf": 1, "in_doc": true}, {"token": "rugi", "contribution": 4.4764, "idf": 4.6556, "tf": 1, "in_doc": true}, {"token": "ganti", "contribution": 4.3768, "idf": 4.5521, "tf": 1, "in_doc": true}, {"token": "jika", "contribution": 3.5842, "idf": 2.5807, "tf": 2, "in_doc": true}, {"token": "dalam", "contribution": 2.417, "idf": 1.7403, "tf": 2, "in_doc": true}, {"token": "dapat", "contribution": 2.1228, "idf": 2.2077, "tf": 1, "in_doc": true}, {"token": "apakah", "contribution": 0.0, "idf": 0.0, "tf": 0, "in_doc": false}, {"token": "seorang", "contribution": 0.0, "idf": 0.0, "tf": 0, "in_doc": false}, {"token": "investor", "contribution": 0.0, "idf": 0.0, "tf": 0, "in_doc": false}, {"token": "yang", "contribution": 0.0, "idf": 0.0, "tf": 3, "in_doc": true}, {"token": "menanggung", "contribution": 0.0, "idf": 0.0, "tf": 0, "in_doc": false}, {"token": "risiko", "contribution": 0.0, "idf": 0.0, "tf": 0, "in_doc": false}, {"token": "besar", "contribution": 0.0, "idf": 0.0, "tf": 0, "in_doc": false}, {"token": "dan", "contribution": 0.0, "idf": 0.0, "tf": 0, "in_doc": false}, {"token": "biaya", "contribution": 0.0, "idf": 0.0, "tf": 0, "in_doc": false}, {"token": "tinggi", "contribution": 0.0, "idf": 0.0, "tf": 0, "in_doc": false}, {"token": "membangun", "contribution": 0.0, "idf": 0.0, "tf": 0, "in_doc": false}, {"token": "infrastruktur", "contribution": 0.0, "idf": 0.0, "tf": 0, "in_doc": false}, {"token": "jalan", "contribution": 0.0, "idf": 0.0, "tf": 0, "in_doc": false}, {"token": "tol", "contribution": 0.0, "idf": 0.0, "tf": 0, "in_doc": false}], "doc_highlights": [{"start": 12, "end": 16, "token": "jika", "intensity": 0.555, "score": 3.5842}, {"start": 58, "end": 63, "token": "dalam", "intensity": 0.374, "score": 2.417}, {"start": 64, "end": 68, "token": "masa", "intensity": 1.0, "score": 6.4585}, {"start": 156, "end": 160, "token": "jika", "intensity": 0.555, "score": 3.5842}, {"start": 222, "end": 227, "token": "dapat", "intensity": 0.329, "score": 2.1228}, {"start": 338, "end": 343, "token": "dalam", "intensity": 0.374, "score": 2.417}, {"start": 379, "end": 384, "token": "ganti", "intensity": 0.678, "score": 4.3768}, {"start": 385, "end": 389, "token": "rugi", "intensity": 0.693, "score": 4.4764}], "query_highlights": [{"start": 70, "end": 75, "token": "dalam", "intensity": 0.374, "score": 2.417}, {"start": 110, "end": 115, "token": "dapat", "intensity": 0.329, "score": 2.1228}, {"start": 125, "end": 130, "token": "ganti", "intensity": 0.678, "score": 4.3768}, {"start": 131, "end": 135, "token": "rugi", "intensity": 0.693, "score": 4.4764}, {"start": 136, "end": 140, "token": "jika", "intensity": 0.555, "score": 3.5842}, {"start": 186, "end": 190, "token": "masa", "intensity": 1.0, "score": 6.4585}]}, {"rank": 6, "doc_id": "1316", "title": "Pasal 1316", "bm25_score": 16.6987, "is_relevant": false, "per_token": [{"token": "menanggung", "contribution": 5.4175, "idf": 4.8563, "tf": 1, "in_doc": true}, {"token": "rugi", "contribution": 5.1936, "idf": 4.6556, "tf": 1, "in_doc": true}, {"token": "ganti", "contribution": 5.0781, "idf": 4.5521, "tf": 1, "in_doc": true}, {"token": "seorang", "contribution": 3.2864, "idf": 2.9459, "tf": 1, "in_doc": true}, {"token": "jika", "contribution": 2.879, "idf": 2.5807, "tf": 1, "in_doc": true}, {"token": "dan", "contribution": 1.7389, "idf": 1.5588, "tf": 1, "in_doc": true}, {"token": "apakah", "contribution": 0.0, "idf": 0.0, "tf": 0, "in_doc": false}, {"token": "investor", "contribution": 0.0, "idf": 0.0, "tf": 0, "in_doc": false}, {"token": "yang", "contribution": 0.0, "idf": 0.0, "tf": 1, "in_doc": true}, {"token": "risiko", "contribution": 0.0, "idf": 0.0, "tf": 0, "in_doc": false}, {"token": "besar", "contribution": 0.0, "idf": 0.0, "tf": 0, "in_doc": false}, {"token": "biaya", "contribution": 0.0, "idf": 0.0, "tf": 0, "in_doc": false}, {"token": "tinggi", "contribution": 0.0, "idf": 0.0, "tf": 0, "in_doc": false}, {"token": "dalam", "contribution": 0.0, "idf": 0.0, "tf": 0, "in_doc": false}, {"token": "membangun", "contribution": 0.0, "idf": 0.0, "tf": 0, "in_doc": false}, {"token": "infrastruktur", "contribution": 0.0, "idf": 0.0, "tf": 0, "in_doc": false}, {"token": "jalan", "contribution": 0.0, "idf": 0.0, "tf": 0, "in_doc": false}, {"token": "tol", "contribution": 0.0, "idf": 0.0, "tf": 0, "in_doc": false}, {"token": "dapat", "contribution": 0.0, "idf": 0.0, "tf": 0, "in_doc": false}, {"token": "menuntut", "contribution": 0.0, "idf": 0.0, "tf": 0, "in_doc": false}], "doc_highlights": [{"start": 28, "end": 38, "token": "menanggung", "intensity": 1.0, "score": 5.4175}, {"start": 39, "end": 46, "token": "seorang", "intensity": 0.607, "score": 3.2864}, {"start": 60, "end": 63, "token": "dan", "intensity": 0.321, "score": 1.7389}, {"start": 160, "end": 165, "token": "ganti", "intensity": 0.937, "score": 5.0781}, {"start": 166, "end": 170, "token": "rugi", "intensity": 0.959, "score": 5.1936}, {"start": 221, "end": 225, "token": "jika", "intensity": 0.531, "score": 2.879}], "query_highlights": [{"start": 7, "end": 14, "token": "seorang", "intensity": 0.607, "score": 3.2864}, {"start": 29, "end": 39, "token": "menanggung", "intensity": 1.0, "score": 5.4175}, {"start": 53, "end": 56, "token": "dan", "intensity": 0.321, "score": 1.7389}, {"start": 125, "end": 130, "token": "ganti", "intensity": 0.937, "score": 5.0781}, {"start": 131, "end": 135, "token": "rugi", "intensity": 0.959, "score": 5.1936}, {"start": 136, "end": 140, "token": "jika", "intensity": 0.531, "score": 2.879}]}, {"rank": 7, "doc_id": "673", "title": "Pasal 673", "bm25_score": 16.6553, "is_relevant": false, "per_token": [{"token": "kerja", "contribution": 7.4755, "idf": 4.7509, "tf": 2, "in_doc": true}, {"token": "tinggi", "contribution": 6.4501, "idf": 5.6184, "tf": 1, "in_doc": true}, {"token": "pemerintah", "contribution": 5.8969, "idf": 5.1366, "tf": 1, "in_doc": true}, {"token": "dalam", "contribution": 1.9979, "idf": 1.7403, "tf": 1, "in_doc": true}, {"token": "apakah", "contribution": 0.0, "idf": 0.0, "tf": 0, "in_doc": false}, {"token": "seorang", "contribution": 0.0, "idf": 0.0, "tf": 0, "in_doc": false}, {"token": "investor", "contribution": 0.0, "idf": 0.0, "tf": 0, "in_doc": false}, {"token": "yang", "contribution": 0.0, "idf": 0.0, "tf": 1, "in_doc": true}, {"token": "menanggung", "contribution": 0.0, "idf": 0.0, "tf": 0, "in_doc": false}, {"token": "risiko", "contribution": 0.0, "idf": 0.0, "tf": 0, "in_doc": false}, {"token": "besar", "contribution": 0.0, "idf": 0.0, "tf": 0, "in_doc": false}, {"token": "dan", "contribution": 0.0, "idf": 0.0, "tf": 0, "in_doc": false}, {"token": "biaya", "contribution": 0.0, "idf": 0.0, "tf": 0, "in_doc": false}, {"token": "membangun", "contribution": 0.0, "idf": 0.0, "tf": 0, "in_doc": false}, {"token": "infrastruktur", "contribution": 0.0, "idf": 0.0, "tf": 0, "in_doc": false}, {"token": "jalan", "contribution": 0.0, "idf": 0.0, "tf": 0, "in_doc": false}, {"token": "tol", "contribution": 0.0, "idf": 0.0, "tf": 0, "in_doc": false}, {"token": "dapat", "contribution": 0.0, "idf": 0.0, "tf": 0, "in_doc": false}, {"token": "menuntut", "contribution": 0.0, "idf": 0.0, "tf": 0, "in_doc": false}, {"token": "ganti", "contribution": 0.0, "idf": 0.0, "tf": 0, "in_doc": false}], "doc_highlights": [{"start": 11, "end": 16, "token": "kerja", "intensity": 1.0, "score": 7.4755}, {"start": 64, "end": 70, "token": "tinggi", "intensity": 0.863, "score": 6.4501}, {"start": 102, "end": 107, "token": "dalam", "intensity": 0.267, "score": 1.9979}, {"start": 155, "end": 165, "token": "pemerintah", "intensity": 0.789, "score": 5.8969}, {"start": 226, "end": 231, "token": "kerja", "intensity": 1.0, "score": 7.4755}], "query_highlights": [{"start": 63, "end": 69, "token": "tinggi", "intensity": 0.863, "score": 6.4501}, {"start": 70, "end": 75, "token": "dalam", "intensity": 0.267, "score": 1.9979}, {"start": 141, "end": 151, "token": "pemerintah", "intensity": 0.789, "score": 5.8969}, {"start": 191, "end": 196, "token": "kerja", "intensity": 1.0, "score": 7.4755}]}, {"rank": 8, "doc_id": "667", "title": "Pasal 667", "bm25_score": 15.9641, "is_relevant": false, "per_token": [{"token": "jalan", "contribution": 8.4234, "idf": 5.1664, "tf": 3, "in_doc": true}, {"token": "rugi", "contribution": 4.4764, "idf": 4.6556, "tf": 1, "in_doc": true}, {"token": "ganti", "contribution": 4.3768, "idf": 4.5521, "tf": 1, "in_doc": true}, {"token": "menuntut", "contribution": 3.3745, "idf": 3.5096, "tf": 1, "in_doc": true}, {"token": "apakah", "contribution": 0.0, "idf": 0.0, "tf": 0, "in_doc": false}, {"token": "seorang", "contribution": 0.0, "idf": 0.0, "tf": 0, "in_doc": false}, {"token": "investor", "contribution": 0.0, "idf": 0.0, "tf": 0, "in_doc": false}, {"token": "yang", "contribution": 0.0, "idf": 0.0, "tf": 2, "in_doc": true}, {"token": "menanggung", "contribution": 0.0, "idf": 0.0, "tf": 0, "in_doc": false}, {"token": "risiko", "contribution": 0.0, "idf": 0.0, "tf": 0, "in_doc": false}, {"token": "besar", "contribution": 0.0, "idf": 0.0, "tf": 0, "in_doc": false}, {"token": "dan", "contribution": 0.0, "idf": 0.0, "tf": 0, "in_doc": false}, {"token": "biaya", "contribution": 0.0, "idf": 0.0, "tf": 0, "in_doc": false}, {"token": "tinggi", "contribution": 0.0, "idf": 0.0, "tf": 0, "in_doc": false}, {"token": "dalam", "contribution": 0.0, "idf": 0.0, "tf": 0, "in_doc": false}, {"token": "membangun", "contribution": 0.0, "idf": 0.0, "tf": 0, "in_doc": false}, {"token": "infrastruktur", "contribution": 0.0, "idf": 0.0, "tf": 0, "in_doc": false}, {"token": "tol", "contribution": 0.0, "idf": 0.0, "tf": 0, "in_doc": false}, {"token": "dapat", "contribution": 0.0, "idf": 0.0, "tf": 0, "in_doc": false}, {"token": "jika", "contribution": 0.0, "idf": 0.0, "tf": 0, "in_doc": false}], "doc_highlights": [{"start": 141, "end": 146, "token": "jalan", "intensity": 1.0, "score": 8.4234}, {"start": 164, "end": 169, "token": "jalan", "intensity": 1.0, "score": 8.4234}, {"start": 202, "end": 210, "token": "menuntut", "intensity": 0.401, "score": 3.3745}, {"start": 272, "end": 277, "token": "jalan", "intensity": 1.0, "score": 8.4234}, {"start": 368, "end": 373, "token": "ganti", "intensity": 0.52, "score": 4.3768}, {"start": 374, "end": 378, "token": "rugi", "intensity": 0.531, "score": 4.4764}], "query_highlights": [{"start": 100, "end": 105, "token": "jalan", "intensity": 1.0, "score": 8.4234}, {"start": 116, "end": 124, "token": "menuntut", "intensity": 0.401, "score": 3.3745}, {"start": 125, "end": 130, "token": "ganti", "intensity": 0.52, "score": 4.3768}, {"start": 131, "end": 135, "token": "rugi", "intensity": 0.531, "score": 4.4764}]}, {"rank": 9, "doc_id": "1601k", "title": "Pasal 1601k", "bm25_score": 15.367, "is_relevant": false, "per_token": [{"token": "kerja", "contribution": 6.5314, "idf": 4.7509, "tf": 5, "in_doc": true}, {"token": "jika", "contribution": 2.729, "idf": 2.5807, "tf": 3, "in_doc": true}, {"token": "dapat", "contribution": 2.3346, "idf": 2.2077, "tf": 3, "in_doc": true}, {"token": "rugi", "contribution": 2.2855, "idf": 4.6556, "tf": 1, "in_doc": true}, {"token": "ganti", "contribution": 2.2347, "idf": 4.5521, "tf": 1, "in_doc": true}, {"token": "dalam", "contribution": 2.1505, "idf": 1.7403, "tf": 4, "in_doc": true}, {"token": "sebelum", "contribution": 1.8304, "idf": 3.7285, "tf": 1, "in_doc": true}, {"token": "menuntut", "contribution": 1.7229, "idf": 3.5096, "tf": 1, "in_doc": true}, {"token": "dan", "contribution": 1.6484, "idf": 1.5588, "tf": 3, "in_doc": true}, {"token": "apakah", "contribution": 0.0, "idf": 0.0, "tf": 0, "in_doc": false}, {"token": "seorang", "contribution": 0.0, "idf": 0.0, "tf": 0, "in_doc": false}, {"token": "investor", "contribution": 0.0, "idf": 0.0, "tf": 0, "in_doc": false}, {"token": "yang", "contribution": 0.0, "idf": 0.0, "tf": 5, "in_doc": true}, {"token": "menanggung", "contribution": 0.0, "idf": 0.0, "tf": 0, "in_doc": false}, {"token": "risiko", "contribution": 0.0, "idf": 0.0, "tf": 0, "in_doc": false}, {"token": "besar", "contribution": 0.0, "idf": 0.0, "tf": 0, "in_doc": false}, {"token": "biaya", "contribution": 0.0, "idf": 0.0, "tf": 0, "in_doc": false}, {"token": "tinggi", "contribution": 0.0, "idf": 0.0, "tf": 0, "in_doc": false}, {"token": "membangun", "contribution": 0.0, "idf": 0.0, "tf": 0, "in_doc": false}, {"token": "infrastruktur", "contribution": 0.0, "idf": 0.0, "tf": 0, "in_doc": false}], "doc_highlights": [{"start": 13, "end": 17, "token": "jika", "intensity": 0.418, "score": 2.729}, {"start": 34, "end": 39, "token": "kerja", "intensity": 1.0, "score": 6.5314}, {"start": 226, "end": 233, "token": "sebelum", "intensity": 0.28, "score": 1.8304}, {"start": 329, "end": 334, "token": "dapat", "intensity": 0.357, "score": 2.3346}, {"start": 375, "end": 379, "token": "jika", "intensity": 0.418, "score": 2.729}, {"start": 456, "end": 461, "token": "dapat", "intensity": 0.357, "score": 2.3346}, {"start": 479, "end": 484, "token": "dalam", "intensity": 0.329, "score": 2.1505}, {"start": 541, "end": 546, "token": "dapat", "intensity": 0.357, "score": 2.3346}, {"start": 547, "end": 555, "token": "menuntut", "intensity": 0.264, "score": 1.7229}, {"start": 594, "end": 599, "token": "kerja", "intensity": 1.0, "score": 6.5314}, {"start": 715, "end": 718, "token": "dan", "intensity": 0.252, "score": 1.6484}, {"start": 755, "end": 759, "token": "jika", "intensity": 0.418, "score": 2.729}, {"start": 860, "end": 865, "token": "dalam", "intensity": 0.329, "score": 2.1505}, {"start": 894, "end": 897, "token": "dan", "intensity": 0.252, "score": 1.6484}, {"start": 930, "end": 935, "token": "kerja", "intensity": 1.0, "score": 6.5314}, {"start": 1027, "end": 1032, "token": "dalam", "intensity": 0.329, "score": 2.1505}, {"start": 1109, "end": 1114, "token": "kerja", "intensity": 1.0, "score": 6.5314}, {"start": 1130, "end": 1133, "token": "dan", "intensity": 0.252, "score": 1.6484}, {"start": 1158, "end": 1163, "token": "ganti", "intensity": 0.342, "score": 2.2347}, {"start": 1164, "end": 1168, "token": "rugi", "intensity": 0.35, "score": 2.2855}, {"start": 1210, "end": 1215, "token": "dalam", "intensity": 0.329, "score": 2.1505}, {"start": 1235, "end": 1240, "token": "kerja", "intensity": 1.0, "score": 6.5314}], "query_highlights": [{"start": 53, "end": 56, "token": "dan", "intensity": 0.252, "score": 1.6484}, {"start": 70, "end": 75, "token": "dalam", "intensity": 0.329, "score": 2.1505}, {"start": 110, "end": 115, "token": "dapat", "intensity": 0.357, "score": 2.3346}, {"start": 116, "end": 124, "token": "menuntut", "intensity": 0.264, "score": 1.7229}, {"start": 125, "end": 130, "token": "ganti", "intensity": 0.342, "score": 2.2347}, {"start": 131, "end": 135, "token": "rugi", "intensity": 0.35, "score": 2.2855}, {"start": 136, "end": 140, "token": "jika", "intensity": 0.418, "score": 2.729}, {"start": 178, "end": 185, "token": "sebelum", "intensity": 0.28, "score": 1.8304}, {"start": 191, "end": 196, "token": "kerja", "intensity": 1.0, "score": 6.5314}]}, {"rank": 10, "doc_id": "669", "title": "Pasal 669", "bm25_score": 15.1351, "is_relevant": false, "per_token": [{"token": "jalan", "contribution": 6.8632, "idf": 5.1664, "tf": 1, "in_doc": true}, {"token": "rugi", "contribution": 6.1846, "idf": 4.6556, "tf": 1, "in_doc": true}, {"token": "ganti", "contribution": 6.0471, "idf": 4.5521, "tf": 1, "in_doc": true}, {"token": "apakah", "contribution": 0.0, "idf": 0.0, "tf": 0, "in_doc": false}, {"token": "seorang", "contribution": 0.0, "idf": 0.0, "tf": 0, "in_doc": false}, {"token": "investor", "contribution": 0.0, "idf": 0.0, "tf": 0, "in_doc": false}, {"token": "yang", "contribution": 0.0, "idf": 0.0, "tf": 0, "in_doc": false}, {"token": "menanggung", "contribution": 0.0, "idf": 0.0, "tf": 0, "in_doc": false}, {"token": "risiko", "contribution": 0.0, "idf": 0.0, "tf": 0, "in_doc": false}, {"token": "besar", "contribution": 0.0, "idf": 0.0, "tf": 0, "in_doc": false}, {"token": "dan", "contribution": 0.0, "idf": 0.0, "tf": 0, "in_doc": false}, {"token": "biaya", "contribution": 0.0, "idf": 0.0, "tf": 0, "in_doc": false}, {"token": "tinggi", "contribution": 0.0, "idf": 0.0, "tf": 0, "in_doc": false}, {"token": "dalam", "contribution": 0.0, "idf": 0.0, "tf": 0, "in_doc": false}, {"token": "membangun", "contribution": 0.0, "idf": 0.0, "tf": 0, "in_doc": false}, {"token": "infrastruktur", "contribution": 0.0, "idf": 0.0, "tf": 0, "in_doc": false}, {"token": "tol", "contribution": 0.0, "idf": 0.0, "tf": 0, "in_doc": false}, {"token": "dapat", "contribution": 0.0, "idf": 0.0, "tf": 0, "in_doc": false}, {"token": "menuntut", "contribution": 0.0, "idf": 0.0, "tf": 0, "in_doc": false}, {"token": "jika", "contribution": 0.0, "idf": 0.0, "tf": 0, "in_doc": false}], "doc_highlights": [{"start": 25, "end": 30, "token": "ganti", "intensity": 0.881, "score": 6.0471}, {"start": 31, "end": 35, "token": "rugi", "intensity": 0.901, "score": 6.1846}, {"start": 103, "end": 108, "token": "jalan", "intensity": 1.0, "score": 6.8632}], "query_highlights": [{"start": 100, "end": 105, "token": "jalan", "intensity": 1.0, "score": 6.8632}, {"start": 125, "end": 130, "token": "ganti", "intensity": 0.881, "score": 6.0471}, {"start": 131, "end": 135, "token": "rugi", "intensity": 0.901, "score": 6.1846}]}, {"rank": 11, "doc_id": "1603l", "title": "Pasal 1603l", "bm25_score": 15.1308, "is_relevant": false, "per_token": [{"token": "masa", "contribution": 11.002, "idf": 6.717, "tf": 3, "in_doc": true}, {"token": "kerja", "contribution": 4.6054, "idf": 4.7509, "tf": 1, "in_doc": true}, {"token": "jika", "contribution": 2.5017, "idf": 2.5807, "tf": 1, "in_doc": true}, {"token": "dan", "contribution": 1.5111, "idf": 1.5588, "tf": 1, "in_doc": true}, {"token": "apakah", "contribution": 0.0, "idf": 0.0, "tf": 0, "in_doc": false}, {"token": "seorang", "contribution": 0.0, "idf": 0.0, "tf": 0, "in_doc": false}, {"token": "investor", "contribution": 0.0, "idf": 0.0, "tf": 0, "in_doc": false}, {"token": "yang", "contribution": 0.0, "idf": 0.0, "tf": 4, "in_doc": true}, {"token": "menanggung", "contribution": 0.0, "idf": 0.0, "tf": 0, "in_doc": false}, {"token": "risiko", "contribution": 0.0, "idf": 0.0, "tf": 0, "in_doc": false}, {"token": "besar", "contribution": 0.0, "idf": 0.0, "tf": 0, "in_doc": false}, {"token": "biaya", "contribution": 0.0, "idf": 0.0, "tf": 0, "in_doc": false}, {"token": "tinggi", "contribution": 0.0, "idf": 0.0, "tf": 0, "in_doc": false}, {"token": "dalam", "contribution": 0.0, "idf": 0.0, "tf": 0, "in_doc": false}, {"token": "membangun", "contribution": 0.0, "idf": 0.0, "tf": 0, "in_doc": false}, {"token": "infrastruktur", "contribution": 0.0, "idf": 0.0, "tf": 0, "in_doc": false}, {"token": "jalan", "contribution": 0.0, "idf": 0.0, "tf": 0, "in_doc": false}, {"token": "tol", "contribution": 0.0, "idf": 0.0, "tf": 0, "in_doc": false}, {"token": "dapat", "contribution": 0.0, "idf": 0.0, "tf": 0, "in_doc": false}, {"token": "menuntut", "contribution": 0.0, "idf": 0.0, "tf": 0, "in_doc": false}], "doc_highlights": [{"start": 13, "end": 17, "token": "jika", "intensity": 0.227, "score": 2.5017}, {"start": 38, "end": 42, "token": "masa", "intensity": 1.0, "score": 11.002}, {"start": 117, "end": 122, "token": "kerja", "intensity": 0.419, "score": 4.6054}, {"start": 184, "end": 188, "token": "masa", "intensity": 1.0, "score": 11.002}, {"start": 278, "end": 281, "token": "dan", "intensity": 0.137, "score": 1.5111}, {"start": 320, "end": 324, "token": "masa", "intensity": 1.0, "score": 11.002}], "query_highlights": [{"start": 53, "end": 56, "token": "dan", "intensity": 0.137, "score": 1.5111}, {"start": 136, "end": 140, "token": "jika", "intensity": 0.227, "score": 2.5017}, {"start": 186, "end": 190, "token": "masa", "intensity": 1.0, "score": 11.002}, {"start": 191, "end": 196, "token": "kerja", "intensity": 0.419, "score": 4.6054}]}, {"rank": 12, "doc_id": "1246", "title": "Pasal 1246", "bm25_score": 14.7673, "is_relevant": true, "per_token": [{"token": "rugi", "contribution": 5.6172, "idf": 4.6556, "tf": 1, "in_doc": true}, {"token": "ganti", "contribution": 5.4923, "idf": 4.5521, "tf": 1, "in_doc": true}, {"token": "biaya", "contribution": 4.4067, "idf": 3.6523, "tf": 1, "in_doc": true}, {"token": "dan", "contribution": 2.871, "idf": 1.5588, "tf": 3, "in_doc": true}, {"token": "dapat", "contribution": 2.6637, "idf": 2.2077, "tf": 1, "in_doc": true}, {"token": "apakah", "contribution": 0.0, "idf": 0.0, "tf": 0, "in_doc": false}, {"token": "seorang", "contribution": 0.0, "idf": 0.0, "tf": 0, "in_doc": false}, {"token": "investor", "contribution": 0.0, "idf": 0.0, "tf": 0, "in_doc": false}, {"token": "yang", "contribution": 0.0, "idf": 0.0, "tf": 4, "in_doc": true}, {"token": "menanggung", "contribution": 0.0, "idf": 0.0, "tf": 0, "in_doc": false}, {"token": "risiko", "contribution": 0.0, "idf": 0.0, "tf": 0, "in_doc": false}, {"token": "besar", "contribution": 0.0, "idf": 0.0, "tf": 0, "in_doc": false}, {"token": "tinggi", "contribution": 0.0, "idf": 0.0, "tf": 0, "in_doc": false}, {"token": "dalam", "contribution": 0.0, "idf": 0.0, "tf": 0, "in_doc": false}, {"token": "membangun", "contribution": 0.0, "idf": 0.0, "tf": 0, "in_doc": false}, {"token": "infrastruktur", "contribution": 0.0, "idf": 0.0, "tf": 0, "in_doc": false}, {"token": "jalan", "contribution": 0.0, "idf": 0.0, "tf": 0, "in_doc": false}, {"token": "tol", "contribution": 0.0, "idf": 0.0, "tf": 0, "in_doc": false}, {"token": "menuntut", "contribution": 0.0, "idf": 0.0, "tf": 0, "in_doc": false}, {"token": "jika", "contribution": 0.0, "idf": 0.0, "tf": 0, "in_doc": false}], "doc_highlights": [{"start": 12, "end": 17, "token": "biaya", "intensity": 0.785, "score": 4.4067}, {"start": 19, "end": 24, "token": "ganti", "intensity": 0.978, "score": 5.4923}, {"start": 25, "end": 29, "token": "rugi", "intensity": 1.0, "score": 5.6172}, {"start": 30, "end": 33, "token": "dan", "intensity": 0.511, "score": 2.871}, {"start": 116, "end": 119, "token": "dan", "intensity": 0.511, "score": 2.871}, {"start": 145, "end": 150, "token": "dapat", "intensity": 0.474, "score": 2.6637}, {"start": 195, "end": 198, "token": "dan", "intensity": 0.511, "score": 2.871}], "query_highlights": [{"start": 53, "end": 56, "token": "dan", "intensity": 0.511, "score": 2.871}, {"start": 57, "end": 62, "token": "biaya", "intensity": 0.785, "score": 4.4067}, {"start": 110, "end": 115, "token": "dapat", "intensity": 0.474, "score": 2.6637}, {"start": 125, "end": 130, "token": "ganti", "intensity": 0.978, "score": 5.4923}, {"start": 131, "end": 135, "token": "rugi", "intensity": 1.0, "score": 5.6172}]}, {"rank": 13, "doc_id": "1576", "title": "Pasal 1576", "bm25_score": 14.6685, "is_relevant": false, "per_token": [{"token": "rugi", "contribution": 6.4282, "idf": 4.6556, "tf": 2, "in_doc": true}, {"token": "ganti", "contribution": 6.2853, "idf": 4.5521, "tf": 2, "in_doc": true}, {"token": "jika", "contribution": 3.5633, "idf": 2.5807, "tf": 2, "in_doc": true}, {"token": "menuntut", "contribution": 3.3474, "idf": 3.5096, "tf": 1, "in_doc": true}, {"token": "apakah", "contribution": 0.0, "idf": 0.0, "tf": 0, "in_doc": false}, {"token": "seorang", "contribution": 0.0, "idf": 0.0, "tf": 0, "in_doc": false}, {"token": "investor", "contribution": 0.0, "idf": 0.0, "tf": 0, "in_doc": false}, {"token": "yang", "contribution": 0.0, "idf": 0.0, "tf": 5, "in_doc": true}, {"token": "menanggung", "contribution": 0.0, "idf": 0.0, "tf": 0, "in_doc": false}, {"token": "risiko", "contribution": 0.0, "idf": 0.0, "tf": 0, "in_doc": false}, {"token": "besar", "contribution": 0.0, "idf": 0.0, "tf": 0, "in_doc": false}, {"token": "dan", "contribution": 0.0, "idf": 0.0, "tf": 0, "in_doc": false}, {"token": "biaya", "contribution": 0.0, "idf": 0.0, "tf": 0, "in_doc": false}, {"token": "tinggi", "contribution": 0.0, "idf": 0.0, "tf": 0, "in_doc": false}, {"token": "dalam", "contribution": 0.0, "idf": 0.0, "tf": 0, "in_doc": false}, {"token": "membangun", "contribution": 0.0, "idf": 0.0, "tf": 0, "in_doc": false}, {"token": "infrastruktur", "contribution": 0.0, "idf": 0.0, "tf": 0, "in_doc": false}, {"token": "jalan", "contribution": 0.0, "idf": 0.0, "tf": 0, "in_doc": false}, {"token": "tol", "contribution": 0.0, "idf": 0.0, "tf": 0, "in_doc": false}, {"token": "dapat", "contribution": 0.0, "idf": 0.0, "tf": 0, "in_doc": false}], "doc_highlights": [{"start": 157, "end": 161, "token": "jika", "intensity": 0.554, "score": 3.5633}, {"start": 214, "end": 222, "token": "menuntut", "intensity": 0.521, "score": 3.3474}, {"start": 223, "end": 228, "token": "ganti", "intensity": 0.978, "score": 6.2853}, {"start": 229, "end": 233, "token": "rugi", "intensity": 1.0, "score": 6.4282}, {"start": 285, "end": 289, "token": "jika", "intensity": 0.554, "score": 3.5633}, {"start": 374, "end": 379, "token": "ganti", "intensity": 0.978, "score": 6.2853}, {"start": 380, "end": 384, "token": "rugi", "intensity": 1.0, "score": 6.4282}], "query_highlights": [{"start": 116, "end": 124, "token": "menuntut", "intensity": 0.521, "score": 3.3474}, {"start": 125, "end": 130, "token": "ganti", "intensity": 0.978, "score": 6.2853}, {"start": 131, "end": 135, "token": "rugi", "intensity": 1.0, "score": 6.4282}, {"start": 136, "end": 140, "token": "jika", "intensity": 0.554, "score": 3.5633}]}, {"rank": 14, "doc_id": "1602c", "title": "Pasal 1602c", "bm25_score": 14.451, "is_relevant": false, "per_token": [{"token": "pemerintah", "contribution": 3.0905, "idf": 5.1366, "tf": 2, "in_doc": true}, {"token": "kerja", "contribution": 2.8584, "idf": 4.7509, "tf": 2, "in_doc": true}, {"token": "rugi", "contribution": 2.8011, "idf": 4.6556, "tf": 2, "in_doc": true}, {"token": "ganti", "contribution": 2.7388, "idf": 4.5521, "tf": 2, "in_doc": true}, {"token": "dalam", "contribution": 1.9233, "idf": 1.7403, "tf": 5, "in_doc": true}, {"token": "dapat", "contribution": 1.7785, "idf": 2.2077, "tf": 3, "in_doc": true}, {"token": "seorang", "contribution": 1.7724, "idf": 2.9459, "tf": 2, "in_doc": true}, {"token": "dan", "contribution": 1.2557, "idf": 1.5588, "tf": 3, "in_doc": true}, {"token": "biaya", "contribution": 1.249, "idf": 3.6523, "tf": 1, "in_doc": true}, {"token": "menuntut", "contribution": 1.2002, "idf": 3.5096, "tf": 1, "in_doc": true}, {"token": "jika", "contribution": 0.8826, "idf": 2.5807, "tf": 1, "in_doc": true}, {"token": "apakah", "contribution": 0.0, "idf": 0.0, "tf": 0, "in_doc": false}, {"token": "investor", "contribution": 0.0, "idf": 0.0, "tf": 0, "in_doc": false}, {"token": "yang", "contribution": 0.0, "idf": 0.0, "tf": 9, "in_doc": true}, {"token": "menanggung", "contribution": 0.0, "idf": 0.0, "tf": 0, "in_doc": false}, {"token": "risiko", "contribution": 0.0, "idf": 0.0, "tf": 0, "in_doc": false}, {"token": "besar", "contribution": 0.0, "idf": 0.0, "tf": 0, "in_doc": false}, {"token": "tinggi", "contribution": 0.0, "idf": 0.0, "tf": 0, "in_doc": false}, {"token": "membangun", "contribution": 0.0, "idf": 0.0, "tf": 0, "in_doc": false}, {"token": "infrastruktur", "contribution": 0.0, "idf": 0.0, "tf": 0, "in_doc": false}], "doc_highlights": [{"start": 52, "end": 55, "token": "dan", "intensity": 0.406, "score": 1.2557}, {"start": 439, "end": 444, "token": "dalam", "intensity": 0.622, "score": 1.9233}, {"start": 488, "end": 493, "token": "ganti", "intensity": 0.886, "score": 2.7388}, {"start": 494, "end": 498, "token": "rugi", "intensity": 0.906, "score": 2.8011}, {"start": 681, "end": 686, "token": "kerja", "intensity": 0.925, "score": 2.8584}, {"start": 749, "end": 754, "token": "ganti", "intensity": 0.886, "score": 2.7388}, {"start": 755, "end": 759, "token": "rugi", "intensity": 0.906, "score": 2.8011}, {"start": 784, "end": 792, "token": "menuntut", "intensity": 0.388, "score": 1.2002}, {"start": 936, "end": 946, "token": "pemerintah", "intensity": 1.0, "score": 3.0905}, {"start": 978, "end": 981, "token": "dan", "intensity": 0.406, "score": 1.2557}, {"start": 988, "end": 993, "token": "dapat", "intensity": 0.575, "score": 1.7785}, {"start": 1018, "end": 1023, "token": "kerja", "intensity": 0.925, "score": 2.8584}, {"start": 1134, "end": 1139, "token": "dalam", "intensity": 0.622, "score": 1.9233}, {"start": 1250, "end": 1253, "token": "dan", "intensity": 0.406, "score": 1.2557}, {"start": 1271, "end": 1278, "token": "seorang", "intensity": 0.573, "score": 1.7724}, {"start": 1304, "end": 1311, "token": "seorang", "intensity": 0.573, "score": 1.7724}, {"start": 1329, "end": 1334, "token": "dalam", "intensity": 0.622, "score": 1.9233}, {"start": 1354, "end": 1359, "token": "dalam", "intensity": 0.622, "score": 1.9233}, {"start": 1402, "end": 1407, "token": "dalam", "intensity": 0.622, "score": 1.9233}, {"start": 1478, "end": 1488, "token": "pemerintah", "intensity": 1.0, "score": 3.0905}, {"start": 1524, "end": 1528, "token": "jika", "intensity": 0.286, "score": 0.8826}, {"start": 1722, "end": 1727, "token": "dapat", "intensity": 0.575, "score": 1.7785}, {"start": 1843, "end": 1848, "token": "biaya", "intensity": 0.404, "score": 1.249}, {"start": 1860, "end": 1865, "token": "dapat", "intensity": 0.575, "score": 1.7785}], "query_highlights": [{"start": 7, "end": 14, "token": "seorang", "intensity": 0.573, "score": 1.7724}, {"start": 53, "end": 56, "token": "dan", "intensity": 0.406, "score": 1.2557}, {"start": 57, "end": 62, "token": "biaya", "intensity": 0.404, "score": 1.249}, {"start": 70, "end": 75, "token": "dalam", "intensity": 0.622, "score": 1.9233}, {"start": 110, "end": 115, "token": "dapat", "intensity": 0.575, "score": 1.7785}, {"start": 116, "end": 124, "token": "menuntut", "intensity": 0.388, "score": 1.2002}, {"start": 125, "end": 130, "token": "ganti", "intensity": 0.886, "score": 2.7388}, {"start": 131, "end": 135, "token": "rugi", "intensity": 0.906, "score": 2.8011}, {"start": 136, "end": 140, "token": "jika", "intensity": 0.286, "score": 0.8826}, {"start": 141, "end": 151, "token": "pemerintah", "intensity": 1.0, "score": 3.0905}, {"start": 191, "end": 196, "token": "kerja", "intensity": 0.925, "score": 2.8584}]}, {"rank": 15, "doc_id": "1379", "title": "Pasal 1379", "bm25_score": 14.4436, "is_relevant": false, "per_token": [{"token": "rugi", "contribution": 6.2548, "idf": 4.6556, "tf": 1, "in_doc": true}, {"token": "ganti", "contribution": 6.1157, "idf": 4.5521, "tf": 1, "in_doc": true}, {"token": "menuntut", "contribution": 4.7152, "idf": 3.5096, "tf": 1, "in_doc": true}, {"token": "dalam", "contribution": 2.3381, "idf": 1.7403, "tf": 1, "in_doc": true}, {"token": "apakah", "contribution": 0.0, "idf": 0.0, "tf": 0, "in_doc": false}, {"token": "seorang", "contribution": 0.0, "idf": 0.0, "tf": 0, "in_doc": false}, {"token": "investor", "contribution": 0.0, "idf": 0.0, "tf": 0, "in_doc": false}, {"token": "yang", "contribution": 0.0, "idf": 0.0, "tf": 2, "in_doc": true}, {"token": "menanggung", "contribution": 0.0, "idf": 0.0, "tf": 0, "in_doc": false}, {"token": "risiko", "contribution": 0.0, "idf": 0.0, "tf": 0, "in_doc": false}, {"token": "besar", "contribution": 0.0, "idf": 0.0, "tf": 0, "in_doc": false}, {"token": "dan", "contribution": 0.0, "idf": 0.0, "tf": 0, "in_doc": false}, {"token": "biaya", "contribution": 0.0, "idf": 0.0, "tf": 0, "in_doc": false}, {"token": "tinggi", "contribution": 0.0, "idf": 0.0, "tf": 0, "in_doc": false}, {"token": "membangun", "contribution": 0.0, "idf": 0.0, "tf": 0, "in_doc": false}, {"token": "infrastruktur", "contribution": 0.0, "idf": 0.0, "tf": 0, "in_doc": false}, {"token": "jalan", "contribution": 0.0, "idf": 0.0, "tf": 0, "in_doc": false}, {"token": "tol", "contribution": 0.0, "idf": 0.0, "tf": 0, "in_doc": false}, {"token": "dapat", "contribution": 0.0, "idf": 0.0, "tf": 0, "in_doc": false}, {"token": "jika", "contribution": 0.0, "idf": 0.0, "tf": 0, "in_doc": false}], "doc_highlights": [{"start": 22, "end": 30, "token": "menuntut", "intensity": 0.754, "score": 4.7152}, {"start": 31, "end": 36, "token": "ganti", "intensity": 0.978, "score": 6.1157}, {"start": 37, "end": 41, "token": "rugi", "intensity": 1.0, "score": 6.2548}, {"start": 65, "end": 70, "token": "dalam", "intensity": 0.374, "score": 2.3381}], "query_highlights": [{"start": 70, "end": 75, "token": "dalam", "intensity": 0.374, "score": 2.3381}, {"start": 116, "end": 124, "token": "menuntut", "intensity": 0.754, "score": 4.7152}, {"start": 125, "end": 130, "token": "ganti", "intensity": 0.978, "score": 6.1157}, {"start": 131, "end": 135, "token": "rugi", "intensity": 1.0, "score": 6.2548}]}, {"rank": 16, "doc_id": "1601x", "title": "Pasal 1601x", "bm25_score": 14.2938, "is_relevant": false, "per_token": [{"token": "kerja", "contribution": 3.7062, "idf": 4.7509, "tf": 2, "in_doc": true}, {"token": "rugi", "contribution": 3.6319, "idf": 4.6556, "tf": 2, "in_doc": true}, {"token": "ganti", "contribution": 3.5511, "idf": 4.5521, "tf": 2, "in_doc": true}, {"token": "jika", "contribution": 3.4284, "idf": 2.5807, "tf": 5, "in_doc": true}, {"token": "membatalkan", "contribution": 2.784, "idf": 6.0239, "tf": 1, "in_doc": true}, {"token": "dalam", "contribution": 1.7616, "idf": 1.7403, "tf": 3, "in_doc": true}, {"token": "dapat", "contribution": 1.0203, "idf": 2.2077, "tf": 1, "in_doc": true}, {"token": "dan", "contribution": 0.7204, "idf": 1.5588, "tf": 1, "in_doc": true}, {"token": "apakah", "contribution": 0.0, "idf": 0.0, "tf": 0, "in_doc": false}, {"token": "seorang", "contribution": 0.0, "idf": 0.0, "tf": 0, "in_doc": false}, {"token": "investor", "contribution": 0.0, "idf": 0.0, "tf": 0, "in_doc": false}, {"token": "yang", "contribution": 0.0, "idf": 0.0, "tf": 9, "in_doc": true}, {"token": "menanggung", "contribution": 0.0, "idf": 0.0, "tf": 0, "in_doc": false}, {"token": "risiko", "contribution": 0.0, "idf": 0.0, "tf": 0, "in_doc": false}, {"token": "besar", "contribution": 0.0, "idf": 0.0, "tf": 0, "in_doc": false}, {"token": "biaya", "contribution": 0.0, "idf": 0.0, "tf": 0, "in_doc": false}, {"token": "tinggi", "contribution": 0.0, "idf": 0.0, "tf": 0, "in_doc": false}, {"token": "membangun", "contribution": 0.0, "idf": 0.0, "tf": 0, "in_doc": false}, {"token": "infrastruktur", "contribution": 0.0, "idf": 0.0, "tf": 0, "in_doc": false}, {"token": "jalan", "contribution": 0.0, "idf": 0.0, "tf": 0, "in_doc": false}], "doc_highlights": [{"start": 91, "end": 96, "token": "kerja", "intensity": 1.0, "score": 3.7062}, {"start": 173, "end": 177, "token": "jika", "intensity": 0.925, "score": 3.4284}, {"start": 185, "end": 190, "token": "dalam", "intensity": 0.475, "score": 1.7616}, {"start": 352, "end": 357, "token": "dalam", "intensity": 0.475, "score": 1.7616}, {"start": 390, "end": 401, "token": "membatalkan", "intensity": 0.751, "score": 2.784}, {"start": 593, "end": 596, "token": "dan", "intensity": 0.194, "score": 0.7204}, {"start": 624, "end": 629, "token": "dalam", "intensity": 0.475, "score": 1.7616}, {"start": 660, "end": 665, "token": "dapat", "intensity": 0.275, "score": 1.0203}, {"start": 684, "end": 688, "token": "jika", "intensity": 0.925, "score": 3.4284}, {"start": 712, "end": 717, "token": "kerja", "intensity": 1.0, "score": 3.7062}, {"start": 746, "end": 750, "token": "jika", "intensity": 0.925, "score": 3.4284}, {"start": 905, "end": 909, "token": "jika", "intensity": 0.925, "score": 3.4284}, {"start": 1106, "end": 1110, "token": "jika", "intensity": 0.925, "score": 3.4284}, {"start": 1163, "end": 1168, "token": "ganti", "intensity": 0.958, "score": 3.5511}, {"start": 1169, "end": 1173, "token": "rugi", "intensity": 0.98, "score": 3.6319}, {"start": 1355, "end": 1360, "token": "ganti", "intensity": 0.958, "score": 3.5511}, {"start": 1361, "end": 1365, "token": "rugi", "intensity": 0.98, "score": 3.6319}], "query_highlights": [{"start": 53, "end": 56, "token": "dan", "intensity": 0.194, "score": 0.7204}, {"start": 70, "end": 75, "token": "dalam", "intensity": 0.475, "score": 1.7616}, {"start": 110, "end": 115, "token": "dapat", "intensity": 0.275, "score": 1.0203}, {"start": 125, "end": 130, "token": "ganti", "intensity": 0.958, "score": 3.5511}, {"start": 131, "end": 135, "token": "rugi", "intensity": 0.98, "score": 3.6319}, {"start": 136, "end": 140, "token": "jika", "intensity": 0.925, "score": 3.4284}, {"start": 152, "end": 163, "token": "membatalkan", "intensity": 0.751, "score": 2.784}, {"start": 191, "end": 196, "token": "kerja", "intensity": 1.0, "score": 3.7062}]}, {"rank": 17, "doc_id": "58", "title": "Pasal 58", "bm25_score": 14.2168, "is_relevant": false, "per_token": [{"token": "menuntut", "contribution": 4.6712, "idf": 3.5096, "tf": 3, "in_doc": true}, {"token": "biaya", "contribution": 3.9398, "idf": 3.6523, "tf": 2, "in_doc": true}, {"token": "rugi", "contribution": 3.2019, "idf": 4.6556, "tf": 1, "in_doc": true}, {"token": "ganti", "contribution": 3.1306, "idf": 4.5521, "tf": 1, "in_doc": true}, {"token": "dan", "contribution": 2.0747, "idf": 1.5588, "tf": 3, "in_doc": true}, {"token": "dalam", "contribution": 1.8773, "idf": 1.7403, "tf": 2, "in_doc": true}, {"token": "jika", "contribution": 1.7749, "idf": 2.5807, "tf": 1, "in_doc": true}, {"token": "dapat", "contribution": 1.5184, "idf": 2.2077, "tf": 1, "in_doc": true}, {"token": "apakah", "contribution": 0.0, "idf": 0.0, "tf": 0, "in_doc": false}, {"token": "seorang", "contribution": 0.0, "idf": 0.0, "tf": 0, "in_doc": false}, {"token": "investor", "contribution": 0.0, "idf": 0.0, "tf": 0, "in_doc": false}, {"token": "yang", "contribution": 0.0, "idf": 0.0, "tf": 2, "in_doc": true}, {"token": "menanggung", "contribution": 0.0, "idf": 0.0, "tf": 0, "in_doc": false}, {"token": "risiko", "contribution": 0.0, "idf": 0.0, "tf": 0, "in_doc": false}, {"token": "besar", "contribution": 0.0, "idf": 0.0, "tf": 0, "in_doc": false}, {"token": "tinggi", "contribution": 0.0, "idf": 0.0, "tf": 0, "in_doc": false}, {"token": "membangun", "contribution": 0.0, "idf": 0.0, "tf": 0, "in_doc": false}, {"token": "infrastruktur", "contribution": 0.0, "idf": 0.0, "tf": 0, "in_doc": false}, {"token": "jalan", "contribution": 0.0, "idf": 0.0, "tf": 0, "in_doc": false}, {"token": "tol", "contribution": 0.0, "idf": 0.0, "tf": 0, "in_doc": false}], "doc_highlights": [{"start": 50, "end": 58, "token": "menuntut", "intensity": 1.0, "score": 4.6712}, {"start": 133, "end": 141, "token": "menuntut", "intensity": 1.0, "score": 4.6712}, {"start": 154, "end": 159, "token": "biaya", "intensity": 0.843, "score": 3.9398}, {"start": 170, "end": 173, "token": "dan", "intensity": 0.444, "score": 2.0747}, {"start": 241, "end": 246, "token": "ganti", "intensity": 0.67, "score": 3.1306}, {"start": 247, "end": 251, "token": "rugi", "intensity": 0.685, "score": 3.2019}, {"start": 252, "end": 257, "token": "dalam", "intensity": 0.402, "score": 1.8773}, {"start": 293, "end": 297, "token": "jika", "intensity": 0.38, "score": 1.7749}, {"start": 373, "end": 378, "token": "dapat", "intensity": 0.325, "score": 1.5184}, {"start": 399, "end": 407, "token": "menuntut", "intensity": 1.0, "score": 4.6712}, {"start": 420, "end": 425, "token": "biaya", "intensity": 0.843, "score": 3.9398}, {"start": 436, "end": 439, "token": "dan", "intensity": 0.444, "score": 2.0747}, {"start": 549, "end": 552, "token": "dan", "intensity": 0.444, "score": 2.0747}, {"start": 580, "end": 585, "token": "dalam", "intensity": 0.402, "score": 1.8773}], "query_highlights": [{"start": 53, "end": 56, "token": "dan", "intensity": 0.444, "score": 2.0747}, {"start": 57, "end": 62, "token": "biaya", "intensity": 0.843, "score": 3.9398}, {"start": 70, "end": 75, "token": "dalam", "intensity": 0.402, "score": 1.8773}, {"start": 110, "end": 115, "token": "dapat", "intensity": 0.325, "score": 1.5184}, {"start": 116, "end": 124, "token": "menuntut", "intensity": 1.0, "score": 4.6712}, {"start": 125, "end": 130, "token": "ganti", "intensity": 0.67, "score": 3.1306}, {"start": 131, "end": 135, "token": "rugi", "intensity": 0.685, "score": 3.2019}, {"start": 136, "end": 140, "token": "jika", "intensity": 0.38, "score": 1.7749}]}, {"rank": 18, "doc_id": "1603n", "title": "Pasal 1603n", "bm25_score": 13.9748, "is_relevant": false, "per_token": [{"token": "kerja", "contribution": 8.0294, "idf": 4.7509, "tf": 4, "in_doc": true}, {"token": "rugi", "contribution": 3.9902, "idf": 4.6556, "tf": 1, "in_doc": true}, {"token": "ganti", "contribution": 3.9014, "idf": 4.5521, "tf": 1, "in_doc": true}, {"token": "dapat", "contribution": 1.8922, "idf": 2.2077, "tf": 1, "in_doc": true}, {"token": "dan", "contribution": 1.336, "idf": 1.5588, "tf": 1, "in_doc": true}, {"token": "apakah", "contribution": 0.0, "idf": 0.0, "tf": 0, "in_doc": false}, {"token": "seorang", "contribution": 0.0, "idf": 0.0, "tf": 0, "in_doc": false}, {"token": "investor", "contribution": 0.0, "idf": 0.0, "tf": 0, "in_doc": false}, {"token": "yang", "contribution": 0.0, "idf": 0.0, "tf": 3, "in_doc": true}, {"token": "menanggung", "contribution": 0.0, "idf": 0.0, "tf": 0, "in_doc": false}, {"token": "risiko", "contribution": 0.0, "idf": 0.0, "tf": 0, "in_doc": false}, {"token": "besar", "contribution": 0.0, "idf": 0.0, "tf": 0, "in_doc": false}, {"token": "biaya", "contribution": 0.0, "idf": 0.0, "tf": 0, "in_doc": false}, {"token": "tinggi", "contribution": 0.0, "idf": 0.0, "tf": 0, "in_doc": false}, {"token": "dalam", "contribution": 0.0, "idf": 0.0, "tf": 0, "in_doc": false}, {"token": "membangun", "contribution": 0.0, "idf": 0.0, "tf": 0, "in_doc": false}, {"token": "infrastruktur", "contribution": 0.0, "idf": 0.0, "tf": 0, "in_doc": false}, {"token": "jalan", "contribution": 0.0, "idf": 0.0, "tf": 0, "in_doc": false}, {"token": "tol", "contribution": 0.0, "idf": 0.0, "tf": 0, "in_doc": false}, {"token": "menuntut", "contribution": 0.0, "idf": 0.0, "tf": 0, "in_doc": false}], "doc_highlights": [{"start": 33, "end": 38, "token": "dapat", "intensity": 0.236, "score": 1.8922}, {"start": 59, "end": 64, "token": "kerja", "intensity": 1.0, "score": 8.0294}, {"start": 104, "end": 109, "token": "kerja", "intensity": 1.0, "score": 8.0294}, {"start": 199, "end": 204, "token": "kerja", "intensity": 1.0, "score": 8.0294}, {"start": 350, "end": 355, "token": "ganti", "intensity": 0.486, "score": 3.9014}, {"start": 356, "end": 360, "token": "rugi", "intensity": 0.497, "score": 3.9902}, {"start": 441, "end": 446, "token": "kerja", "intensity": 1.0, "score": 8.0294}, {"start": 475, "end": 478, "token": "dan", "intensity": 0.166, "score": 1.336}], "query_highlights": [{"start": 53, "end": 56, "token": "dan", "intensity": 0.166, "score": 1.336}, {"start": 110, "end": 115, "token": "dapat", "intensity": 0.236, "score": 1.8922}, {"start": 125, "end": 130, "token": "ganti", "intensity": 0.486, "score": 3.9014}, {"start": 131, "end": 135, "token": "rugi", "intensity": 0.497, "score": 3.9902}, {"start": 191, "end": 196, "token": "kerja", "intensity": 1.0, "score": 8.0294}]}, {"rank": 19, "doc_id": "1502", "title": "Pasal 1502", "bm25_score": 13.8678, "is_relevant": false, "per_token": [{"token": "rugi", "contribution": 4.6659, "idf": 4.6556, "tf": 1, "in_doc": true}, {"token": "ganti", "contribution": 4.5621, "idf": 4.5521, "tf": 1, "in_doc": true}, {"token": "jika", "contribution": 4.3065, "idf": 2.5807, "tf": 3, "in_doc": true}, {"token": "menuntut", "contribution": 3.5174, "idf": 3.5096, "tf": 1, "in_doc": true}, {"token": "dapat", "contribution": 3.1589, "idf": 2.2077, "tf": 2, "in_doc": true}, {"token": "apakah", "contribution": 0.0, "idf": 0.0, "tf": 0, "in_doc": false}, {"token": "seorang", "contribution": 0.0, "idf": 0.0, "tf": 0, "in_doc": false}, {"token": "investor", "contribution": 0.0, "idf": 0.0, "tf": 0, "in_doc": false}, {"token": "yang", "contribution": 0.0, "idf": 0.0, "tf": 1, "in_doc": true}, {"token": "menanggung", "contribution": 0.0, "idf": 0.0, "tf": 0, "in_doc": false}, {"token": "risiko", "contribution": 0.0, "idf": 0.0, "tf": 0, "in_doc": false}, {"token": "besar", "contribution": 0.0, "idf": 0.0, "tf": 0, "in_doc": false}, {"token": "dan", "contribution": 0.0, "idf": 0.0, "tf": 0, "in_doc": false}, {"token": "biaya", "contribution": 0.0, "idf": 0.0, "tf": 0, "in_doc": false}, {"token": "tinggi", "contribution": 0.0, "idf": 0.0, "tf": 0, "in_doc": false}, {"token": "dalam", "contribution": 0.0, "idf": 0.0, "tf": 0, "in_doc": false}, {"token": "membangun", "contribution": 0.0, "idf": 0.0, "tf": 0, "in_doc": false}, {"token": "infrastruktur", "contribution": 0.0, "idf": 0.0, "tf": 0, "in_doc": false}, {"token": "jalan", "contribution": 0.0, "idf": 0.0, "tf": 0, "in_doc": false}, {"token": "tol", "contribution": 0.0, "idf": 0.0, "tf": 0, "in_doc": false}], "doc_highlights": [{"start": 12, "end": 16, "token": "jika", "intensity": 0.923, "score": 4.3065}, {"start": 231, "end": 236, "token": "dapat", "intensity": 0.677, "score": 3.1589}, {"start": 289, "end": 293, "token": "jika", "intensity": 0.923, "score": 4.3065}, {"start": 324, "end": 329, "token": "dapat", "intensity": 0.677, "score": 3.1589}, {"start": 330, "end": 338, "token": "menuntut", "intensity": 0.754, "score": 3.5174}, {"start": 369, "end": 373, "token": "jika", "intensity": 0.923, "score": 4.3065}, {"start": 394, "end": 399, "token": "ganti", "intensity": 0.978, "score": 4.5621}, {"start": 400, "end": 404, "token": "rugi", "intensity": 1.0, "score": 4.6659}], "query_highlights": [{"start": 110, "end": 115, "token": "dapat", "intensity": 0.677, "score": 3.1589}, {"start": 116, "end": 124, "token": "menuntut", "intensity": 0.754, "score": 3.5174}, {"start": 125, "end": 130, "token": "ganti", "intensity": 0.978, "score": 4.5621}, {"start": 131, "end": 135, "token": "rugi", "intensity": 1.0, "score": 4.6659}, {"start": 136, "end": 140, "token": "jika", "intensity": 0.923, "score": 4.3065}]}, {"rank": 20, "doc_id": "1307", "title": "Pasal 1307", "bm25_score": 13.8072, "is_relevant": false, "per_token": [{"token": "ganti", "contribution": 5.1757, "idf": 4.5521, "tf": 1, "in_doc": true}, {"token": "biaya", "contribution": 4.1527, "idf": 3.6523, "tf": 1, "in_doc": true}, {"token": "menuntut", "contribution": 3.9905, "idf": 3.5096, "tf": 1, "in_doc": true}, {"token": "jika", "contribution": 2.9343, "idf": 2.5807, "tf": 1, "in_doc": true}, {"token": "dapat", "contribution": 2.5102, "idf": 2.2077, "tf": 1, "in_doc": true}, {"token": "dan", "contribution": 2.4366, "idf": 1.5588, "tf": 2, "in_doc": true}, {"token": "apakah", "contribution": 0.0, "idf": 0.0, "tf": 0, "in_doc": false}, {"token": "seorang", "contribution": 0.0, "idf": 0.0, "tf": 0, "in_doc": false}, {"token": "investor", "contribution": 0.0, "idf": 0.0, "tf": 0, "in_doc": false}, {"token": "yang", "contribution": 0.0, "idf": 0.0, "tf": 1, "in_doc": true}, {"token": "menanggung", "contribution": 0.0, "idf": 0.0, "tf": 0, "in_doc": false}, {"token": "risiko", "contribution": 0.0, "idf": 0.0, "tf": 0, "in_doc": false}, {"token": "besar", "contribution": 0.0, "idf": 0.0, "tf": 0, "in_doc": false}, {"token": "tinggi", "contribution": 0.0, "idf": 0.0, "tf": 0, "in_doc": false}, {"token": "dalam", "contribution": 0.0, "idf": 0.0, "tf": 0, "in_doc": false}, {"token": "membangun", "contribution": 0.0, "idf": 0.0, "tf": 0, "in_doc": false}, {"token": "infrastruktur", "contribution": 0.0, "idf": 0.0, "tf": 0, "in_doc": false}, {"token": "jalan", "contribution": 0.0, "idf": 0.0, "tf": 0, "in_doc": false}, {"token": "tol", "contribution": 0.0, "idf": 0.0, "tf": 0, "in_doc": false}, {"token": "rugi", "contribution": 0.0, "idf": 0.0, "tf": 0, "in_doc": false}], "doc_highlights": [{"start": 50, "end": 55, "token": "ganti", "intensity": 1.0, "score": 5.1757}, {"start": 68, "end": 73, "token": "biaya", "intensity": 0.802, "score": 4.1527}, {"start": 84, "end": 87, "token": "dan", "intensity": 0.471, "score": 2.4366}, {"start": 166, "end": 171, "token": "dapat", "intensity": 0.485, "score": 2.5102}, {"start": 172, "end": 180, "token": "menuntut", "intensity": 0.771, "score": 3.9905}, {"start": 193, "end": 196, "token": "dan", "intensity": 0.471, "score": 2.4366}, {"start": 230, "end": 234, "token": "jika", "intensity": 0.567, "score": 2.9343}], "query_highlights": [{"start": 53, "end": 56, "token": "dan", "intensity": 0.471, "score": 2.4366}, {"start": 57, "end": 62, "token": "biaya", "intensity": 0.802, "score": 4.1527}, {"start": 110, "end": 115, "token": "dapat", "intensity": 0.485, "score": 2.5102}, {"start": 116, "end": 124, "token": "menuntut", "intensity": 0.771, "score": 3.9905}, {"start": 125, "end": 130, "token": "ganti", "intensity": 1.0, "score": 5.1757}, {"start": 136, "end": 140, "token": "jika", "intensity": 0.567, "score": 2.9343}]}, {"rank": 21, "doc_id": "1839", "title": "Pasal 1839", "bm25_score": 13.6605, "is_relevant": false, "per_token": [{"token": "biaya", "contribution": 6.3297, "idf": 3.6523, "tf": 5, "in_doc": true}, {"token": "apakah", "contribution": 4.2364, "idf": 5.4441, "tf": 1, "in_doc": true}, {"token": "menuntut", "contribution": 4.1656, "idf": 3.5096, "tf": 2, "in_doc": true}, {"token": "dapat", "contribution": 3.1765, "idf": 2.2077, "tf": 3, "in_doc": true}, {"token": "dalam", "contribution": 1.3543, "idf": 1.7403, "tf": 1, "in_doc": true}, {"token": "dan", "contribution": 1.213, "idf": 1.5588, "tf": 1, "in_doc": true}, {"token": "seorang", "contribution": 0.0, "idf": 0.0, "tf": 0, "in_doc": false}, {"token": "investor", "contribution": 0.0, "idf": 0.0, "tf": 0, "in_doc": false}, {"token": "yang", "contribution": 0.0, "idf": 0.0, "tf": 4, "in_doc": true}, {"token": "menanggung", "contribution": 0.0, "idf": 0.0, "tf": 0, "in_doc": false}, {"token": "risiko", "contribution": 0.0, "idf": 0.0, "tf": 0, "in_doc": false}, {"token": "besar", "contribution": 0.0, "idf": 0.0, "tf": 0, "in_doc": false}, {"token": "tinggi", "contribution": 0.0, "idf": 0.0, "tf": 0, "in_doc": false}, {"token": "membangun", "contribution": 0.0, "idf": 0.0, "tf": 0, "in_doc": false}, {"token": "infrastruktur", "contribution": 0.0, "idf": 0.0, "tf": 0, "in_doc": false}, {"token": "jalan", "contribution": 0.0, "idf": 0.0, "tf": 0, "in_doc": false}, {"token": "tol", "contribution": 0.0, "idf": 0.0, "tf": 0, "in_doc": false}, {"token": "ganti", "contribution": 0.0, "idf": 0.0, "tf": 0, "in_doc": false}, {"token": "rugi", "contribution": 0.0, "idf": 0.0, "tf": 0, "in_doc": false}, {"token": "jika", "contribution": 0.0, "idf": 0.0, "tf": 0, "in_doc": false}], "doc_highlights": [{"start": 43, "end": 48, "token": "dapat", "intensity": 0.502, "score": 3.1765}, {"start": 49, "end": 57, "token": "menuntut", "intensity": 0.658, "score": 4.1656}, {"start": 128, "end": 134, "token": "apakah", "intensity": 0.669, "score": 4.2364}, {"start": 228, "end": 233, "token": "dapat", "intensity": 0.502, "score": 3.1765}, {"start": 297, "end": 302, "token": "biaya", "intensity": 1.0, "score": 6.3297}, {"start": 303, "end": 308, "token": "biaya", "intensity": 1.0, "score": 6.3297}, {"start": 319, "end": 324, "token": "biaya", "intensity": 1.0, "score": 6.3297}, {"start": 325, "end": 330, "token": "biaya", "intensity": 1.0, "score": 6.3297}, {"start": 358, "end": 363, "token": "dapat", "intensity": 0.502, "score": 3.1765}, {"start": 392, "end": 397, "token": "dalam", "intensity": 0.214, "score": 1.3543}, {"start": 556, "end": 564, "token": "menuntut", "intensity": 0.658, "score": 4.1656}, {"start": 577, "end": 582, "token": "biaya", "intensity": 1.0, "score": 6.3297}, {"start": 593, "end": 596, "token": "dan", "intensity": 0.192, "score": 1.213}], "query_highlights": [{"start": 0, "end": 6, "token": "apakah", "intensity": 0.669, "score": 4.2364}, {"start": 53, "end": 56, "token": "dan", "intensity": 0.192, "score": 1.213}, {"start": 57, "end": 62, "token": "biaya", "intensity": 1.0, "score": 6.3297}, {"start": 70, "end": 75, "token": "dalam", "intensity": 0.214, "score": 1.3543}, {"start": 110, "end": 115, "token": "dapat", "intensity": 0.502, "score": 3.1765}, {"start": 116, "end": 124, "token": "menuntut", "intensity": 0.658, "score": 4.1656}]}, {"rank": 22, "doc_id": "1603w", "title": "Pasal 1603w", "bm25_score": 13.425, "is_relevant": false, "per_token": [{"token": "kerja", "contribution": 6.2412, "idf": 4.7509, "tf": 1, "in_doc": true}, {"token": "biaya", "contribution": 4.7979, "idf": 3.6523, "tf": 1, "in_doc": true}, {"token": "menuntut", "contribution": 4.6105, "idf": 3.5096, "tf": 1, "in_doc": true}, {"token": "dalam", "contribution": 2.2862, "idf": 1.7403, "tf": 1, "in_doc": true}, {"token": "dan", "contribution": 2.0478, "idf": 1.5588, "tf": 1, "in_doc": true}, {"token": "apakah", "contribution": 0.0, "idf": 0.0, "tf": 0, "in_doc": false}, {"token": "seorang", "contribution": 0.0, "idf": 0.0, "tf": 0, "in_doc": false}, {"token": "investor", "contribution": 0.0, "idf": 0.0, "tf": 0, "in_doc": false}, {"token": "yang", "contribution": 0.0, "idf": 0.0, "tf": 0, "in_doc": false}, {"token": "menanggung", "contribution": 0.0, "idf": 0.0, "tf": 0, "in_doc": false}, {"token": "risiko", "contribution": 0.0, "idf": 0.0, "tf": 0, "in_doc": false}, {"token": "besar", "contribution": 0.0, "idf": 0.0, "tf": 0, "in_doc": false}, {"token": "tinggi", "contribution": 0.0, "idf": 0.0, "tf": 0, "in_doc": false}, {"token": "membangun", "contribution": 0.0, "idf": 0.0, "tf": 0, "in_doc": false}, {"token": "infrastruktur", "contribution": 0.0, "idf": 0.0, "tf": 0, "in_doc": false}, {"token": "jalan", "contribution": 0.0, "idf": 0.0, "tf": 0, "in_doc": false}, {"token": "tol", "contribution": 0.0, "idf": 0.0, "tf": 0, "in_doc": false}, {"token": "dapat", "contribution": 0.0, "idf": 0.0, "tf": 0, "in_doc": false}, {"token": "ganti", "contribution": 0.0, "idf": 0.0, "tf": 0, "in_doc": false}, {"token": "rugi", "contribution": 0.0, "idf": 0.0, "tf": 0, "in_doc": false}], "doc_highlights": [{"start": 39, "end": 47, "token": "menuntut", "intensity": 0.739, "score": 4.6105}, {"start": 67, "end": 72, "token": "kerja", "intensity": 1.0, "score": 6.2412}, {"start": 114, "end": 119, "token": "biaya", "intensity": 0.769, "score": 4.7979}, {"start": 130, "end": 133, "token": "dan", "intensity": 0.328, "score": 2.0478}, {"start": 180, "end": 185, "token": "dalam", "intensity": 0.366, "score": 2.2862}], "query_highlights": [{"start": 53, "end": 56, "token": "dan", "intensity": 0.328, "score": 2.0478}, {"start": 57, "end": 62, "token": "biaya", "intensity": 0.769, "score": 4.7979}, {"start": 70, "end": 75, "token": "dalam", "intensity": 0.366, "score": 2.2862}, {"start": 116, "end": 124, "token": "menuntut", "intensity": 0.739, "score": 4.6105}, {"start": 191, "end": 196, "token": "kerja", "intensity": 1.0, "score": 6.2412}]}, {"rank": 23, "doc_id": "1611", "title": "Pasal 1611", "bm25_score": 13.3549, "is_relevant": false, "per_token": [{"token": "rugi", "contribution": 5.3971, "idf": 4.6556, "tf": 1, "in_doc": true}, {"token": "ganti", "contribution": 5.2771, "idf": 4.5521, "tf": 1, "in_doc": true}, {"token": "biaya", "contribution": 4.234, "idf": 3.6523, "tf": 1, "in_doc": true}, {"token": "dapat", "contribution": 2.5594, "idf": 2.2077, "tf": 1, "in_doc": true}, {"token": "dan", "contribution": 1.8071, "idf": 1.5588, "tf": 1, "in_doc": true}, {"token": "apakah", "contribution": 0.0, "idf": 0.0, "tf": 0, "in_doc": false}, {"token": "seorang", "contribution": 0.0, "idf": 0.0, "tf": 0, "in_doc": false}, {"token": "investor", "contribution": 0.0, "idf": 0.0, "tf": 0, "in_doc": false}, {"token": "yang", "contribution": 0.0, "idf": 0.0, "tf": 1, "in_doc": true}, {"token": "menanggung", "contribution": 0.0, "idf": 0.0, "tf": 0, "in_doc": false}, {"token": "risiko", "contribution": 0.0, "idf": 0.0, "tf": 0, "in_doc": false}, {"token": "besar", "contribution": 0.0, "idf": 0.0, "tf": 0, "in_doc": false}, {"token": "tinggi", "contribution": 0.0, "idf": 0.0, "tf": 0, "in_doc": false}, {"token": "dalam", "contribution": 0.0, "idf": 0.0, "tf": 0, "in_doc": false}, {"token": "membangun", "contribution": 0.0, "idf": 0.0, "tf": 0, "in_doc": false}, {"token": "infrastruktur", "contribution": 0.0, "idf": 0.0, "tf": 0, "in_doc": false}, {"token": "jalan", "contribution": 0.0, "idf": 0.0, "tf": 0, "in_doc": false}, {"token": "tol", "contribution": 0.0, "idf": 0.0, "tf": 0, "in_doc": false}, {"token": "menuntut", "contribution": 0.0, "idf": 0.0, "tf": 0, "in_doc": false}, {"token": "jika", "contribution": 0.0, "idf": 0.0, "tf": 0, "in_doc": false}], "doc_highlights": [{"start": 47, "end": 52, "token": "dapat", "intensity": 0.474, "score": 2.5594}, {"start": 148, "end": 153, "token": "ganti", "intensity": 0.978, "score": 5.2771}, {"start": 154, "end": 158, "token": "rugi", "intensity": 1.0, "score": 5.3971}, {"start": 198, "end": 203, "token": "biaya", "intensity": 0.784, "score": 4.234}, {"start": 250, "end": 253, "token": "dan", "intensity": 0.335, "score": 1.8071}], "query_highlights": [{"start": 53, "end": 56, "token": "dan", "intensity": 0.335, "score": 1.8071}, {"start": 57, "end": 62, "token": "biaya", "intensity": 0.784, "score": 4.234}, {"start": 110, "end": 115, "token": "dapat", "intensity": 0.474, "score": 2.5594}, {"start": 125, "end": 130, "token": "ganti", "intensity": 0.978, "score": 5.2771}, {"start": 131, "end": 135, "token": "rugi", "intensity": 1.0, "score": 5.3971}]}, {"rank": 24, "doc_id": "1552", "title": "Pasal 1552", "bm25_score": 13.2681, "is_relevant": false, "per_token": [{"token": "menanggung", "contribution": 4.9939, "idf": 4.8563, "tf": 1, "in_doc": true}, {"token": "rugi", "contribution": 4.7875, "idf": 4.6556, "tf": 1, "in_doc": true}, {"token": "ganti", "contribution": 4.6811, "idf": 4.5521, "tf": 1, "in_doc": true}, {"token": "jika", "contribution": 2.6538, "idf": 2.5807, "tf": 1, "in_doc": true}, {"token": "apakah", "contribution": 0.0, "idf": 0.0, "tf": 0, "in_doc": false}, {"token": "seorang", "contribution": 0.0, "idf": 0.0, "tf": 0, "in_doc": false}, {"token": "investor", "contribution": 0.0, "idf": 0.0, "tf": 0, "in_doc": false}, {"token": "yang", "contribution": 0.0, "idf": 0.0, "tf": 5, "in_doc": true}, {"token": "risiko", "contribution": 0.0, "idf": 0.0, "tf": 0, "in_doc": false}, {"token": "besar", "contribution": 0.0, "idf": 0.0, "tf": 0, "in_doc": false}, {"token": "dan", "contribution": 0.0, "idf": 0.0, "tf": 0, "in_doc": false}, {"token": "biaya", "contribution": 0.0, "idf": 0.0, "tf": 0, "in_doc": false}, {"token": "tinggi", "contribution": 0.0, "idf": 0.0, "tf": 0, "in_doc": false}, {"token": "dalam", "contribution": 0.0, "idf": 0.0, "tf": 0, "in_doc": false}, {"token": "membangun", "contribution": 0.0, "idf": 0.0, "tf": 0, "in_doc": false}, {"token": "infrastruktur", "contribution": 0.0, "idf": 0.0, "tf": 0, "in_doc": false}, {"token": "jalan", "contribution": 0.0, "idf": 0.0, "tf": 0, "in_doc": false}, {"token": "tol", "contribution": 0.0, "idf": 0.0, "tf": 0, "in_doc": false}, {"token": "dapat", "contribution": 0.0, "idf": 0.0, "tf": 0, "in_doc": false}, {"token": "menuntut", "contribution": 0.0, "idf": 0.0, "tf": 0, "in_doc": false}], "doc_highlights": [{"start": 40, "end": 50, "token": "menanggung", "intensity": 1.0, "score": 4.9939}, {"start": 239, "end": 243, "token": "jika", "intensity": 0.531, "score": 2.6538}, {"start": 353, "end": 358, "token": "ganti", "intensity": 0.937, "score": 4.6811}, {"start": 359, "end": 363, "token": "rugi", "intensity": 0.959, "score": 4.7875}], "query_highlights": [{"start": 29, "end": 39, "token": "menanggung", "intensity": 1.0, "score": 4.9939}, {"start": 125, "end": 130, "token": "ganti", "intensity": 0.937, "score": 4.6811}, {"start": 131, "end": 135, "token": "rugi", "intensity": 0.959, "score": 4.7875}, {"start": 136, "end": 140, "token": "jika", "intensity": 0.531, "score": 2.6538}]}, {"rank": 25, "doc_id": "628", "title": "Pasal 628", "bm25_score": 13.2263, "is_relevant": false, "per_token": [{"token": "jalan", "contribution": 5.0916, "idf": 5.1664, "tf": 1, "in_doc": true}, {"token": "rugi", "contribution": 4.5882, "idf": 4.6556, "tf": 1, "in_doc": true}, {"token": "ganti", "contribution": 4.4862, "idf": 4.5521, "tf": 1, "in_doc": true}, {"token": "jika", "contribution": 2.5434, "idf": 2.5807, "tf": 1, "in_doc": true}, {"token": "dalam", "contribution": 1.7151, "idf": 1.7403, "tf": 1, "in_doc": true}, {"token": "apakah", "contribution": 0.0, "idf": 0.0, "tf": 0, "in_doc": false}, {"token": "seorang", "contribution": 0.0, "idf": 0.0, "tf": 0, "in_doc": false}, {"token": "investor", "contribution": 0.0, "idf": 0.0, "tf": 0, "in_doc": false}, {"token": "yang", "contribution": 0.0, "idf": 0.0, "tf": 1, "in_doc": true}, {"token": "menanggung", "contribution": 0.0, "idf": 0.0, "tf": 0, "in_doc": false}, {"token": "risiko", "contribution": 0.0, "idf": 0.0, "tf": 0, "in_doc": false}, {"token": "besar", "contribution": 0.0, "idf": 0.0, "tf": 0, "in_doc": false}, {"token": "dan", "contribution": 0.0, "idf": 0.0, "tf": 0, "in_doc": false}, {"token": "biaya", "contribution": 0.0, "idf": 0.0, "tf": 0, "in_doc": false}, {"token": "tinggi", "contribution": 0.0, "idf": 0.0, "tf": 0, "in_doc": false}, {"token": "membangun", "contribution": 0.0, "idf": 0.0, "tf": 0, "in_doc": false}, {"token": "infrastruktur", "contribution": 0.0, "idf": 0.0, "tf": 0, "in_doc": false}, {"token": "tol", "contribution": 0.0, "idf": 0.0, "tf": 0, "in_doc": false}, {"token": "dapat", "contribution": 0.0, "idf": 0.0, "tf": 0, "in_doc": false}, {"token": "menuntut", "contribution": 0.0, "idf": 0.0, "tf": 0, "in_doc": false}], "doc_highlights": [{"start": 49, "end": 54, "token": "jalan", "intensity": 1.0, "score": 5.0916}, {"start": 156, "end": 161, "token": "dalam", "intensity": 0.337, "score": 1.7151}, {"start": 197, "end": 202, "token": "ganti", "intensity": 0.881, "score": 4.4862}, {"start": 203, "end": 207, "token": "rugi", "intensity": 0.901, "score": 4.5882}, {"start": 257, "end": 261, "token": "jika", "intensity": 0.5, "score": 2.5434}], "query_highlights": [{"start": 70, "end": 75, "token": "dalam", "intensity": 0.337, "score": 1.7151}, {"start": 100, "end": 105, "token": "jalan", "intensity": 1.0, "score": 5.0916}, {"start": 125, "end": 130, "token": "ganti", "intensity": 0.881, "score": 4.4862}, {"start": 131, "end": 135, "token": "rugi", "intensity": 0.901, "score": 4.5882}, {"start": 136, "end": 140, "token": "jika", "intensity": 0.5, "score": 2.5434}]}, {"rank": 143, "doc_id": "1236", "title": "Pasal 1236", "bm25_score": 8.3862, "is_relevant": true, "per_token": [{"token": "ganti", "contribution": 5.7257, "idf": 4.5521, "tf": 1, "in_doc": true}, {"token": "biaya", "contribution": 4.594, "idf": 3.6523, "tf": 1, "in_doc": true}, {"token": "dan", "contribution": 1.9607, "idf": 1.5588, "tf": 1, "in_doc": true}, {"token": "apakah", "contribution": 0.0, "idf": 0.0, "tf": 0, "in_doc": false}, {"token": "seorang", "contribution": 0.0, "idf": 0.0, "tf": 0, "in_doc": false}, {"token": "investor", "contribution": 0.0, "idf": 0.0, "tf": 0, "in_doc": false}, {"token": "yang", "contribution": 0.0, "idf": 0.0, "tf": 0, "in_doc": false}, {"token": "menanggung", "contribution": 0.0, "idf": 0.0, "tf": 0, "in_doc": false}, {"token": "risiko", "contribution": 0.0, "idf": 0.0, "tf": 0, "in_doc": false}, {"token": "besar", "contribution": 0.0, "idf": 0.0, "tf": 0, "in_doc": false}, {"token": "tinggi", "contribution": 0.0, "idf": 0.0, "tf": 0, "in_doc": false}, {"token": "dalam", "contribution": 0.0, "idf": 0.0, "tf": 0, "in_doc": false}, {"token": "membangun", "contribution": 0.0, "idf": 0.0, "tf": 0, "in_doc": false}, {"token": "infrastruktur", "contribution": 0.0, "idf": 0.0, "tf": 0, "in_doc": false}, {"token": "jalan", "contribution": 0.0, "idf": 0.0, "tf": 0, "in_doc": false}, {"token": "tol", "contribution": 0.0, "idf": 0.0, "tf": 0, "in_doc": false}, {"token": "dapat", "contribution": 0.0, "idf": 0.0, "tf": 0, "in_doc": false}, {"token": "menuntut", "contribution": 0.0, "idf": 0.0, "tf": 0, "in_doc": false}, {"token": "rugi", "contribution": 0.0, "idf": 0.0, "tf": 0, "in_doc": false}, {"token": "jika", "contribution": 0.0, "idf": 0.0, "tf": 0, "in_doc": false}], "doc_highlights": [{"start": 34, "end": 39, "token": "ganti", "intensity": 1.0, "score": 5.7257}, {"start": 40, "end": 45, "token": "biaya", "intensity": 0.802, "score": 4.594}, {"start": 56, "end": 59, "token": "dan", "intensity": 0.342, "score": 1.9607}], "query_highlights": [{"start": 53, "end": 56, "token": "dan", "intensity": 0.342, "score": 1.9607}, {"start": 57, "end": 62, "token": "biaya", "intensity": 0.802, "score": 4.594}, {"start": 125, "end": 130, "token": "ganti", "intensity": 1.0, "score": 5.7257}], "beyond_topk": true}]}