{"qid": "q2311", "query_text": "Apakah seorang suami dapat dituntut secara perdata atas tindakan kekerasan fisik, verbal, dan pemasangan kamera pengintai pada pakaian istri tanpa izin?", "case_name": "salinan_putusan_494_Pdt_G_2023_PN_Smg.pdf", "n_gt": 2, "gt_doc_ids": ["1365", "1372"], "gt_ranks": {"1372": 392, "1365": 1641}, "ranked_docs": [{"rank": 1, "doc_id": "332b", "title": "Pasal 332b", "bm25_score": 17.4892, "is_relevant": false, "per_token": [{"token": "tindakan", "contribution": 6.7158, "idf": 5.1972, "tf": 3, "in_doc": true}, {"token": "izin", "contribution": 4.5945, "idf": 4.4144, "tf": 2, "in_doc": true}, {"token": "tanpa", "contribution": 3.8946, "idf": 3.014, "tf": 3, "in_doc": true}, {"token": "suami", "contribution": 3.583, "idf": 3.4426, "tf": 2, "in_doc": true}, {"token": "perdata", "contribution": 3.1629, "idf": 4.8128, "tf": 1, "in_doc": true}, {"token": "atas", "contribution": 1.5524, "idf": 2.3622, "tf": 1, "in_doc": true}, {"token": "dan", "contribution": 1.0244, "idf": 1.5588, "tf": 1, "in_doc": true}, {"token": "apakah", "contribution": 0.0, "idf": 0.0, "tf": 0, "in_doc": false}, {"token": "seorang", "contribution": 0.0, "idf": 0.0, "tf": 0, "in_doc": false}, {"token": "dapat", "contribution": 0.0, "idf": 0.0, "tf": 0, "in_doc": false}, {"token": "dituntut", "contribution": 0.0, "idf": 0.0, "tf": 0, "in_doc": false}, {"token": "secara", "contribution": 0.0, "idf": 0.0, "tf": 0, "in_doc": false}, {"token": "kekerasan", "contribution": 0.0, "idf": 0.0, "tf": 0, "in_doc": false}, {"token": "fisik", "contribution": 0.0, "idf": 0.0, "tf": 0, "in_doc": false}, {"token": "verbal", "contribution": 0.0, "idf": 0.0, "tf": 0, "in_doc": false}, {"token": "pemasangan", "contribution": 0.0, "idf": 0.0, "tf": 0, "in_doc": false}, {"token": "kamera", "contribution": 0.0, "idf": 0.0, "tf": 0, "in_doc": false}, {"token": "pengintai", "contribution": 0.0, "idf": 0.0, "tf": 0, "in_doc": false}, {"token": "pada", "contribution": 0.0, "idf": 0.0, "tf": 0, "in_doc": false}, {"token": "pakaian", "contribution": 0.0, "idf": 0.0, "tf": 0, "in_doc": false}], "doc_highlights": [{"start": 53, "end": 58, "token": "tanpa", "intensity": 0.58, "score": 3.8946}, {"start": 72, "end": 76, "token": "izin", "intensity": 0.684, "score": 4.5945}, {"start": 91, "end": 96, "token": "suami", "intensity": 0.534, "score": 3.583}, {"start": 103, "end": 108, "token": "suami", "intensity": 0.534, "score": 3.583}, {"start": 139, "end": 143, "token": "izin", "intensity": 0.684, "score": 4.5945}, {"start": 415, "end": 423, "token": "tindakan", "intensity": 1.0, "score": 6.7158}, {"start": 424, "end": 431, "token": "perdata", "intensity": 0.471, "score": 3.1629}, {"start": 463, "end": 466, "token": "dan", "intensity": 0.153, "score": 1.0244}, {"start": 485, "end": 489, "token": "atas", "intensity": 0.231, "score": 1.5524}, {"start": 490, "end": 498, "token": "tindakan", "intensity": 1.0, "score": 6.7158}, {"start": 499, "end": 507, "token": "tindakan", "intensity": 1.0, "score": 6.7158}, {"start": 513, "end": 518, "token": "tanpa", "intensity": 0.58, "score": 3.8946}, {"start": 781, "end": 786, "token": "tanpa", "intensity": 0.58, "score": 3.8946}], "query_highlights": [{"start": 15, "end": 20, "token": "suami", "intensity": 0.534, "score": 3.583}, {"start": 43, "end": 50, "token": "perdata", "intensity": 0.471, "score": 3.1629}, {"start": 51, "end": 55, "token": "atas", "intensity": 0.231, "score": 1.5524}, {"start": 56, "end": 64, "token": "tindakan", "intensity": 1.0, "score": 6.7158}, {"start": 90, "end": 93, "token": "dan", "intensity": 0.153, "score": 1.0244}, {"start": 141, "end": 146, "token": "tanpa", "intensity": 0.58, "score": 3.8946}, {"start": 147, "end": 151, "token": "izin", "intensity": 0.684, "score": 4.5945}]}, {"rank": 2, "doc_id": "129", "title": "Pasal 129", "bm25_score": 17.4344, "is_relevant": false, "per_token": [{"token": "pakaian", "contribution": 6.083, "idf": 6.5835, "tf": 1, "in_doc": true}, {"token": "suami", "contribution": 4.645, "idf": 3.4426, "tf": 2, "in_doc": true}, {"token": "dituntut", "contribution": 4.4084, "idf": 4.7711, "tf": 1, "in_doc": true}, {"token": "seorang", "contribution": 3.9748, "idf": 2.9459, "tf": 2, "in_doc": true}, {"token": "secara", "contribution": 3.0594, "idf": 3.3111, "tf": 1, "in_doc": true}, {"token": "dan", "contribution": 2.732, "idf": 1.5588, "tf": 4, "in_doc": true}, {"token": "apakah", "contribution": 0.0, "idf": 0.0, "tf": 0, "in_doc": false}, {"token": "dapat", "contribution": 0.0, "idf": 0.0, "tf": 0, "in_doc": false}, {"token": "perdata", "contribution": 0.0, "idf": 0.0, "tf": 0, "in_doc": false}, {"token": "atas", "contribution": 0.0, "idf": 0.0, "tf": 0, "in_doc": false}, {"token": "tindakan", "contribution": 0.0, "idf": 0.0, "tf": 0, "in_doc": false}, {"token": "kekerasan", "contribution": 0.0, "idf": 0.0, "tf": 0, "in_doc": false}, {"token": "fisik", "contribution": 0.0, "idf": 0.0, "tf": 0, "in_doc": false}, {"token": "verbal", "contribution": 0.0, "idf": 0.0, "tf": 0, "in_doc": false}, {"token": "pemasangan", "contribution": 0.0, "idf": 0.0, "tf": 0, "in_doc": false}, {"token": "kamera", "contribution": 0.0, "idf": 0.0, "tf": 0, "in_doc": false}, {"token": "pengintai", "contribution": 0.0, "idf": 0.0, "tf": 0, "in_doc": false}, {"token": "pada", "contribution": 0.0, "idf": 0.0, "tf": 0, "in_doc": false}, {"token": "istri", "contribution": 0.0, "idf": 0.0, "tf": 0, "in_doc": false}, {"token": "tanpa", "contribution": 0.0, "idf": 0.0, "tf": 0, "in_doc": false}], "doc_highlights": [{"start": 11, "end": 18, "token": "pakaian", "intensity": 1.0, "score": 6.083}, {"start": 30, "end": 33, "token": "dan", "intensity": 0.449, "score": 2.732}, {"start": 72, "end": 79, "token": "seorang", "intensity": 0.653, "score": 3.9748}, {"start": 85, "end": 90, "token": "suami", "intensity": 0.764, "score": 4.645}, {"start": 121, "end": 124, "token": "dan", "intensity": 0.449, "score": 2.732}, {"start": 154, "end": 157, "token": "dan", "intensity": 0.449, "score": 2.732}, {"start": 168, "end": 171, "token": "dan", "intensity": 0.449, "score": 2.732}, {"start": 271, "end": 278, "token": "seorang", "intensity": 0.653, "score": 3.9748}, {"start": 284, "end": 289, "token": "suami", "intensity": 0.764, "score": 4.645}, {"start": 308, "end": 316, "token": "dituntut", "intensity": 0.725, "score": 4.4084}, {"start": 380, "end": 386, "token": "secara", "intensity": 0.503, "score": 3.0594}], "query_highlights": [{"start": 7, "end": 14, "token": "seorang", "intensity": 0.653, "score": 3.9748}, {"start": 15, "end": 20, "token": "suami", "intensity": 0.764, "score": 4.645}, {"start": 27, "end": 35, "token": "dituntut", "intensity": 0.725, "score": 4.4084}, {"start": 36, "end": 42, "token": "secara", "intensity": 0.503, "score": 3.0594}, {"start": 90, "end": 93, "token": "dan", "intensity": 0.449, "score": 2.732}, {"start": 127, "end": 134, "token": "pakaian", "intensity": 1.0, "score": 6.083}]}, {"rank": 3, "doc_id": "87", "title": "Pasal 87", "bm25_score": 16.9243, "is_relevant": false, "per_token": [{"token": "istri", "contribution": 8.0225, "idf": 5.1366, "tf": 4, "in_doc": true}, {"token": "suami", "contribution": 5.3767, "idf": 3.4426, "tf": 4, "in_doc": true}, {"token": "seorang", "contribution": 3.3455, "idf": 2.9459, "tf": 2, "in_doc": true}, {"token": "dapat", "contribution": 2.5072, "idf": 2.2077, "tf": 2, "in_doc": true}, {"token": "secara", "contribution": 2.4327, "idf": 3.3111, "tf": 1, "in_doc": true}, {"token": "tanpa", "contribution": 2.2144, "idf": 3.014, "tf": 1, "in_doc": true}, {"token": "apakah", "contribution": 0.0, "idf": 0.0, "tf": 0, "in_doc": false}, {"token": "dituntut", "contribution": 0.0, "idf": 0.0, "tf": 0, "in_doc": false}, {"token": "perdata", "contribution": 0.0, "idf": 0.0, "tf": 0, "in_doc": false}, {"token": "atas", "contribution": 0.0, "idf": 0.0, "tf": 0, "in_doc": false}, {"token": "tindakan", "contribution": 0.0, "idf": 0.0, "tf": 0, "in_doc": false}, {"token": "kekerasan", "contribution": 0.0, "idf": 0.0, "tf": 0, "in_doc": false}, {"token": "fisik", "contribution": 0.0, "idf": 0.0, "tf": 0, "in_doc": false}, {"token": "verbal", "contribution": 0.0, "idf": 0.0, "tf": 0, "in_doc": false}, {"token": "dan", "contribution": 0.0, "idf": 0.0, "tf": 0, "in_doc": false}, {"token": "pemasangan", "contribution": 0.0, "idf": 0.0, "tf": 0, "in_doc": false}, {"token": "kamera", "contribution": 0.0, "idf": 0.0, "tf": 0, "in_doc": false}, {"token": "pengintai", "contribution": 0.0, "idf": 0.0, "tf": 0, "in_doc": false}, {"token": "pada", "contribution": 0.0, "idf": 0.0, "tf": 0, "in_doc": false}, {"token": "pakaian", "contribution": 0.0, "idf": 0.0, "tf": 0, "in_doc": false}], "doc_highlights": [{"start": 54, "end": 59, "token": "tanpa", "intensity": 0.276, "score": 2.2144}, {"start": 84, "end": 89, "token": "suami", "intensity": 0.67, "score": 5.3767}, {"start": 90, "end": 95, "token": "istri", "intensity": 1.0, "score": 8.0225}, {"start": 107, "end": 114, "token": "seorang", "intensity": 0.417, "score": 3.3455}, {"start": 134, "end": 139, "token": "dapat", "intensity": 0.313, "score": 2.5072}, {"start": 154, "end": 159, "token": "suami", "intensity": 0.67, "score": 5.3767}, {"start": 160, "end": 165, "token": "istri", "intensity": 1.0, "score": 8.0225}, {"start": 187, "end": 194, "token": "seorang", "intensity": 0.417, "score": 3.3455}, {"start": 235, "end": 241, "token": "secara", "intensity": 0.303, "score": 2.4327}, {"start": 350, "end": 355, "token": "dapat", "intensity": 0.313, "score": 2.5072}, {"start": 370, "end": 375, "token": "suami", "intensity": 0.67, "score": 5.3767}, {"start": 381, "end": 386, "token": "istri", "intensity": 1.0, "score": 8.0225}, {"start": 590, "end": 595, "token": "suami", "intensity": 0.67, "score": 5.3767}, {"start": 601, "end": 606, "token": "istri", "intensity": 1.0, "score": 8.0225}], "query_highlights": [{"start": 7, "end": 14, "token": "seorang", "intensity": 0.417, "score": 3.3455}, {"start": 15, "end": 20, "token": "suami", "intensity": 0.67, "score": 5.3767}, {"start": 21, "end": 26, "token": "dapat", "intensity": 0.313, "score": 2.5072}, {"start": 36, "end": 42, "token": "secara", "intensity": 0.303, "score": 2.4327}, {"start": 135, "end": 140, "token": "istri", "intensity": 1.0, "score": 8.0225}, {"start": 141, "end": 146, "token": "tanpa", "intensity": 0.276, "score": 2.2144}]}, {"rank": 4, "doc_id": "86", "title": "Pasal 86", "bm25_score": 16.8182, "is_relevant": false, "per_token": [{"token": "istri", "contribution": 6.7386, "idf": 5.1366, "tf": 2, "in_doc": true}, {"token": "suami", "contribution": 4.5163, "idf": 3.4426, "tf": 2, "in_doc": true}, {"token": "dituntut", "contribution": 4.2428, "idf": 4.7711, "tf": 1, "in_doc": true}, {"token": "seorang", "contribution": 2.6197, "idf": 2.9459, "tf": 1, "in_doc": true}, {"token": "atas", "contribution": 2.1006, "idf": 2.3622, "tf": 1, "in_doc": true}, {"token": "dan", "contribution": 2.045, "idf": 1.5588, "tf": 2, "in_doc": true}, {"token": "dapat", "contribution": 1.9633, "idf": 2.2077, "tf": 1, "in_doc": true}, {"token": "apakah", "contribution": 0.0, "idf": 0.0, "tf": 0, "in_doc": false}, {"token": "secara", "contribution": 0.0, "idf": 0.0, "tf": 0, "in_doc": false}, {"token": "perdata", "contribution": 0.0, "idf": 0.0, "tf": 0, "in_doc": false}, {"token": "tindakan", "contribution": 0.0, "idf": 0.0, "tf": 0, "in_doc": false}, {"token": "kekerasan", "contribution": 0.0, "idf": 0.0, "tf": 0, "in_doc": false}, {"token": "fisik", "contribution": 0.0, "idf": 0.0, "tf": 0, "in_doc": false}, {"token": "verbal", "contribution": 0.0, "idf": 0.0, "tf": 0, "in_doc": false}, {"token": "pemasangan", "contribution": 0.0, "idf": 0.0, "tf": 0, "in_doc": false}, {"token": "kamera", "contribution": 0.0, "idf": 0.0, "tf": 0, "in_doc": false}, {"token": "pengintai", "contribution": 0.0, "idf": 0.0, "tf": 0, "in_doc": false}, {"token": "pada", "contribution": 0.0, "idf": 0.0, "tf": 0, "in_doc": false}, {"token": "pakaian", "contribution": 0.0, "idf": 0.0, "tf": 0, "in_doc": false}, {"token": "tanpa", "contribution": 0.0, "idf": 0.0, "tf": 0, "in_doc": false}], "doc_highlights": [{"start": 81, "end": 86, "token": "dapat", "intensity": 0.291, "score": 1.9633}, {"start": 87, "end": 95, "token": "dituntut", "intensity": 0.63, "score": 4.2428}, {"start": 162, "end": 169, "token": "seorang", "intensity": 0.389, "score": 2.6197}, {"start": 170, "end": 173, "token": "dan", "intensity": 0.303, "score": 2.045}, {"start": 174, "end": 179, "token": "suami", "intensity": 0.67, "score": 4.5163}, {"start": 180, "end": 185, "token": "istri", "intensity": 1.0, "score": 6.7386}, {"start": 196, "end": 201, "token": "suami", "intensity": 0.67, "score": 4.5163}, {"start": 202, "end": 207, "token": "istri", "intensity": 1.0, "score": 6.7386}, {"start": 258, "end": 262, "token": "atas", "intensity": 0.312, "score": 2.1006}, {"start": 338, "end": 341, "token": "dan", "intensity": 0.303, "score": 2.045}], "query_highlights": [{"start": 7, "end": 14, "token": "seorang", "intensity": 0.389, "score": 2.6197}, {"start": 15, "end": 20, "token": "suami", "intensity": 0.67, "score": 4.5163}, {"start": 21, "end": 26, "token": "dapat", "intensity": 0.291, "score": 1.9633}, {"start": 27, "end": 35, "token": "dituntut", "intensity": 0.63, "score": 4.2428}, {"start": 51, "end": 55, "token": "atas", "intensity": 0.312, "score": 2.1006}, {"start": 90, "end": 93, "token": "dan", "intensity": 0.303, "score": 2.045}, {"start": 135, "end": 140, "token": "istri", "intensity": 1.0, "score": 6.7386}]}, {"rank": 5, "doc_id": "1989", "title": "Pasal 1989", "bm25_score": 16.5401, "is_relevant": false, "per_token": [{"token": "istri", "contribution": 9.3128, "idf": 5.1366, "tf": 4, "in_doc": true}, {"token": "suami", "contribution": 4.8962, "idf": 3.4426, "tf": 2, "in_doc": true}, {"token": "tanpa", "contribution": 2.9953, "idf": 3.014, "tf": 1, "in_doc": true}, {"token": "seorang", "contribution": 2.9276, "idf": 2.9459, "tf": 1, "in_doc": true}, {"token": "dapat", "contribution": 2.194, "idf": 2.2077, "tf": 1, "in_doc": true}, {"token": "dan", "contribution": 1.5491, "idf": 1.5588, "tf": 1, "in_doc": true}, {"token": "apakah", "contribution": 0.0, "idf": 0.0, "tf": 0, "in_doc": false}, {"token": "dituntut", "contribution": 0.0, "idf": 0.0, "tf": 0, "in_doc": false}, {"token": "secara", "contribution": 0.0, "idf": 0.0, "tf": 0, "in_doc": false}, {"token": "perdata", "contribution": 0.0, "idf": 0.0, "tf": 0, "in_doc": false}, {"token": "atas", "contribution": 0.0, "idf": 0.0, "tf": 0, "in_doc": false}, {"token": "tindakan", "contribution": 0.0, "idf": 0.0, "tf": 0, "in_doc": false}, {"token": "kekerasan", "contribution": 0.0, "idf": 0.0, "tf": 0, "in_doc": false}, {"token": "fisik", "contribution": 0.0, "idf": 0.0, "tf": 0, "in_doc": false}, {"token": "verbal", "contribution": 0.0, "idf": 0.0, "tf": 0, "in_doc": false}, {"token": "pemasangan", "contribution": 0.0, "idf": 0.0, "tf": 0, "in_doc": false}, {"token": "kamera", "contribution": 0.0, "idf": 0.0, "tf": 0, "in_doc": false}, {"token": "pengintai", "contribution": 0.0, "idf": 0.0, "tf": 0, "in_doc": false}, {"token": "pada", "contribution": 0.0, "idf": 0.0, "tf": 0, "in_doc": false}, {"token": "pakaian", "contribution": 0.0, "idf": 0.0, "tf": 0, "in_doc": false}], "doc_highlights": [{"start": 47, "end": 54, "token": "seorang", "intensity": 0.314, "score": 2.9276}, {"start": 55, "end": 60, "token": "istri", "intensity": 1.0, "score": 9.3128}, {"start": 120, "end": 125, "token": "istri", "intensity": 1.0, "score": 9.3128}, {"start": 132, "end": 137, "token": "dapat", "intensity": 0.236, "score": 2.194}, {"start": 234, "end": 239, "token": "suami", "intensity": 0.526, "score": 4.8962}, {"start": 277, "end": 282, "token": "istri", "intensity": 1.0, "score": 9.3128}, {"start": 283, "end": 288, "token": "tanpa", "intensity": 0.322, "score": 2.9953}, {"start": 337, "end": 340, "token": "dan", "intensity": 0.166, "score": 1.5491}, {"start": 350, "end": 355, "token": "istri", "intensity": 1.0, "score": 9.3128}, {"start": 379, "end": 384, "token": "suami", "intensity": 0.526, "score": 4.8962}], "query_highlights": [{"start": 7, "end": 14, "token": "seorang", "intensity": 0.314, "score": 2.9276}, {"start": 15, "end": 20, "token": "suami", "intensity": 0.526, "score": 4.8962}, {"start": 21, "end": 26, "token": "dapat", "intensity": 0.236, "score": 2.194}, {"start": 90, "end": 93, "token": "dan", "intensity": 0.166, "score": 1.5491}, {"start": 135, "end": 140, "token": "istri", "intensity": 1.0, "score": 9.3128}, {"start": 141, "end": 146, "token": "tanpa", "intensity": 0.322, "score": 2.9953}]}, {"rank": 6, "doc_id": "71", "title": "Pasal 71", "bm25_score": 16.3564, "is_relevant": false, "per_token": [{"token": "izin", "contribution": 7.3525, "idf": 4.4144, "tf": 8, "in_doc": true}, {"token": "istri", "contribution": 5.4972, "idf": 5.1366, "tf": 3, "in_doc": true}, {"token": "suami", "contribution": 3.6843, "idf": 3.4426, "tf": 3, "in_doc": true}, {"token": "dan", "contribution": 2.3363, "idf": 1.5588, "tf": 6, "in_doc": true}, {"token": "tanpa", "contribution": 1.5046, "idf": 3.014, "tf": 1, "in_doc": true}, {"token": "pada", "contribution": 1.314, "idf": 2.6323, "tf": 1, "in_doc": true}, {"token": "dapat", "contribution": 1.1021, "idf": 2.2077, "tf": 1, "in_doc": true}, {"token": "apakah", "contribution": 0.0, "idf": 0.0, "tf": 0, "in_doc": false}, {"token": "seorang", "contribution": 0.0, "idf": 0.0, "tf": 0, "in_doc": false}, {"token": "dituntut", "contribution": 0.0, "idf": 0.0, "tf": 0, "in_doc": false}, {"token": "secara", "contribution": 0.0, "idf": 0.0, "tf": 0, "in_doc": false}, {"token": "perdata", "contribution": 0.0, "idf": 0.0, "tf": 0, "in_doc": false}, {"token": "atas", "contribution": 0.0, "idf": 0.0, "tf": 0, "in_doc": false}, {"token": "tindakan", "contribution": 0.0, "idf": 0.0, "tf": 0, "in_doc": false}, {"token": "kekerasan", "contribution": 0.0, "idf": 0.0, "tf": 0, "in_doc": false}, {"token": "fisik", "contribution": 0.0, "idf": 0.0, "tf": 0, "in_doc": false}, {"token": "verbal", "contribution": 0.0, "idf": 0.0, "tf": 0, "in_doc": false}, {"token": "pemasangan", "contribution": 0.0, "idf": 0.0, "tf": 0, "in_doc": false}, {"token": "kamera", "contribution": 0.0, "idf": 0.0, "tf": 0, "in_doc": false}, {"token": "pengintai", "contribution": 0.0, "idf": 0.0, "tf": 0, "in_doc": false}], "doc_highlights": [{"start": 149, "end": 154, "token": "suami", "intensity": 0.501, "score": 3.6843}, {"start": 155, "end": 160, "token": "istri", "intensity": 0.748, "score": 5.4972}, {"start": 208, "end": 211, "token": "dan", "intensity": 0.318, "score": 2.3363}, {"start": 237, "end": 241, "token": "izin", "intensity": 1.0, "score": 7.3525}, {"start": 284, "end": 288, "token": "izin", "intensity": 1.0, "score": 7.3525}, {"start": 348, "end": 352, "token": "izin", "intensity": 1.0, "score": 7.3525}, {"start": 368, "end": 371, "token": "dan", "intensity": 0.318, "score": 2.3363}, {"start": 401, "end": 405, "token": "izin", "intensity": 1.0, "score": 7.3525}, {"start": 422, "end": 426, "token": "izin", "intensity": 1.0, "score": 7.3525}, {"start": 436, "end": 441, "token": "dapat", "intensity": 0.15, "score": 1.1021}, {"start": 452, "end": 456, "token": "pada", "intensity": 0.179, "score": 1.314}, {"start": 555, "end": 560, "token": "suami", "intensity": 0.501, "score": 3.6843}, {"start": 561, "end": 566, "token": "istri", "intensity": 0.748, "score": 5.4972}, {"start": 619, "end": 623, "token": "izin", "intensity": 1.0, "score": 7.3525}, {"start": 671, "end": 674, "token": "dan", "intensity": 0.318, "score": 2.3363}, {"start": 675, "end": 680, "token": "suami", "intensity": 0.501, "score": 3.6843}, {"start": 686, "end": 691, "token": "istri", "intensity": 0.748, "score": 5.4972}, {"start": 784, "end": 787, "token": "dan", "intensity": 0.318, "score": 2.3363}, {"start": 822, "end": 826, "token": "izin", "intensity": 1.0, "score": 7.3525}, {"start": 894, "end": 899, "token": "tanpa", "intensity": 0.205, "score": 1.5046}, {"start": 955, "end": 958, "token": "dan", "intensity": 0.318, "score": 2.3363}, {"start": 1074, "end": 1078, "token": "izin", "intensity": 1.0, "score": 7.3525}, {"start": 1098, "end": 1101, "token": "dan", "intensity": 0.318, "score": 2.3363}], "query_highlights": [{"start": 15, "end": 20, "token": "suami", "intensity": 0.501, "score": 3.6843}, {"start": 21, "end": 26, "token": "dapat", "intensity": 0.15, "score": 1.1021}, {"start": 90, "end": 93, "token": "dan", "intensity": 0.318, "score": 2.3363}, {"start": 122, "end": 126, "token": "pada", "intensity": 0.179, "score": 1.314}, {"start": 135, "end": 140, "token": "istri", "intensity": 0.748, "score": 5.4972}, {"start": 141, "end": 146, "token": "tanpa", "intensity": 0.205, "score": 1.5046}, {"start": 147, "end": 151, "token": "izin", "intensity": 1.0, "score": 7.3525}]}, {"rank": 7, "doc_id": "113", "title": "Pasal 113", "bm25_score": 16.0081, "is_relevant": false, "per_token": [{"token": "suami", "contribution": 4.6985, "idf": 3.4426, "tf": 2, "in_doc": true}, {"token": "secara", "contribution": 4.5191, "idf": 3.3111, "tf": 2, "in_doc": true}, {"token": "izin", "contribution": 4.1435, "idf": 4.4144, "tf": 1, "in_doc": true}, {"token": "tanpa", "contribution": 2.829, "idf": 3.014, "tf": 1, "in_doc": true}, {"token": "seorang", "contribution": 2.7651, "idf": 2.9459, "tf": 1, "in_doc": true}, {"token": "pada", "contribution": 2.4707, "idf": 2.6323, "tf": 1, "in_doc": true}, {"token": "atas", "contribution": 2.2172, "idf": 2.3622, "tf": 1, "in_doc": true}, {"token": "apakah", "contribution": 0.0, "idf": 0.0, "tf": 0, "in_doc": false}, {"token": "dapat", "contribution": 0.0, "idf": 0.0, "tf": 0, "in_doc": false}, {"token": "dituntut", "contribution": 0.0, "idf": 0.0, "tf": 0, "in_doc": false}, {"token": "perdata", "contribution": 0.0, "idf": 0.0, "tf": 0, "in_doc": false}, {"token": "tindakan", "contribution": 0.0, "idf": 0.0, "tf": 0, "in_doc": false}, {"token": "kekerasan", "contribution": 0.0, "idf": 0.0, "tf": 0, "in_doc": false}, {"token": "fisik", "contribution": 0.0, "idf": 0.0, "tf": 0, "in_doc": false}, {"token": "verbal", "contribution": 0.0, "idf": 0.0, "tf": 0, "in_doc": false}, {"token": "dan", "contribution": 0.0, "idf": 0.0, "tf": 0, "in_doc": false}, {"token": "pemasangan", "contribution": 0.0, "idf": 0.0, "tf": 0, "in_doc": false}, {"token": "kamera", "contribution": 0.0, "idf": 0.0, "tf": 0, "in_doc": false}, {"token": "pengintai", "contribution": 0.0, "idf": 0.0, "tf": 0, "in_doc": false}, {"token": "pakaian", "contribution": 0.0, "idf": 0.0, "tf": 0, "in_doc": false}], "doc_highlights": [{"start": 11, "end": 18, "token": "seorang", "intensity": 0.589, "score": 2.7651}, {"start": 31, "end": 35, "token": "atas", "intensity": 0.472, "score": 2.2172}, {"start": 83, "end": 87, "token": "izin", "intensity": 0.882, "score": 4.1435}, {"start": 98, "end": 104, "token": "secara", "intensity": 0.962, "score": 4.5191}, {"start": 116, "end": 122, "token": "secara", "intensity": 0.962, "score": 4.5191}, {"start": 202, "end": 207, "token": "tanpa", "intensity": 0.602, "score": 2.829}, {"start": 291, "end": 296, "token": "suami", "intensity": 1.0, "score": 4.6985}, {"start": 310, "end": 314, "token": "pada", "intensity": 0.526, "score": 2.4707}, {"start": 339, "end": 344, "token": "suami", "intensity": 1.0, "score": 4.6985}], "query_highlights": [{"start": 7, "end": 14, "token": "seorang", "intensity": 0.589, "score": 2.7651}, {"start": 15, "end": 20, "token": "suami", "intensity": 1.0, "score": 4.6985}, {"start": 36, "end": 42, "token": "secara", "intensity": 0.962, "score": 4.5191}, {"start": 51, "end": 55, "token": "atas", "intensity": 0.472, "score": 2.2172}, {"start": 122, "end": 126, "token": "pada", "intensity": 0.526, "score": 2.4707}, {"start": 141, "end": 146, "token": "tanpa", "intensity": 0.602, "score": 2.829}, {"start": 147, "end": 151, "token": "izin", "intensity": 0.882, "score": 4.1435}]}, {"rank": 8, "doc_id": "901", "title": "Pasal 901", "bm25_score": 15.3228, "is_relevant": false, "per_token": [{"token": "izin", "contribution": 4.9246, "idf": 4.4144, "tf": 1, "in_doc": true}, {"token": "suami", "contribution": 3.8404, "idf": 3.4426, "tf": 1, "in_doc": true}, {"token": "dapat", "contribution": 3.4059, "idf": 2.2077, "tf": 2, "in_doc": true}, {"token": "tanpa", "contribution": 3.3623, "idf": 3.014, "tf": 1, "in_doc": true}, {"token": "seorang", "contribution": 3.2864, "idf": 2.9459, "tf": 1, "in_doc": true}, {"token": "pada", "contribution": 2.9365, "idf": 2.6323, "tf": 1, "in_doc": true}, {"token": "dan", "contribution": 2.4048, "idf": 1.5588, "tf": 2, "in_doc": true}, {"token": "apakah", "contribution": 0.0, "idf": 0.0, "tf": 0, "in_doc": false}, {"token": "dituntut", "contribution": 0.0, "idf": 0.0, "tf": 0, "in_doc": false}, {"token": "secara", "contribution": 0.0, "idf": 0.0, "tf": 0, "in_doc": false}, {"token": "perdata", "contribution": 0.0, "idf": 0.0, "tf": 0, "in_doc": false}, {"token": "atas", "contribution": 0.0, "idf": 0.0, "tf": 0, "in_doc": false}, {"token": "tindakan", "contribution": 0.0, "idf": 0.0, "tf": 0, "in_doc": false}, {"token": "kekerasan", "contribution": 0.0, "idf": 0.0, "tf": 0, "in_doc": false}, {"token": "fisik", "contribution": 0.0, "idf": 0.0, "tf": 0, "in_doc": false}, {"token": "verbal", "contribution": 0.0, "idf": 0.0, "tf": 0, "in_doc": false}, {"token": "pemasangan", "contribution": 0.0, "idf": 0.0, "tf": 0, "in_doc": false}, {"token": "kamera", "contribution": 0.0, "idf": 0.0, "tf": 0, "in_doc": false}, {"token": "pengintai", "contribution": 0.0, "idf": 0.0, "tf": 0, "in_doc": false}, {"token": "pakaian", "contribution": 0.0, "idf": 0.0, "tf": 0, "in_doc": false}], "doc_highlights": [{"start": 11, "end": 18, "token": "seorang", "intensity": 0.667, "score": 3.2864}, {"start": 19, "end": 24, "token": "suami", "intensity": 0.78, "score": 3.8404}, {"start": 43, "end": 48, "token": "dapat", "intensity": 0.692, "score": 3.4059}, {"start": 71, "end": 74, "token": "dan", "intensity": 0.488, "score": 2.4048}, {"start": 143, "end": 148, "token": "tanpa", "intensity": 0.683, "score": 3.3623}, {"start": 149, "end": 153, "token": "izin", "intensity": 1.0, "score": 4.9246}, {"start": 164, "end": 167, "token": "dan", "intensity": 0.488, "score": 2.4048}, {"start": 195, "end": 199, "token": "pada", "intensity": 0.596, "score": 2.9365}, {"start": 237, "end": 242, "token": "dapat", "intensity": 0.692, "score": 3.4059}], "query_highlights": [{"start": 7, "end": 14, "token": "seorang", "intensity": 0.667, "score": 3.2864}, {"start": 15, "end": 20, "token": "suami", "intensity": 0.78, "score": 3.8404}, {"start": 21, "end": 26, "token": "dapat", "intensity": 0.692, "score": 3.4059}, {"start": 90, "end": 93, "token": "dan", "intensity": 0.488, "score": 2.4048}, {"start": 122, "end": 126, "token": "pada", "intensity": 0.596, "score": 2.9365}, {"start": 141, "end": 146, "token": "tanpa", "intensity": 0.683, "score": 3.3623}, {"start": 147, "end": 151, "token": "izin", "intensity": 1.0, "score": 4.9246}]}, {"rank": 9, "doc_id": "108", "title": "Pasal 108", "bm25_score": 15.0911, "is_relevant": false, "per_token": [{"token": "izin", "contribution": 5.6965, "idf": 4.4144, "tf": 2, "in_doc": true}, {"token": "suami", "contribution": 5.2966, "idf": 3.4426, "tf": 3, "in_doc": true}, {"token": "tanpa", "contribution": 3.8893, "idf": 3.014, "tf": 2, "in_doc": true}, {"token": "secara", "contribution": 2.8795, "idf": 3.3111, "tf": 1, "in_doc": true}, {"token": "seorang", "contribution": 2.5619, "idf": 2.9459, "tf": 1, "in_doc": true}, {"token": "dapat", "contribution": 1.92, "idf": 2.2077, "tf": 1, "in_doc": true}, {"token": "apakah", "contribution": 0.0, "idf": 0.0, "tf": 0, "in_doc": false}, {"token": "dituntut", "contribution": 0.0, "idf": 0.0, "tf": 0, "in_doc": false}, {"token": "perdata", "contribution": 0.0, "idf": 0.0, "tf": 0, "in_doc": false}, {"token": "atas", "contribution": 0.0, "idf": 0.0, "tf": 0, "in_doc": false}, {"token": "tindakan", "contribution": 0.0, "idf": 0.0, "tf": 0, "in_doc": false}, {"token": "kekerasan", "contribution": 0.0, "idf": 0.0, "tf": 0, "in_doc": false}, {"token": "fisik", "contribution": 0.0, "idf": 0.0, "tf": 0, "in_doc": false}, {"token": "verbal", "contribution": 0.0, "idf": 0.0, "tf": 0, "in_doc": false}, {"token": "dan", "contribution": 0.0, "idf": 0.0, "tf": 0, "in_doc": false}, {"token": "pemasangan", "contribution": 0.0, "idf": 0.0, "tf": 0, "in_doc": false}, {"token": "kamera", "contribution": 0.0, "idf": 0.0, "tf": 0, "in_doc": false}, {"token": "pengintai", "contribution": 0.0, "idf": 0.0, "tf": 0, "in_doc": false}, {"token": "pada", "contribution": 0.0, "idf": 0.0, "tf": 0, "in_doc": false}, {"token": "pakaian", "contribution": 0.0, "idf": 0.0, "tf": 0, "in_doc": false}], "doc_highlights": [{"start": 11, "end": 18, "token": "seorang", "intensity": 0.45, "score": 2.5619}, {"start": 109, "end": 114, "token": "dapat", "intensity": 0.337, "score": 1.92}, {"start": 187, "end": 193, "token": "secara", "intensity": 0.505, "score": 2.8795}, {"start": 225, "end": 230, "token": "tanpa", "intensity": 0.683, "score": 3.8893}, {"start": 239, "end": 244, "token": "suami", "intensity": 0.93, "score": 5.2966}, {"start": 261, "end": 265, "token": "izin", "intensity": 1.0, "score": 5.6965}, {"start": 286, "end": 291, "token": "suami", "intensity": 0.93, "score": 5.2966}, {"start": 472, "end": 477, "token": "tanpa", "intensity": 0.683, "score": 3.8893}, {"start": 478, "end": 482, "token": "izin", "intensity": 1.0, "score": 5.6965}, {"start": 494, "end": 499, "token": "suami", "intensity": 0.93, "score": 5.2966}], "query_highlights": [{"start": 7, "end": 14, "token": "seorang", "intensity": 0.45, "score": 2.5619}, {"start": 15, "end": 20, "token": "suami", "intensity": 0.93, "score": 5.2966}, {"start": 21, "end": 26, "token": "dapat", "intensity": 0.337, "score": 1.92}, {"start": 36, "end": 42, "token": "secara", "intensity": 0.505, "score": 2.8795}, {"start": 141, "end": 146, "token": "tanpa", "intensity": 0.683, "score": 3.8893}, {"start": 147, "end": 151, "token": "izin", "intensity": 1.0, "score": 5.6965}]}, {"rank": 10, "doc_id": "89", "title": "Pasal 89", "bm25_score": 14.9571, "is_relevant": false, "per_token": [{"token": "istri", "contribution": 6.5217, "idf": 5.1366, "tf": 2, "in_doc": true}, {"token": "dituntut", "contribution": 4.0598, "idf": 4.7711, "tf": 1, "in_doc": true}, {"token": "suami", "contribution": 2.9293, "idf": 3.4426, "tf": 1, "in_doc": true}, {"token": "seorang", "contribution": 2.5067, "idf": 2.9459, "tf": 1, "in_doc": true}, {"token": "pada", "contribution": 2.2398, "idf": 2.6323, "tf": 1, "in_doc": true}, {"token": "dapat", "contribution": 1.8786, "idf": 2.2077, "tf": 1, "in_doc": true}, {"token": "apakah", "contribution": 0.0, "idf": 0.0, "tf": 0, "in_doc": false}, {"token": "secara", "contribution": 0.0, "idf": 0.0, "tf": 0, "in_doc": false}, {"token": "perdata", "contribution": 0.0, "idf": 0.0, "tf": 0, "in_doc": false}, {"token": "atas", "contribution": 0.0, "idf": 0.0, "tf": 0, "in_doc": false}, {"token": "tindakan", "contribution": 0.0, "idf": 0.0, "tf": 0, "in_doc": false}, {"token": "kekerasan", "contribution": 0.0, "idf": 0.0, "tf": 0, "in_doc": false}, {"token": "fisik", "contribution": 0.0, "idf": 0.0, "tf": 0, "in_doc": false}, {"token": "verbal", "contribution": 0.0, "idf": 0.0, "tf": 0, "in_doc": false}, {"token": "dan", "contribution": 0.0, "idf": 0.0, "tf": 0, "in_doc": false}, {"token": "pemasangan", "contribution": 0.0, "idf": 0.0, "tf": 0, "in_doc": false}, {"token": "kamera", "contribution": 0.0, "idf": 0.0, "tf": 0, "in_doc": false}, {"token": "pengintai", "contribution": 0.0, "idf": 0.0, "tf": 0, "in_doc": false}, {"token": "pakaian", "contribution": 0.0, "idf": 0.0, "tf": 0, "in_doc": false}, {"token": "tanpa", "contribution": 0.0, "idf": 0.0, "tf": 0, "in_doc": false}], "doc_highlights": [{"start": 142, "end": 150, "token": "dituntut", "intensity": 0.623, "score": 4.0598}, {"start": 255, "end": 260, "token": "dapat", "intensity": 0.288, "score": 1.8786}, {"start": 279, "end": 283, "token": "pada", "intensity": 0.343, "score": 2.2398}, {"start": 334, "end": 341, "token": "seorang", "intensity": 0.384, "score": 2.5067}, {"start": 353, "end": 358, "token": "suami", "intensity": 0.449, "score": 2.9293}, {"start": 359, "end": 364, "token": "istri", "intensity": 1.0, "score": 6.5217}, {"start": 411, "end": 416, "token": "istri", "intensity": 1.0, "score": 6.5217}], "query_highlights": [{"start": 7, "end": 14, "token": "seorang", "intensity": 0.384, "score": 2.5067}, {"start": 15, "end": 20, "token": "suami", "intensity": 0.449, "score": 2.9293}, {"start": 21, "end": 26, "token": "dapat", "intensity": 0.288, "score": 1.8786}, {"start": 27, "end": 35, "token": "dituntut", "intensity": 0.623, "score": 4.0598}, {"start": 122, "end": 126, "token": "pada", "intensity": 0.343, "score": 2.2398}, {"start": 135, "end": 140, "token": "istri", "intensity": 1.0, "score": 6.5217}]}, {"rank": 11, "doc_id": "118", "title": "Pasal 118", "bm25_score": 14.5662, "is_relevant": false, "per_token": [{"token": "izin", "contribution": 7.0514, "idf": 4.4144, "tf": 1, "in_doc": true}, {"token": "suami", "contribution": 5.499, "idf": 3.4426, "tf": 1, "in_doc": true}, {"token": "tanpa", "contribution": 4.8143, "idf": 3.014, "tf": 1, "in_doc": true}, {"token": "dapat", "contribution": 3.5265, "idf": 2.2077, "tf": 1, "in_doc": true}, {"token": "apakah", "contribution": 0.0, "idf": 0.0, "tf": 0, "in_doc": false}, {"token": "seorang", "contribution": 0.0, "idf": 0.0, "tf": 0, "in_doc": false}, {"token": "dituntut", "contribution": 0.0, "idf": 0.0, "tf": 0, "in_doc": false}, {"token": "secara", "contribution": 0.0, "idf": 0.0, "tf": 0, "in_doc": false}, {"token": "perdata", "contribution": 0.0, "idf": 0.0, "tf": 0, "in_doc": false}, {"token": "atas", "contribution": 0.0, "idf": 0.0, "tf": 0, "in_doc": false}, {"token": "tindakan", "contribution": 0.0, "idf": 0.0, "tf": 0, "in_doc": false}, {"token": "kekerasan", "contribution": 0.0, "idf": 0.0, "tf": 0, "in_doc": false}, {"token": "fisik", "contribution": 0.0, "idf": 0.0, "tf": 0, "in_doc": false}, {"token": "verbal", "contribution": 0.0, "idf": 0.0, "tf": 0, "in_doc": false}, {"token": "dan", "contribution": 0.0, "idf": 0.0, "tf": 0, "in_doc": false}, {"token": "pemasangan", "contribution": 0.0, "idf": 0.0, "tf": 0, "in_doc": false}, {"token": "kamera", "contribution": 0.0, "idf": 0.0, "tf": 0, "in_doc": false}, {"token": "pengintai", "contribution": 0.0, "idf": 0.0, "tf": 0, "in_doc": false}, {"token": "pada", "contribution": 0.0, "idf": 0.0, "tf": 0, "in_doc": false}, {"token": "pakaian", "contribution": 0.0, "idf": 0.0, "tf": 0, "in_doc": false}], "doc_highlights": [{"start": 18, "end": 23, "token": "dapat", "intensity": 0.5, "score": 3.5265}, {"start": 39, "end": 44, "token": "tanpa", "intensity": 0.683, "score": 4.8143}, {"start": 45, "end": 49, "token": "izin", "intensity": 1.0, "score": 7.0514}, {"start": 50, "end": 55, "token": "suami", "intensity": 0.78, "score": 5.499}], "query_highlights": [{"start": 15, "end": 20, "token": "suami", "intensity": 0.78, "score": 5.499}, {"start": 21, "end": 26, "token": "dapat", "intensity": 0.5, "score": 3.5265}, {"start": 141, "end": 146, "token": "tanpa", "intensity": 0.683, "score": 4.8143}, {"start": 147, "end": 151, "token": "izin", "intensity": 1.0, "score": 7.0514}]}, {"rank": 12, "doc_id": "1467", "title": "Pasal 1467", "bm25_score": 14.224, "is_relevant": false, "per_token": [{"token": "istri", "contribution": 8.9189, "idf": 5.1366, "tf": 7, "in_doc": true}, {"token": "suami", "contribution": 4.2476, "idf": 3.4426, "tf": 3, "in_doc": true}, {"token": "seorang", "contribution": 2.9003, "idf": 2.9459, "tf": 2, "in_doc": true}, {"token": "secara", "contribution": 2.0295, "idf": 3.3111, "tf": 1, "in_doc": true}, {"token": "dapat", "contribution": 1.3532, "idf": 2.2077, "tf": 1, "in_doc": true}, {"token": "apakah", "contribution": 0.0, "idf": 0.0, "tf": 0, "in_doc": false}, {"token": "dituntut", "contribution": 0.0, "idf": 0.0, "tf": 0, "in_doc": false}, {"token": "perdata", "contribution": 0.0, "idf": 0.0, "tf": 0, "in_doc": false}, {"token": "atas", "contribution": 0.0, "idf": 0.0, "tf": 0, "in_doc": false}, {"token": "tindakan", "contribution": 0.0, "idf": 0.0, "tf": 0, "in_doc": false}, {"token": "kekerasan", "contribution": 0.0, "idf": 0.0, "tf": 0, "in_doc": false}, {"token": "fisik", "contribution": 0.0, "idf": 0.0, "tf": 0, "in_doc": false}, {"token": "verbal", "contribution": 0.0, "idf": 0.0, "tf": 0, "in_doc": false}, {"token": "dan", "contribution": 0.0, "idf": 0.0, "tf": 0, "in_doc": false}, {"token": "pemasangan", "contribution": 0.0, "idf": 0.0, "tf": 0, "in_doc": false}, {"token": "kamera", "contribution": 0.0, "idf": 0.0, "tf": 0, "in_doc": false}, {"token": "pengintai", "contribution": 0.0, "idf": 0.0, "tf": 0, "in_doc": false}, {"token": "pada", "contribution": 0.0, "idf": 0.0, "tf": 0, "in_doc": false}, {"token": "pakaian", "contribution": 0.0, "idf": 0.0, "tf": 0, "in_doc": false}, {"token": "tanpa", "contribution": 0.0, "idf": 0.0, "tf": 0, "in_doc": false}], "doc_highlights": [{"start": 19, "end": 24, "token": "suami", "intensity": 0.476, "score": 4.2476}, {"start": 25, "end": 30, "token": "istri", "intensity": 1.0, "score": 8.9189}, {"start": 37, "end": 42, "token": "dapat", "intensity": 0.152, "score": 1.3532}, {"start": 102, "end": 109, "token": "seorang", "intensity": 0.325, "score": 2.9003}, {"start": 110, "end": 115, "token": "suami", "intensity": 0.476, "score": 4.2476}, {"start": 121, "end": 126, "token": "istri", "intensity": 1.0, "score": 8.9189}, {"start": 160, "end": 165, "token": "istri", "intensity": 1.0, "score": 8.9189}, {"start": 239, "end": 244, "token": "istri", "intensity": 1.0, "score": 8.9189}, {"start": 312, "end": 319, "token": "seorang", "intensity": 0.325, "score": 2.9003}, {"start": 320, "end": 325, "token": "suami", "intensity": 0.476, "score": 4.2476}, {"start": 410, "end": 415, "token": "istri", "intensity": 1.0, "score": 8.9189}, {"start": 447, "end": 452, "token": "istri", "intensity": 1.0, "score": 8.9189}, {"start": 525, "end": 530, "token": "istri", "intensity": 1.0, "score": 8.9189}, {"start": 856, "end": 862, "token": "secara", "intensity": 0.228, "score": 2.0295}], "query_highlights": [{"start": 7, "end": 14, "token": "seorang", "intensity": 0.325, "score": 2.9003}, {"start": 15, "end": 20, "token": "suami", "intensity": 0.476, "score": 4.2476}, {"start": 21, "end": 26, "token": "dapat", "intensity": 0.152, "score": 1.3532}, {"start": 36, "end": 42, "token": "secara", "intensity": 0.228, "score": 2.0295}, {"start": 135, "end": 140, "token": "istri", "intensity": 1.0, "score": 8.9189}]}, {"rank": 13, "doc_id": "447", "title": "Pasal 447", "bm25_score": 14.1331, "is_relevant": false, "per_token": [{"token": "tindakan", "contribution": 8.5175, "idf": 5.1972, "tf": 2, "in_doc": true}, {"token": "perdata", "contribution": 5.8666, "idf": 4.8128, "tf": 1, "in_doc": true}, {"token": "pada", "contribution": 3.2086, "idf": 2.6323, "tf": 1, "in_doc": true}, {"token": "dan", "contribution": 1.9001, "idf": 1.5588, "tf": 1, "in_doc": true}, {"token": "apakah", "contribution": 0.0, "idf": 0.0, "tf": 0, "in_doc": false}, {"token": "seorang", "contribution": 0.0, "idf": 0.0, "tf": 0, "in_doc": false}, {"token": "suami", "contribution": 0.0, "idf": 0.0, "tf": 0, "in_doc": false}, {"token": "dapat", "contribution": 0.0, "idf": 0.0, "tf": 0, "in_doc": false}, {"token": "dituntut", "contribution": 0.0, "idf": 0.0, "tf": 0, "in_doc": false}, {"token": "secara", "contribution": 0.0, "idf": 0.0, "tf": 0, "in_doc": false}, {"token": "atas", "contribution": 0.0, "idf": 0.0, "tf": 0, "in_doc": false}, {"token": "kekerasan", "contribution": 0.0, "idf": 0.0, "tf": 0, "in_doc": false}, {"token": "fisik", "contribution": 0.0, "idf": 0.0, "tf": 0, "in_doc": false}, {"token": "verbal", "contribution": 0.0, "idf": 0.0, "tf": 0, "in_doc": false}, {"token": "pemasangan", "contribution": 0.0, "idf": 0.0, "tf": 0, "in_doc": false}, {"token": "kamera", "contribution": 0.0, "idf": 0.0, "tf": 0, "in_doc": false}, {"token": "pengintai", "contribution": 0.0, "idf": 0.0, "tf": 0, "in_doc": false}, {"token": "pakaian", "contribution": 0.0, "idf": 0.0, "tf": 0, "in_doc": false}, {"token": "istri", "contribution": 0.0, "idf": 0.0, "tf": 0, "in_doc": false}, {"token": "tanpa", "contribution": 0.0, "idf": 0.0, "tf": 0, "in_doc": false}], "doc_highlights": [{"start": 24, "end": 31, "token": "perdata", "intensity": 0.689, "score": 5.8666}, {"start": 115, "end": 118, "token": "dan", "intensity": 0.223, "score": 1.9001}, {"start": 185, "end": 189, "token": "pada", "intensity": 0.377, "score": 3.2086}, {"start": 195, "end": 203, "token": "tindakan", "intensity": 1.0, "score": 8.5175}, {"start": 204, "end": 212, "token": "tindakan", "intensity": 1.0, "score": 8.5175}], "query_highlights": [{"start": 43, "end": 50, "token": "perdata", "intensity": 0.689, "score": 5.8666}, {"start": 56, "end": 64, "token": "tindakan", "intensity": 1.0, "score": 8.5175}, {"start": 90, "end": 93, "token": "dan", "intensity": 0.223, "score": 1.9001}, {"start": 122, "end": 126, "token": "pada", "intensity": 0.377, "score": 3.2086}]}, {"rank": 14, "doc_id": "91", "title": "Pasal 91", "bm25_score": 13.947, "is_relevant": false, "per_token": [{"token": "izin", "contribution": 4.5151, "idf": 4.4144, "tf": 2, "in_doc": true}, {"token": "istri", "contribution": 3.3024, "idf": 5.1366, "tf": 1, "in_doc": true}, {"token": "tanpa", "contribution": 3.0827, "idf": 3.014, "tf": 2, "in_doc": true}, {"token": "dituntut", "contribution": 3.0674, "idf": 4.7711, "tf": 1, "in_doc": true}, {"token": "suami", "contribution": 2.2133, "idf": 3.4426, "tf": 1, "in_doc": true}, {"token": "secara", "contribution": 2.1287, "idf": 3.3111, "tf": 1, "in_doc": true}, {"token": "dan", "contribution": 1.5943, "idf": 1.5588, "tf": 2, "in_doc": true}, {"token": "apakah", "contribution": 0.0, "idf": 0.0, "tf": 0, "in_doc": false}, {"token": "seorang", "contribution": 0.0, "idf": 0.0, "tf": 0, "in_doc": false}, {"token": "dapat", "contribution": 0.0, "idf": 0.0, "tf": 0, "in_doc": false}, {"token": "perdata", "contribution": 0.0, "idf": 0.0, "tf": 0, "in_doc": false}, {"token": "atas", "contribution": 0.0, "idf": 0.0, "tf": 0, "in_doc": false}, {"token": "tindakan", "contribution": 0.0, "idf": 0.0, "tf": 0, "in_doc": false}, {"token": "kekerasan", "contribution": 0.0, "idf": 0.0, "tf": 0, "in_doc": false}, {"token": "fisik", "contribution": 0.0, "idf": 0.0, "tf": 0, "in_doc": false}, {"token": "verbal", "contribution": 0.0, "idf": 0.0, "tf": 0, "in_doc": false}, {"token": "pemasangan", "contribution": 0.0, "idf": 0.0, "tf": 0, "in_doc": false}, {"token": "kamera", "contribution": 0.0, "idf": 0.0, "tf": 0, "in_doc": false}, {"token": "pengintai", "contribution": 0.0, "idf": 0.0, "tf": 0, "in_doc": false}, {"token": "pada", "contribution": 0.0, "idf": 0.0, "tf": 0, "in_doc": false}], "doc_highlights": [{"start": 45, "end": 50, "token": "tanpa", "intensity": 0.683, "score": 3.0827}, {"start": 51, "end": 55, "token": "izin", "intensity": 1.0, "score": 4.5151}, {"start": 122, "end": 126, "token": "izin", "intensity": 1.0, "score": 4.5151}, {"start": 205, "end": 208, "token": "dan", "intensity": 0.353, "score": 1.5943}, {"start": 247, "end": 255, "token": "dituntut", "intensity": 0.679, "score": 3.0674}, {"start": 440, "end": 446, "token": "secara", "intensity": 0.471, "score": 2.1287}, {"start": 507, "end": 512, "token": "tanpa", "intensity": 0.683, "score": 3.0827}, {"start": 530, "end": 533, "token": "dan", "intensity": 0.353, "score": 1.5943}, {"start": 734, "end": 739, "token": "suami", "intensity": 0.49, "score": 2.2133}, {"start": 740, "end": 745, "token": "istri", "intensity": 0.731, "score": 3.3024}], "query_highlights": [{"start": 15, "end": 20, "token": "suami", "intensity": 0.49, "score": 2.2133}, {"start": 27, "end": 35, "token": "dituntut", "intensity": 0.679, "score": 3.0674}, {"start": 36, "end": 42, "token": "secara", "intensity": 0.471, "score": 2.1287}, {"start": 90, "end": 93, "token": "dan", "intensity": 0.353, "score": 1.5943}, {"start": 135, "end": 140, "token": "istri", "intensity": 0.731, "score": 3.3024}, {"start": 141, "end": 146, "token": "tanpa", "intensity": 0.683, "score": 3.0827}, {"start": 147, "end": 151, "token": "izin", "intensity": 1.0, "score": 4.5151}]}, {"rank": 15, "doc_id": "1429", "title": "Pasal 1429", "bm25_score": 13.4517, "is_relevant": false, "per_token": [{"token": "dituntut", "contribution": 6.7451, "idf": 4.7711, "tf": 2, "in_doc": true}, {"token": "secara", "contribution": 3.2631, "idf": 3.3111, "tf": 1, "in_doc": true}, {"token": "tanpa", "contribution": 2.9703, "idf": 3.014, "tf": 1, "in_doc": true}, {"token": "pada", "contribution": 2.5941, "idf": 2.6323, "tf": 1, "in_doc": true}, {"token": "dapat", "contribution": 2.1758, "idf": 2.2077, "tf": 1, "in_doc": true}, {"token": "dan", "contribution": 1.5362, "idf": 1.5588, "tf": 1, "in_doc": true}, {"token": "apakah", "contribution": 0.0, "idf": 0.0, "tf": 0, "in_doc": false}, {"token": "seorang", "contribution": 0.0, "idf": 0.0, "tf": 0, "in_doc": false}, {"token": "suami", "contribution": 0.0, "idf": 0.0, "tf": 0, "in_doc": false}, {"token": "perdata", "contribution": 0.0, "idf": 0.0, "tf": 0, "in_doc": false}, {"token": "atas", "contribution": 0.0, "idf": 0.0, "tf": 0, "in_doc": false}, {"token": "tindakan", "contribution": 0.0, "idf": 0.0, "tf": 0, "in_doc": false}, {"token": "kekerasan", "contribution": 0.0, "idf": 0.0, "tf": 0, "in_doc": false}, {"token": "fisik", "contribution": 0.0, "idf": 0.0, "tf": 0, "in_doc": false}, {"token": "verbal", "contribution": 0.0, "idf": 0.0, "tf": 0, "in_doc": false}, {"token": "pemasangan", "contribution": 0.0, "idf": 0.0, "tf": 0, "in_doc": false}, {"token": "kamera", "contribution": 0.0, "idf": 0.0, "tf": 0, "in_doc": false}, {"token": "pengintai", "contribution": 0.0, "idf": 0.0, "tf": 0, "in_doc": false}, {"token": "pakaian", "contribution": 0.0, "idf": 0.0, "tf": 0, "in_doc": false}, {"token": "istri", "contribution": 0.0, "idf": 0.0, "tf": 0, "in_doc": false}], "doc_highlights": [{"start": 31, "end": 36, "token": "tanpa", "intensity": 0.44, "score": 2.9703}, {"start": 103, "end": 111, "token": "dituntut", "intensity": 1.0, "score": 6.7451}, {"start": 143, "end": 149, "token": "secara", "intensity": 0.484, "score": 3.2631}, {"start": 183, "end": 186, "token": "dan", "intensity": 0.228, "score": 1.5362}, {"start": 216, "end": 224, "token": "dituntut", "intensity": 1.0, "score": 6.7451}, {"start": 331, "end": 335, "token": "pada", "intensity": 0.385, "score": 2.5941}, {"start": 379, "end": 384, "token": "dapat", "intensity": 0.323, "score": 2.1758}], "query_highlights": [{"start": 21, "end": 26, "token": "dapat", "intensity": 0.323, "score": 2.1758}, {"start": 27, "end": 35, "token": "dituntut", "intensity": 1.0, "score": 6.7451}, {"start": 36, "end": 42, "token": "secara", "intensity": 0.484, "score": 3.2631}, {"start": 90, "end": 93, "token": "dan", "intensity": 0.228, "score": 1.5362}, {"start": 122, "end": 126, "token": "pada", "intensity": 0.385, "score": 2.5941}, {"start": 141, "end": 146, "token": "tanpa", "intensity": 0.44, "score": 2.9703}]}, {"rank": 16, "doc_id": "215", "title": "Pasal 215", "bm25_score": 13.3108, "is_relevant": false, "per_token": [{"token": "tindakan", "contribution": 7.4815, "idf": 5.1972, "tf": 2, "in_doc": true}, {"token": "suami", "contribution": 4.9557, "idf": 3.4426, "tf": 2, "in_doc": true}, {"token": "perdata", "contribution": 4.8646, "idf": 4.8128, "tf": 1, "in_doc": true}, {"token": "apakah", "contribution": 0.0, "idf": 0.0, "tf": 0, "in_doc": false}, {"token": "seorang", "contribution": 0.0, "idf": 0.0, "tf": 0, "in_doc": false}, {"token": "dapat", "contribution": 0.0, "idf": 0.0, "tf": 0, "in_doc": false}, {"token": "dituntut", "contribution": 0.0, "idf": 0.0, "tf": 0, "in_doc": false}, {"token": "secara", "contribution": 0.0, "idf": 0.0, "tf": 0, "in_doc": false}, {"token": "atas", "contribution": 0.0, "idf": 0.0, "tf": 0, "in_doc": false}, {"token": "kekerasan", "contribution": 0.0, "idf": 0.0, "tf": 0, "in_doc": false}, {"token": "fisik", "contribution": 0.0, "idf": 0.0, "tf": 0, "in_doc": false}, {"token": "verbal", "contribution": 0.0, "idf": 0.0, "tf": 0, "in_doc": false}, {"token": "dan", "contribution": 0.0, "idf": 0.0, "tf": 0, "in_doc": false}, {"token": "pemasangan", "contribution": 0.0, "idf": 0.0, "tf": 0, "in_doc": false}, {"token": "kamera", "contribution": 0.0, "idf": 0.0, "tf": 0, "in_doc": false}, {"token": "pengintai", "contribution": 0.0, "idf": 0.0, "tf": 0, "in_doc": false}, {"token": "pada", "contribution": 0.0, "idf": 0.0, "tf": 0, "in_doc": false}, {"token": "pakaian", "contribution": 0.0, "idf": 0.0, "tf": 0, "in_doc": false}, {"token": "istri", "contribution": 0.0, "idf": 0.0, "tf": 0, "in_doc": false}, {"token": "tanpa", "contribution": 0.0, "idf": 0.0, "tf": 0, "in_doc": false}], "doc_highlights": [{"start": 22, "end": 27, "token": "suami", "intensity": 0.662, "score": 4.9557}, {"start": 190, "end": 198, "token": "tindakan", "intensity": 1.0, "score": 7.4815}, {"start": 199, "end": 207, "token": "tindakan", "intensity": 1.0, "score": 7.4815}, {"start": 277, "end": 284, "token": "perdata", "intensity": 0.65, "score": 4.8646}, {"start": 300, "end": 305, "token": "suami", "intensity": 0.662, "score": 4.9557}], "query_highlights": [{"start": 15, "end": 20, "token": "suami", "intensity": 0.662, "score": 4.9557}, {"start": 43, "end": 50, "token": "perdata", "intensity": 0.65, "score": 4.8646}, {"start": 56, "end": 64, "token": "tindakan", "intensity": 1.0, "score": 7.4815}]}, {"rank": 17, "doc_id": "88", "title": "Pasal 88", "bm25_score": 13.1932, "is_relevant": false, "per_token": [{"token": "istri", "contribution": 6.0361, "idf": 5.1366, "tf": 2, "in_doc": true}, {"token": "suami", "contribution": 4.0455, "idf": 3.4426, "tf": 2, "in_doc": true}, {"token": "dituntut", "contribution": 3.6646, "idf": 4.7711, "tf": 1, "in_doc": true}, {"token": "dan", "contribution": 2.4921, "idf": 1.5588, "tf": 4, "in_doc": true}, {"token": "atas", "contribution": 1.8143, "idf": 2.3622, "tf": 1, "in_doc": true}, {"token": "dapat", "contribution": 1.6957, "idf": 2.2077, "tf": 1, "in_doc": true}, {"token": "apakah", "contribution": 0.0, "idf": 0.0, "tf": 0, "in_doc": false}, {"token": "seorang", "contribution": 0.0, "idf": 0.0, "tf": 0, "in_doc": false}, {"token": "secara", "contribution": 0.0, "idf": 0.0, "tf": 0, "in_doc": false}, {"token": "perdata", "contribution": 0.0, "idf": 0.0, "tf": 0, "in_doc": false}, {"token": "tindakan", "contribution": 0.0, "idf": 0.0, "tf": 0, "in_doc": false}, {"token": "kekerasan", "contribution": 0.0, "idf": 0.0, "tf": 0, "in_doc": false}, {"token": "fisik", "contribution": 0.0, "idf": 0.0, "tf": 0, "in_doc": false}, {"token": "verbal", "contribution": 0.0, "idf": 0.0, "tf": 0, "in_doc": false}, {"token": "pemasangan", "contribution": 0.0, "idf": 0.0, "tf": 0, "in_doc": false}, {"token": "kamera", "contribution": 0.0, "idf": 0.0, "tf": 0, "in_doc": false}, {"token": "pengintai", "contribution": 0.0, "idf": 0.0, "tf": 0, "in_doc": false}, {"token": "pada", "contribution": 0.0, "idf": 0.0, "tf": 0, "in_doc": false}, {"token": "pakaian", "contribution": 0.0, "idf": 0.0, "tf": 0, "in_doc": false}, {"token": "tanpa", "contribution": 0.0, "idf": 0.0, "tf": 0, "in_doc": false}], "doc_highlights": [{"start": 169, "end": 172, "token": "dan", "intensity": 0.413, "score": 2.4921}, {"start": 205, "end": 209, "token": "atas", "intensity": 0.301, "score": 1.8143}, {"start": 229, "end": 232, "token": "dan", "intensity": 0.413, "score": 2.4921}, {"start": 250, "end": 253, "token": "dan", "intensity": 0.413, "score": 2.4921}, {"start": 297, "end": 300, "token": "dan", "intensity": 0.413, "score": 2.4921}, {"start": 392, "end": 400, "token": "dituntut", "intensity": 0.607, "score": 3.6646}, {"start": 406, "end": 411, "token": "suami", "intensity": 0.67, "score": 4.0455}, {"start": 417, "end": 422, "token": "istri", "intensity": 1.0, "score": 6.0361}, {"start": 497, "end": 502, "token": "dapat", "intensity": 0.281, "score": 1.6957}, {"start": 523, "end": 528, "token": "suami", "intensity": 0.67, "score": 4.0455}, {"start": 529, "end": 534, "token": "istri", "intensity": 1.0, "score": 6.0361}], "query_highlights": [{"start": 15, "end": 20, "token": "suami", "intensity": 0.67, "score": 4.0455}, {"start": 21, "end": 26, "token": "dapat", "intensity": 0.281, "score": 1.6957}, {"start": 27, "end": 35, "token": "dituntut", "intensity": 0.607, "score": 3.6646}, {"start": 51, "end": 55, "token": "atas", "intensity": 0.301, "score": 1.8143}, {"start": 90, "end": 93, "token": "dan", "intensity": 0.413, "score": 2.4921}, {"start": 135, "end": 140, "token": "istri", "intensity": 1.0, "score": 6.0361}]}, {"rank": 18, "doc_id": "92", "title": "Pasal 92", "bm25_score": 13.1273, "is_relevant": false, "per_token": [{"token": "istri", "contribution": 6.5895, "idf": 5.1366, "tf": 3, "in_doc": true}, {"token": "suami", "contribution": 4.4164, "idf": 3.4426, "tf": 3, "in_doc": true}, {"token": "dapat", "contribution": 2.8322, "idf": 2.2077, "tf": 3, "in_doc": true}, {"token": "dan", "contribution": 2.6431, "idf": 1.5588, "tf": 6, "in_doc": true}, {"token": "tanpa", "contribution": 1.959, "idf": 3.014, "tf": 1, "in_doc": true}, {"token": "atas", "contribution": 1.5353, "idf": 2.3622, "tf": 1, "in_doc": true}, {"token": "apakah", "contribution": 0.0, "idf": 0.0, "tf": 0, "in_doc": false}, {"token": "seorang", "contribution": 0.0, "idf": 0.0, "tf": 0, "in_doc": false}, {"token": "dituntut", "contribution": 0.0, "idf": 0.0, "tf": 0, "in_doc": false}, {"token": "secara", "contribution": 0.0, "idf": 0.0, "tf": 0, "in_doc": false}, {"token": "perdata", "contribution": 0.0, "idf": 0.0, "tf": 0, "in_doc": false}, {"token": "tindakan", "contribution": 0.0, "idf": 0.0, "tf": 0, "in_doc": false}, {"token": "kekerasan", "contribution": 0.0, "idf": 0.0, "tf": 0, "in_doc": false}, {"token": "fisik", "contribution": 0.0, "idf": 0.0, "tf": 0, "in_doc": false}, {"token": "verbal", "contribution": 0.0, "idf": 0.0, "tf": 0, "in_doc": false}, {"token": "pemasangan", "contribution": 0.0, "idf": 0.0, "tf": 0, "in_doc": false}, {"token": "kamera", "contribution": 0.0, "idf": 0.0, "tf": 0, "in_doc": false}, {"token": "pengintai", "contribution": 0.0, "idf": 0.0, "tf": 0, "in_doc": false}, {"token": "pada", "contribution": 0.0, "idf": 0.0, "tf": 0, "in_doc": false}, {"token": "pakaian", "contribution": 0.0, "idf": 0.0, "tf": 0, "in_doc": false}], "doc_highlights": [{"start": 93, "end": 96, "token": "dan", "intensity": 0.401, "score": 2.6431}, {"start": 97, "end": 102, "token": "tanpa", "intensity": 0.297, "score": 1.959}, {"start": 146, "end": 151, "token": "dapat", "intensity": 0.43, "score": 2.8322}, {"start": 182, "end": 187, "token": "suami", "intensity": 0.67, "score": 4.4164}, {"start": 188, "end": 193, "token": "istri", "intensity": 1.0, "score": 6.5895}, {"start": 216, "end": 219, "token": "dan", "intensity": 0.401, "score": 2.6431}, {"start": 260, "end": 264, "token": "atas", "intensity": 0.233, "score": 1.5353}, {"start": 266, "end": 269, "token": "dan", "intensity": 0.401, "score": 2.6431}, {"start": 301, "end": 304, "token": "dan", "intensity": 0.401, "score": 2.6431}, {"start": 355, "end": 358, "token": "dan", "intensity": 0.401, "score": 2.6431}, {"start": 608, "end": 613, "token": "suami", "intensity": 0.67, "score": 4.4164}, {"start": 614, "end": 619, "token": "istri", "intensity": 1.0, "score": 6.5895}, {"start": 621, "end": 624, "token": "dan", "intensity": 0.401, "score": 2.6431}, {"start": 625, "end": 630, "token": "dapat", "intensity": 0.43, "score": 2.8322}, {"start": 717, "end": 722, "token": "suami", "intensity": 0.67, "score": 4.4164}, {"start": 723, "end": 728, "token": "istri", "intensity": 1.0, "score": 6.5895}, {"start": 739, "end": 744, "token": "dapat", "intensity": 0.43, "score": 2.8322}], "query_highlights": [{"start": 15, "end": 20, "token": "suami", "intensity": 0.67, "score": 4.4164}, {"start": 21, "end": 26, "token": "dapat", "intensity": 0.43, "score": 2.8322}, {"start": 51, "end": 55, "token": "atas", "intensity": 0.233, "score": 1.5353}, {"start": 90, "end": 93, "token": "dan", "intensity": 0.401, "score": 2.6431}, {"start": 135, "end": 140, "token": "istri", "intensity": 1.0, "score": 6.5895}, {"start": 141, "end": 146, "token": "tanpa", "intensity": 0.297, "score": 1.959}]}, {"rank": 19, "doc_id": "78", "title": "Pasal 78", "bm25_score": 13.108, "is_relevant": false, "per_token": [{"token": "istri", "contribution": 7.5903, "idf": 5.1366, "tf": 1, "in_doc": true}, {"token": "suami", "contribution": 5.0871, "idf": 3.4426, "tf": 1, "in_doc": true}, {"token": "secara", "contribution": 4.8927, "idf": 3.3111, "tf": 1, "in_doc": true}, {"token": "apakah", "contribution": 0.0, "idf": 0.0, "tf": 0, "in_doc": false}, {"token": "seorang", "contribution": 0.0, "idf": 0.0, "tf": 0, "in_doc": false}, {"token": "dapat", "contribution": 0.0, "idf": 0.0, "tf": 0, "in_doc": false}, {"token": "dituntut", "contribution": 0.0, "idf": 0.0, "tf": 0, "in_doc": false}, {"token": "perdata", "contribution": 0.0, "idf": 0.0, "tf": 0, "in_doc": false}, {"token": "atas", "contribution": 0.0, "idf": 0.0, "tf": 0, "in_doc": false}, {"token": "tindakan", "contribution": 0.0, "idf": 0.0, "tf": 0, "in_doc": false}, {"token": "kekerasan", "contribution": 0.0, "idf": 0.0, "tf": 0, "in_doc": false}, {"token": "fisik", "contribution": 0.0, "idf": 0.0, "tf": 0, "in_doc": false}, {"token": "verbal", "contribution": 0.0, "idf": 0.0, "tf": 0, "in_doc": false}, {"token": "dan", "contribution": 0.0, "idf": 0.0, "tf": 0, "in_doc": false}, {"token": "pemasangan", "contribution": 0.0, "idf": 0.0, "tf": 0, "in_doc": false}, {"token": "kamera", "contribution": 0.0, "idf": 0.0, "tf": 0, "in_doc": false}, {"token": "pengintai", "contribution": 0.0, "idf": 0.0, "tf": 0, "in_doc": false}, {"token": "pada", "contribution": 0.0, "idf": 0.0, "tf": 0, "in_doc": false}, {"token": "pakaian", "contribution": 0.0, "idf": 0.0, "tf": 0, "in_doc": false}, {"token": "tanpa", "contribution": 0.0, "idf": 0.0, "tf": 0, "in_doc": false}], "doc_highlights": [{"start": 22, "end": 27, "token": "suami", "intensity": 0.67, "score": 5.0871}, {"start": 28, "end": 33, "token": "istri", "intensity": 1.0, "score": 7.5903}, {"start": 47, "end": 53, "token": "secara", "intensity": 0.645, "score": 4.8927}], "query_highlights": [{"start": 15, "end": 20, "token": "suami", "intensity": 0.67, "score": 5.0871}, {"start": 36, "end": 42, "token": "secara", "intensity": 0.645, "score": 4.8927}, {"start": 135, "end": 140, "token": "istri", "intensity": 1.0, "score": 7.5903}]}, {"rank": 20, "doc_id": "1796", "title": "Pasal 1796", "bm25_score": 13.1052, "is_relevant": false, "per_token": [{"token": "tindakan", "contribution": 8.9243, "idf": 5.1972, "tf": 3, "in_doc": true}, {"token": "secara", "contribution": 3.496, "idf": 3.3111, "tf": 1, "in_doc": true}, {"token": "seorang", "contribution": 3.1105, "idf": 2.9459, "tf": 1, "in_doc": true}, {"token": "dapat", "contribution": 2.3311, "idf": 2.2077, "tf": 1, "in_doc": true}, {"token": "apakah", "contribution": 0.0, "idf": 0.0, "tf": 0, "in_doc": false}, {"token": "suami", "contribution": 0.0, "idf": 0.0, "tf": 0, "in_doc": false}, {"token": "dituntut", "contribution": 0.0, "idf": 0.0, "tf": 0, "in_doc": false}, {"token": "perdata", "contribution": 0.0, "idf": 0.0, "tf": 0, "in_doc": false}, {"token": "atas", "contribution": 0.0, "idf": 0.0, "tf": 0, "in_doc": false}, {"token": "kekerasan", "contribution": 0.0, "idf": 0.0, "tf": 0, "in_doc": false}, {"token": "fisik", "contribution": 0.0, "idf": 0.0, "tf": 0, "in_doc": false}, {"token": "verbal", "contribution": 0.0, "idf": 0.0, "tf": 0, "in_doc": false}, {"token": "dan", "contribution": 0.0, "idf": 0.0, "tf": 0, "in_doc": false}, {"token": "pemasangan", "contribution": 0.0, "idf": 0.0, "tf": 0, "in_doc": false}, {"token": "kamera", "contribution": 0.0, "idf": 0.0, "tf": 0, "in_doc": false}, {"token": "pengintai", "contribution": 0.0, "idf": 0.0, "tf": 0, "in_doc": false}, {"token": "pada", "contribution": 0.0, "idf": 0.0, "tf": 0, "in_doc": false}, {"token": "pakaian", "contribution": 0.0, "idf": 0.0, "tf": 0, "in_doc": false}, {"token": "istri", "contribution": 0.0, "idf": 0.0, "tf": 0, "in_doc": false}, {"token": "tanpa", "contribution": 0.0, "idf": 0.0, "tf": 0, "in_doc": false}], "doc_highlights": [{"start": 44, "end": 50, "token": "secara", "intensity": 0.392, "score": 3.496}, {"start": 71, "end": 79, "token": "tindakan", "intensity": 1.0, "score": 8.9243}, {"start": 80, "end": 88, "token": "tindakan", "intensity": 1.0, "score": 8.9243}, {"start": 234, "end": 242, "token": "tindakan", "intensity": 1.0, "score": 8.9243}, {"start": 259, "end": 264, "token": "dapat", "intensity": 0.261, "score": 2.3311}, {"start": 280, "end": 287, "token": "seorang", "intensity": 0.349, "score": 3.1105}], "query_highlights": [{"start": 7, "end": 14, "token": "seorang", "intensity": 0.349, "score": 3.1105}, {"start": 21, "end": 26, "token": "dapat", "intensity": 0.261, "score": 2.3311}, {"start": 36, "end": 42, "token": "secara", "intensity": 0.392, "score": 3.496}, {"start": 56, "end": 64, "token": "tindakan", "intensity": 1.0, "score": 8.9243}]}, {"rank": 21, "doc_id": "31", "title": "Pasal 31", "bm25_score": 12.9918, "is_relevant": false, "per_token": [{"token": "istri", "contribution": 6.9938, "idf": 5.1366, "tf": 3, "in_doc": true}, {"token": "suami", "contribution": 4.6873, "idf": 3.4426, "tf": 3, "in_doc": true}, {"token": "izin", "contribution": 3.1457, "idf": 4.4144, "tf": 1, "in_doc": true}, {"token": "dan", "contribution": 1.7288, "idf": 1.5588, "tf": 2, "in_doc": true}, {"token": "atas", "contribution": 1.6832, "idf": 2.3622, "tf": 1, "in_doc": true}, {"token": "apakah", "contribution": 0.0, "idf": 0.0, "tf": 0, "in_doc": false}, {"token": "seorang", "contribution": 0.0, "idf": 0.0, "tf": 0, "in_doc": false}, {"token": "dapat", "contribution": 0.0, "idf": 0.0, "tf": 0, "in_doc": false}, {"token": "dituntut", "contribution": 0.0, "idf": 0.0, "tf": 0, "in_doc": false}, {"token": "secara", "contribution": 0.0, "idf": 0.0, "tf": 0, "in_doc": false}, {"token": "perdata", "contribution": 0.0, "idf": 0.0, "tf": 0, "in_doc": false}, {"token": "tindakan", "contribution": 0.0, "idf": 0.0, "tf": 0, "in_doc": false}, {"token": "kekerasan", "contribution": 0.0, "idf": 0.0, "tf": 0, "in_doc": false}, {"token": "fisik", "contribution": 0.0, "idf": 0.0, "tf": 0, "in_doc": false}, {"token": "verbal", "contribution": 0.0, "idf": 0.0, "tf": 0, "in_doc": false}, {"token": "pemasangan", "contribution": 0.0, "idf": 0.0, "tf": 0, "in_doc": false}, {"token": "kamera", "contribution": 0.0, "idf": 0.0, "tf": 0, "in_doc": false}, {"token": "pengintai", "contribution": 0.0, "idf": 0.0, "tf": 0, "in_doc": false}, {"token": "pada", "contribution": 0.0, "idf": 0.0, "tf": 0, "in_doc": false}, {"token": "pakaian", "contribution": 0.0, "idf": 0.0, "tf": 0, "in_doc": false}], "doc_highlights": [{"start": 61, "end": 64, "token": "dan", "intensity": 0.247, "score": 1.7288}, {"start": 114, "end": 119, "token": "suami", "intensity": 0.67, "score": 4.6873}, {"start": 125, "end": 130, "token": "istri", "intensity": 1.0, "score": 6.9938}, {"start": 199, "end": 203, "token": "atas", "intensity": 0.241, "score": 1.6832}, {"start": 228, "end": 233, "token": "suami", "intensity": 0.67, "score": 4.6873}, {"start": 242, "end": 247, "token": "istri", "intensity": 1.0, "score": 6.9938}, {"start": 264, "end": 268, "token": "izin", "intensity": 0.45, "score": 3.1457}, {"start": 287, "end": 292, "token": "suami", "intensity": 0.67, "score": 4.6873}, {"start": 298, "end": 303, "token": "istri", "intensity": 1.0, "score": 6.9938}, {"start": 366, "end": 369, "token": "dan", "intensity": 0.247, "score": 1.7288}], "query_highlights": [{"start": 15, "end": 20, "token": "suami", "intensity": 0.67, "score": 4.6873}, {"start": 51, "end": 55, "token": "atas", "intensity": 0.241, "score": 1.6832}, {"start": 90, "end": 93, "token": "dan", "intensity": 0.247, "score": 1.7288}, {"start": 135, "end": 140, "token": "istri", "intensity": 1.0, "score": 6.9938}, {"start": 147, "end": 151, "token": "izin", "intensity": 0.45, "score": 3.1457}]}, {"rank": 22, "doc_id": "202", "title": "Pasal 202", "bm25_score": 12.9494, "is_relevant": false, "per_token": [{"token": "tindakan", "contribution": 7.2968, "idf": 5.1972, "tf": 6, "in_doc": true}, {"token": "suami", "contribution": 4.8333, "idf": 3.4426, "tf": 6, "in_doc": true}, {"token": "seorang", "contribution": 3.3924, "idf": 2.9459, "tf": 4, "in_doc": true}, {"token": "dan", "contribution": 1.795, "idf": 1.5588, "tf": 4, "in_doc": true}, {"token": "secara", "contribution": 1.4563, "idf": 3.3111, "tf": 1, "in_doc": true}, {"token": "apakah", "contribution": 0.0, "idf": 0.0, "tf": 0, "in_doc": false}, {"token": "dapat", "contribution": 0.0, "idf": 0.0, "tf": 0, "in_doc": false}, {"token": "dituntut", "contribution": 0.0, "idf": 0.0, "tf": 0, "in_doc": false}, {"token": "perdata", "contribution": 0.0, "idf": 0.0, "tf": 0, "in_doc": false}, {"token": "atas", "contribution": 0.0, "idf": 0.0, "tf": 0, "in_doc": false}, {"token": "kekerasan", "contribution": 0.0, "idf": 0.0, "tf": 0, "in_doc": false}, {"token": "fisik", "contribution": 0.0, "idf": 0.0, "tf": 0, "in_doc": false}, {"token": "verbal", "contribution": 0.0, "idf": 0.0, "tf": 0, "in_doc": false}, {"token": "pemasangan", "contribution": 0.0, "idf": 0.0, "tf": 0, "in_doc": false}, {"token": "kamera", "contribution": 0.0, "idf": 0.0, "tf": 0, "in_doc": false}, {"token": "pengintai", "contribution": 0.0, "idf": 0.0, "tf": 0, "in_doc": false}, {"token": "pada", "contribution": 0.0, "idf": 0.0, "tf": 0, "in_doc": false}, {"token": "pakaian", "contribution": 0.0, "idf": 0.0, "tf": 0, "in_doc": false}, {"token": "istri", "contribution": 0.0, "idf": 0.0, "tf": 0, "in_doc": false}, {"token": "tanpa", "contribution": 0.0, "idf": 0.0, "tf": 0, "in_doc": false}], "doc_highlights": [{"start": 96, "end": 101, "token": "suami", "intensity": 0.662, "score": 4.8333}, {"start": 113, "end": 119, "token": "secara", "intensity": 0.2, "score": 1.4563}, {"start": 151, "end": 158, "token": "seorang", "intensity": 0.465, "score": 3.3924}, {"start": 325, "end": 328, "token": "dan", "intensity": 0.246, "score": 1.795}, {"start": 503, "end": 508, "token": "suami", "intensity": 0.662, "score": 4.8333}, {"start": 532, "end": 539, "token": "seorang", "intensity": 0.465, "score": 3.3924}, {"start": 545, "end": 550, "token": "suami", "intensity": 0.662, "score": 4.8333}, {"start": 760, "end": 765, "token": "suami", "intensity": 0.662, "score": 4.8333}, {"start": 811, "end": 819, "token": "tindakan", "intensity": 1.0, "score": 7.2968}, {"start": 820, "end": 828, "token": "tindakan", "intensity": 1.0, "score": 7.2968}, {"start": 923, "end": 931, "token": "tindakan", "intensity": 1.0, "score": 7.2968}, {"start": 932, "end": 940, "token": "tindakan", "intensity": 1.0, "score": 7.2968}, {"start": 959, "end": 962, "token": "dan", "intensity": 0.246, "score": 1.795}, {"start": 1039, "end": 1046, "token": "seorang", "intensity": 0.465, "score": 3.3924}, {"start": 1047, "end": 1050, "token": "dan", "intensity": 0.246, "score": 1.795}, {"start": 1051, "end": 1056, "token": "suami", "intensity": 0.662, "score": 4.8333}, {"start": 1159, "end": 1166, "token": "seorang", "intensity": 0.465, "score": 3.3924}, {"start": 1235, "end": 1243, "token": "tindakan", "intensity": 1.0, "score": 7.2968}, {"start": 1244, "end": 1252, "token": "tindakan", "intensity": 1.0, "score": 7.2968}, {"start": 1280, "end": 1283, "token": "dan", "intensity": 0.246, "score": 1.795}, {"start": 1365, "end": 1370, "token": "suami", "intensity": 0.662, "score": 4.8333}], "query_highlights": [{"start": 7, "end": 14, "token": "seorang", "intensity": 0.465, "score": 3.3924}, {"start": 15, "end": 20, "token": "suami", "intensity": 0.662, "score": 4.8333}, {"start": 36, "end": 42, "token": "secara", "intensity": 0.2, "score": 1.4563}, {"start": 56, "end": 64, "token": "tindakan", "intensity": 1.0, "score": 7.2968}, {"start": 90, "end": 93, "token": "dan", "intensity": 0.246, "score": 1.795}]}, {"rank": 23, "doc_id": "562", "title": "Pasal 562", "bm25_score": 12.9175, "is_relevant": false, "per_token": [{"token": "kekerasan", "contribution": 8.3554, "idf": 6.3604, "tf": 1, "in_doc": true}, {"token": "tanpa", "contribution": 3.9594, "idf": 3.014, "tf": 1, "in_doc": true}, {"token": "atas", "contribution": 3.1031, "idf": 2.3622, "tf": 1, "in_doc": true}, {"token": "dapat", "contribution": 2.9003, "idf": 2.2077, "tf": 1, "in_doc": true}, {"token": "apakah", "contribution": 0.0, "idf": 0.0, "tf": 0, "in_doc": false}, {"token": "seorang", "contribution": 0.0, "idf": 0.0, "tf": 0, "in_doc": false}, {"token": "suami", "contribution": 0.0, "idf": 0.0, "tf": 0, "in_doc": false}, {"token": "dituntut", "contribution": 0.0, "idf": 0.0, "tf": 0, "in_doc": false}, {"token": "secara", "contribution": 0.0, "idf": 0.0, "tf": 0, "in_doc": false}, {"token": "perdata", "contribution": 0.0, "idf": 0.0, "tf": 0, "in_doc": false}, {"token": "tindakan", "contribution": 0.0, "idf": 0.0, "tf": 0, "in_doc": false}, {"token": "fisik", "contribution": 0.0, "idf": 0.0, "tf": 0, "in_doc": false}, {"token": "verbal", "contribution": 0.0, "idf": 0.0, "tf": 0, "in_doc": false}, {"token": "dan", "contribution": 0.0, "idf": 0.0, "tf": 0, "in_doc": false}, {"token": "pemasangan", "contribution": 0.0, "idf": 0.0, "tf": 0, "in_doc": false}, {"token": "kamera", "contribution": 0.0, "idf": 0.0, "tf": 0, "in_doc": false}, {"token": "pengintai", "contribution": 0.0, "idf": 0.0, "tf": 0, "in_doc": false}, {"token": "pada", "contribution": 0.0, "idf": 0.0, "tf": 0, "in_doc": false}, {"token": "pakaian", "contribution": 0.0, "idf": 0.0, "tf": 0, "in_doc": false}, {"token": "istri", "contribution": 0.0, "idf": 0.0, "tf": 0, "in_doc": false}], "doc_highlights": [{"start": 31, "end": 35, "token": "atas", "intensity": 0.371, "score": 3.1031}, {"start": 81, "end": 86, "token": "tanpa", "intensity": 0.474, "score": 3.9594}, {"start": 87, "end": 96, "token": "kekerasan", "intensity": 1.0, "score": 8.3554}, {"start": 106, "end": 111, "token": "dapat", "intensity": 0.347, "score": 2.9003}], "query_highlights": [{"start": 21, "end": 26, "token": "dapat", "intensity": 0.347, "score": 2.9003}, {"start": 51, "end": 55, "token": "atas", "intensity": 0.371, "score": 3.1031}, {"start": 65, "end": 74, "token": "kekerasan", "intensity": 1.0, "score": 8.3554}, {"start": 141, "end": 146, "token": "tanpa", "intensity": 0.474, "score": 3.9594}]}, {"rank": 24, "doc_id": "11", "title": "Pasal 11", "bm25_score": 12.857, "is_relevant": false, "per_token": [{"token": "izin", "contribution": 5.5526, "idf": 4.4144, "tf": 1, "in_doc": true}, {"token": "tanpa", "contribution": 3.7911, "idf": 3.014, "tf": 1, "in_doc": true}, {"token": "seorang", "contribution": 3.7055, "idf": 2.9459, "tf": 1, "in_doc": true}, {"token": "pada", "contribution": 3.3109, "idf": 2.6323, "tf": 1, "in_doc": true}, {"token": "atas", "contribution": 2.9712, "idf": 2.3622, "tf": 1, "in_doc": true}, {"token": "apakah", "contribution": 0.0, "idf": 0.0, "tf": 0, "in_doc": false}, {"token": "suami", "contribution": 0.0, "idf": 0.0, "tf": 0, "in_doc": false}, {"token": "dapat", "contribution": 0.0, "idf": 0.0, "tf": 0, "in_doc": false}, {"token": "dituntut", "contribution": 0.0, "idf": 0.0, "tf": 0, "in_doc": false}, {"token": "secara", "contribution": 0.0, "idf": 0.0, "tf": 0, "in_doc": false}, {"token": "perdata", "contribution": 0.0, "idf": 0.0, "tf": 0, "in_doc": false}, {"token": "tindakan", "contribution": 0.0, "idf": 0.0, "tf": 0, "in_doc": false}, {"token": "kekerasan", "contribution": 0.0, "idf": 0.0, "tf": 0, "in_doc": false}, {"token": "fisik", "contribution": 0.0, "idf": 0.0, "tf": 0, "in_doc": false}, {"token": "verbal", "contribution": 0.0, "idf": 0.0, "tf": 0, "in_doc": false}, {"token": "dan", "contribution": 0.0, "idf": 0.0, "tf": 0, "in_doc": false}, {"token": "pemasangan", "contribution": 0.0, "idf": 0.0, "tf": 0, "in_doc": false}, {"token": "kamera", "contribution": 0.0, "idf": 0.0, "tf": 0, "in_doc": false}, {"token": "pengintai", "contribution": 0.0, "idf": 0.0, "tf": 0, "in_doc": false}, {"token": "pakaian", "contribution": 0.0, "idf": 0.0, "tf": 0, "in_doc": false}], "doc_highlights": [{"start": 16, "end": 23, "token": "seorang", "intensity": 0.667, "score": 3.7055}, {"start": 90, "end": 94, "token": "pada", "intensity": 0.596, "score": 3.3109}, {"start": 104, "end": 109, "token": "tanpa", "intensity": 0.683, "score": 3.7911}, {"start": 110, "end": 114, "token": "izin", "intensity": 1.0, "score": 5.5526}, {"start": 151, "end": 155, "token": "atas", "intensity": 0.535, "score": 2.9712}], "query_highlights": [{"start": 7, "end": 14, "token": "seorang", "intensity": 0.667, "score": 3.7055}, {"start": 51, "end": 55, "token": "atas", "intensity": 0.535, "score": 2.9712}, {"start": 122, "end": 126, "token": "pada", "intensity": 0.596, "score": 3.3109}, {"start": 141, "end": 146, "token": "tanpa", "intensity": 0.683, "score": 3.7911}, {"start": 147, "end": 151, "token": "izin", "intensity": 1.0, "score": 5.5526}]}, {"rank": 25, "doc_id": "1340", "title": "Pasal 1340", "bm25_score": 12.5194, "is_relevant": false, "per_token": [{"token": "tindakan", "contribution": 8.2234, "idf": 5.1972, "tf": 6, "in_doc": true}, {"token": "apakah", "contribution": 3.038, "idf": 5.4441, "tf": 1, "in_doc": true}, {"token": "dapat", "contribution": 2.0144, "idf": 2.2077, "tf": 2, "in_doc": true}, {"token": "pada", "contribution": 1.4689, "idf": 2.6323, "tf": 1, "in_doc": true}, {"token": "dan", "contribution": 1.4223, "idf": 1.5588, "tf": 2, "in_doc": true}, {"token": "atas", "contribution": 1.3182, "idf": 2.3622, "tf": 1, "in_doc": true}, {"token": "seorang", "contribution": 0.0, "idf": 0.0, "tf": 0, "in_doc": false}, {"token": "suami", "contribution": 0.0, "idf": 0.0, "tf": 0, "in_doc": false}, {"token": "dituntut", "contribution": 0.0, "idf": 0.0, "tf": 0, "in_doc": false}, {"token": "secara", "contribution": 0.0, "idf": 0.0, "tf": 0, "in_doc": false}, {"token": "perdata", "contribution": 0.0, "idf": 0.0, "tf": 0, "in_doc": false}, {"token": "kekerasan", "contribution": 0.0, "idf": 0.0, "tf": 0, "in_doc": false}, {"token": "fisik", "contribution": 0.0, "idf": 0.0, "tf": 0, "in_doc": false}, {"token": "verbal", "contribution": 0.0, "idf": 0.0, "tf": 0, "in_doc": false}, {"token": "pemasangan", "contribution": 0.0, "idf": 0.0, "tf": 0, "in_doc": false}, {"token": "kamera", "contribution": 0.0, "idf": 0.0, "tf": 0, "in_doc": false}, {"token": "pengintai", "contribution": 0.0, "idf": 0.0, "tf": 0, "in_doc": false}, {"token": "pakaian", "contribution": 0.0, "idf": 0.0, "tf": 0, "in_doc": false}, {"token": "istri", "contribution": 0.0, "idf": 0.0, "tf": 0, "in_doc": false}, {"token": "tanpa", "contribution": 0.0, "idf": 0.0, "tf": 0, "in_doc": false}], "doc_highlights": [{"start": 92, "end": 97, "token": "dapat", "intensity": 0.245, "score": 2.0144}, {"start": 140, "end": 145, "token": "dapat", "intensity": 0.245, "score": 2.0144}, {"start": 316, "end": 324, "token": "tindakan", "intensity": 1.0, "score": 8.2234}, {"start": 455, "end": 463, "token": "tindakan", "intensity": 1.0, "score": 8.2234}, {"start": 492, "end": 495, "token": "dan", "intensity": 0.173, "score": 1.4223}, {"start": 571, "end": 579, "token": "tindakan", "intensity": 1.0, "score": 8.2234}, {"start": 682, "end": 686, "token": "atas", "intensity": 0.16, "score": 1.3182}, {"start": 720, "end": 723, "token": "dan", "intensity": 0.173, "score": 1.4223}, {"start": 724, "end": 732, "token": "tindakan", "intensity": 1.0, "score": 8.2234}, {"start": 792, "end": 800, "token": "tindakan", "intensity": 1.0, "score": 8.2234}, {"start": 878, "end": 882, "token": "pada", "intensity": 0.179, "score": 1.4689}, {"start": 899, "end": 907, "token": "tindakan", "intensity": 1.0, "score": 8.2234}, {"start": 998, "end": 1004, "token": "apakah", "intensity": 0.369, "score": 3.038}], "query_highlights": [{"start": 0, "end": 6, "token": "apakah", "intensity": 0.369, "score": 3.038}, {"start": 21, "end": 26, "token": "dapat", "intensity": 0.245, "score": 2.0144}, {"start": 51, "end": 55, "token": "atas", "intensity": 0.16, "score": 1.3182}, {"start": 56, "end": 64, "token": "tindakan", "intensity": 1.0, "score": 8.2234}, {"start": 90, "end": 93, "token": "dan", "intensity": 0.173, "score": 1.4223}, {"start": 122, "end": 126, "token": "pada", "intensity": 0.179, "score": 1.4689}]}, {"rank": 392, "doc_id": "1372", "title": "Pasal 1372", "bm25_score": 5.1374, "is_relevant": true, "per_token": [{"token": "perdata", "contribution": 5.369, "idf": 4.8128, "tf": 1, "in_doc": true}, {"token": "dan", "contribution": 2.7566, "idf": 1.5588, "tf": 3, "in_doc": true}, {"token": "apakah", "contribution": 0.0, "idf": 0.0, "tf": 0, "in_doc": false}, {"token": "seorang", "contribution": 0.0, "idf": 0.0, "tf": 0, "in_doc": false}, {"token": "suami", "contribution": 0.0, "idf": 0.0, "tf": 0, "in_doc": false}, {"token": "dapat", "contribution": 0.0, "idf": 0.0, "tf": 0, "in_doc": false}, {"token": "dituntut", "contribution": 0.0, "idf": 0.0, "tf": 0, "in_doc": false}, {"token": "secara", "contribution": 0.0, "idf": 0.0, "tf": 0, "in_doc": false}, {"token": "atas", "contribution": 0.0, "idf": 0.0, "tf": 0, "in_doc": false}, {"token": "tindakan", "contribution": 0.0, "idf": 0.0, "tf": 0, "in_doc": false}, {"token": "kekerasan", "contribution": 0.0, "idf": 0.0, "tf": 0, "in_doc": false}, {"token": "fisik", "contribution": 0.0, "idf": 0.0, "tf": 0, "in_doc": false}, {"token": "verbal", "contribution": 0.0, "idf": 0.0, "tf": 0, "in_doc": false}, {"token": "pemasangan", "contribution": 0.0, "idf": 0.0, "tf": 0, "in_doc": false}, {"token": "kamera", "contribution": 0.0, "idf": 0.0, "tf": 0, "in_doc": false}, {"token": "pengintai", "contribution": 0.0, "idf": 0.0, "tf": 0, "in_doc": false}, {"token": "pada", "contribution": 0.0, "idf": 0.0, "tf": 0, "in_doc": false}, {"token": "pakaian", "contribution": 0.0, "idf": 0.0, "tf": 0, "in_doc": false}, {"token": "istri", "contribution": 0.0, "idf": 0.0, "tf": 0, "in_doc": false}, {"token": "tanpa", "contribution": 0.0, "idf": 0.0, "tf": 0, "in_doc": false}], "doc_highlights": [{"start": 21, "end": 28, "token": "perdata", "intensity": 1.0, "score": 5.369}, {"start": 126, "end": 129, "token": "dan", "intensity": 0.513, "score": 2.7566}, {"start": 260, "end": 263, "token": "dan", "intensity": 0.513, "score": 2.7566}, {"start": 292, "end": 295, "token": "dan", "intensity": 0.513, "score": 2.7566}], "query_highlights": [{"start": 43, "end": 50, "token": "perdata", "intensity": 1.0, "score": 5.369}, {"start": 90, "end": 93, "token": "dan", "intensity": 0.513, "score": 2.7566}], "beyond_topk": true}, {"rank": 1641, "doc_id": "1365", "title": "Pasal 1365", "bm25_score": 0.7436, "is_relevant": true, "per_token": [{"token": "dan", "contribution": 2.0478, "idf": 1.5588, "tf": 1, "in_doc": true}, {"token": "apakah", "contribution": 0.0, "idf": 0.0, "tf": 0, "in_doc": false}, {"token": "seorang", "contribution": 0.0, "idf": 0.0, "tf": 0, "in_doc": false}, {"token": "suami", "contribution": 0.0, "idf": 0.0, "tf": 0, "in_doc": false}, {"token": "dapat", "contribution": 0.0, "idf": 0.0, "tf": 0, "in_doc": false}, {"token": "dituntut", "contribution": 0.0, "idf": 0.0, "tf": 0, "in_doc": false}, {"token": "secara", "contribution": 0.0, "idf": 0.0, "tf": 0, "in_doc": false}, {"token": "perdata", "contribution": 0.0, "idf": 0.0, "tf": 0, "in_doc": false}, {"token": "atas", "contribution": 0.0, "idf": 0.0, "tf": 0, "in_doc": false}, {"token": "tindakan", "contribution": 0.0, "idf": 0.0, "tf": 0, "in_doc": false}, {"token": "kekerasan", "contribution": 0.0, "idf": 0.0, "tf": 0, "in_doc": false}, {"token": "fisik", "contribution": 0.0, "idf": 0.0, "tf": 0, "in_doc": false}, {"token": "verbal", "contribution": 0.0, "idf": 0.0, "tf": 0, "in_doc": false}, {"token": "pemasangan", "contribution": 0.0, "idf": 0.0, "tf": 0, "in_doc": false}, {"token": "kamera", "contribution": 0.0, "idf": 0.0, "tf": 0, "in_doc": false}, {"token": "pengintai", "contribution": 0.0, "idf": 0.0, "tf": 0, "in_doc": false}, {"token": "pada", "contribution": 0.0, "idf": 0.0, "tf": 0, "in_doc": false}, {"token": "pakaian", "contribution": 0.0, "idf": 0.0, "tf": 0, "in_doc": false}, {"token": "istri", "contribution": 0.0, "idf": 0.0, "tf": 0, "in_doc": false}, {"token": "tanpa", "contribution": 0.0, "idf": 0.0, "tf": 0, "in_doc": false}], "doc_highlights": [{"start": 48, "end": 51, "token": "dan", "intensity": 1.0, "score": 2.0478}], "query_highlights": [{"start": 90, "end": 93, "token": "dan", "intensity": 1.0, "score": 2.0478}], "beyond_topk": true}]}