{"qid": "q500", "query_text": "Mengapa pengadilan menolak gugatan [Penggugat] karena dianggap kurang melibatkan ahli waris lain dari pemilik tanah yang meninggal, padahal [Penggugat] dan [Tergugat] sudah menandatangani perjanjian kerjasama?", "case_name": "Putusan_PN_DENPASAR_Nomor_1305_Pdt.G_2023_PN_Dps.pdf", "n_gt": 5, "gt_doc_ids": ["1320", "1338", "2", "832", "852"], "gt_ranks": {"832": 246, "852": 629, "2": 670, "1338": 1275, "1320": 1881}, "ranked_docs": [{"rank": 1, "doc_id": "1058", "title": "Pasal 1058", "bm25_score": 18.979, "is_relevant": false, "per_token": [{"token": "menolak", "contribution": 7.3265, "idf": 4.8343, "tf": 1, "in_doc": true}, {"token": "waris", "contribution": 6.5587, "idf": 3.4756, "tf": 2, "in_doc": true}, {"token": "ahli", "contribution": 6.1187, "idf": 3.2424, "tf": 2, "in_doc": true}, {"token": "dianggap", "contribution": 5.5658, "idf": 3.6725, "tf": 1, "in_doc": true}, {"token": "mengapa", "contribution": 0.0, "idf": 0.0, "tf": 0, "in_doc": false}, {"token": "pengadilan", "contribution": 0.0, "idf": 0.0, "tf": 0, "in_doc": false}, {"token": "gugatan", "contribution": 0.0, "idf": 0.0, "tf": 0, "in_doc": false}, {"token": "penggugat", "contribution": 0.0, "idf": 0.0, "tf": 0, "in_doc": false}, {"token": "karena", "contribution": 0.0, "idf": 0.0, "tf": 0, "in_doc": false}, {"token": "kurang", "contribution": 0.0, "idf": 0.0, "tf": 0, "in_doc": false}, {"token": "melibatkan", "contribution": 0.0, "idf": 0.0, "tf": 0, "in_doc": false}, {"token": "lain", "contribution": 0.0, "idf": 0.0, "tf": 0, "in_doc": false}, {"token": "dari", "contribution": 0.0, "idf": 0.0, "tf": 0, "in_doc": false}, {"token": "pemilik", "contribution": 0.0, "idf": 0.0, "tf": 0, "in_doc": false}, {"token": "tanah", "contribution": 0.0, "idf": 0.0, "tf": 0, "in_doc": false}, {"token": "yang", "contribution": 0.0, "idf": 0.0, "tf": 1, "in_doc": true}, {"token": "meninggal", "contribution": 0.0, "idf": 0.0, "tf": 0, "in_doc": false}, {"token": "padahal", "contribution": 0.0, "idf": 0.0, "tf": 0, "in_doc": false}, {"token": "dan", "contribution": 0.0, "idf": 0.0, "tf": 0, "in_doc": false}, {"token": "tergugat", "contribution": 0.0, "idf": 0.0, "tf": 0, "in_doc": false}], "doc_highlights": [{"start": 12, "end": 16, "token": "ahli", "intensity": 0.835, "score": 6.1187}, {"start": 17, "end": 22, "token": "waris", "intensity": 0.895, "score": 6.5587}, {"start": 28, "end": 35, "token": "menolak", "intensity": 1.0, "score": 7.3265}, {"start": 45, "end": 53, "token": "dianggap", "intensity": 0.76, "score": 5.5658}, {"start": 75, "end": 79, "token": "ahli", "intensity": 0.835, "score": 6.1187}, {"start": 80, "end": 85, "token": "waris", "intensity": 0.895, "score": 6.5587}], "query_highlights": [{"start": 19, "end": 26, "token": "menolak", "intensity": 1.0, "score": 7.3265}, {"start": 54, "end": 62, "token": "dianggap", "intensity": 0.76, "score": 5.5658}, {"start": 81, "end": 85, "token": "ahli", "intensity": 0.835, "score": 6.1187}, {"start": 86, "end": 91, "token": "waris", "intensity": 0.895, "score": 6.5587}]}, {"rank": 2, "doc_id": "1655", "title": "Pasal 1655", "bm25_score": 17.5016, "is_relevant": false, "per_token": [{"token": "tergugat", "contribution": 6.4842, "idf": 6.3604, "tf": 1, "in_doc": true}, {"token": "penggugat", "contribution": 6.2984, "idf": 6.178, "tf": 1, "in_doc": true}, {"token": "perjanjian", "contribution": 3.4612, "idf": 3.3951, "tf": 1, "in_doc": true}, {"token": "pengadilan", "contribution": 3.2966, "idf": 3.2336, "tf": 1, "in_doc": true}, {"token": "lain", "contribution": 2.7261, "idf": 2.674, "tf": 1, "in_doc": true}, {"token": "dan", "contribution": 2.2577, "idf": 1.5588, "tf": 2, "in_doc": true}, {"token": "mengapa", "contribution": 0.0, "idf": 0.0, "tf": 0, "in_doc": false}, {"token": "menolak", "contribution": 0.0, "idf": 0.0, "tf": 0, "in_doc": false}, {"token": "gugatan", "contribution": 0.0, "idf": 0.0, "tf": 0, "in_doc": false}, {"token": "karena", "contribution": 0.0, "idf": 0.0, "tf": 0, "in_doc": false}, {"token": "dianggap", "contribution": 0.0, "idf": 0.0, "tf": 0, "in_doc": false}, {"token": "kurang", "contribution": 0.0, "idf": 0.0, "tf": 0, "in_doc": false}, {"token": "melibatkan", "contribution": 0.0, "idf": 0.0, "tf": 0, "in_doc": false}, {"token": "ahli", "contribution": 0.0, "idf": 0.0, "tf": 0, "in_doc": false}, {"token": "waris", "contribution": 0.0, "idf": 0.0, "tf": 0, "in_doc": false}, {"token": "dari", "contribution": 0.0, "idf": 0.0, "tf": 0, "in_doc": false}, {"token": "pemilik", "contribution": 0.0, "idf": 0.0, "tf": 0, "in_doc": false}, {"token": "tanah", "contribution": 0.0, "idf": 0.0, "tf": 0, "in_doc": false}, {"token": "yang", "contribution": 0.0, "idf": 0.0, "tf": 0, "in_doc": false}, {"token": "meninggal", "contribution": 0.0, "idf": 0.0, "tf": 0, "in_doc": false}], "doc_highlights": [{"start": 61, "end": 65, "token": "lain", "intensity": 0.42, "score": 2.7261}, {"start": 103, "end": 113, "token": "perjanjian", "intensity": 0.534, "score": 3.4612}, {"start": 164, "end": 167, "token": "dan", "intensity": 0.348, "score": 2.2577}, {"start": 266, "end": 269, "token": "dan", "intensity": 0.348, "score": 2.2577}, {"start": 299, "end": 309, "token": "pengadilan", "intensity": 0.508, "score": 3.2966}, {"start": 323, "end": 332, "token": "penggugat", "intensity": 0.971, "score": 6.2984}, {"start": 348, "end": 356, "token": "tergugat", "intensity": 1.0, "score": 6.4842}], "query_highlights": [{"start": 8, "end": 18, "token": "pengadilan", "intensity": 0.508, "score": 3.2966}, {"start": 36, "end": 45, "token": "penggugat", "intensity": 0.971, "score": 6.2984}, {"start": 92, "end": 96, "token": "lain", "intensity": 0.42, "score": 2.7261}, {"start": 141, "end": 150, "token": "penggugat", "intensity": 0.971, "score": 6.2984}, {"start": 152, "end": 155, "token": "dan", "intensity": 0.348, "score": 2.2577}, {"start": 157, "end": 165, "token": "tergugat", "intensity": 1.0, "score": 6.4842}, {"start": 188, "end": 198, "token": "perjanjian", "intensity": 0.534, "score": 3.4612}]}, {"rank": 3, "doc_id": "1060", "title": "Pasal 1060", "bm25_score": 17.0539, "is_relevant": false, "per_token": [{"token": "menolak", "contribution": 7.1326, "idf": 4.8343, "tf": 2, "in_doc": true}, {"token": "waris", "contribution": 6.4495, "idf": 3.4756, "tf": 4, "in_doc": true}, {"token": "ahli", "contribution": 6.0169, "idf": 3.2424, "tf": 4, "in_doc": true}, {"token": "karena", "contribution": 3.1765, "idf": 3.0353, "tf": 1, "in_doc": true}, {"token": "dan", "contribution": 1.6313, "idf": 1.5588, "tf": 1, "in_doc": true}, {"token": "mengapa", "contribution": 0.0, "idf": 0.0, "tf": 0, "in_doc": false}, {"token": "pengadilan", "contribution": 0.0, "idf": 0.0, "tf": 0, "in_doc": false}, {"token": "gugatan", "contribution": 0.0, "idf": 0.0, "tf": 0, "in_doc": false}, {"token": "penggugat", "contribution": 0.0, "idf": 0.0, "tf": 0, "in_doc": false}, {"token": "dianggap", "contribution": 0.0, "idf": 0.0, "tf": 0, "in_doc": false}, {"token": "kurang", "contribution": 0.0, "idf": 0.0, "tf": 0, "in_doc": false}, {"token": "melibatkan", "contribution": 0.0, "idf": 0.0, "tf": 0, "in_doc": false}, {"token": "lain", "contribution": 0.0, "idf": 0.0, "tf": 0, "in_doc": false}, {"token": "dari", "contribution": 0.0, "idf": 0.0, "tf": 0, "in_doc": false}, {"token": "pemilik", "contribution": 0.0, "idf": 0.0, "tf": 0, "in_doc": false}, {"token": "tanah", "contribution": 0.0, "idf": 0.0, "tf": 0, "in_doc": false}, {"token": "yang", "contribution": 0.0, "idf": 0.0, "tf": 2, "in_doc": true}, {"token": "meninggal", "contribution": 0.0, "idf": 0.0, "tf": 0, "in_doc": false}, {"token": "padahal", "contribution": 0.0, "idf": 0.0, "tf": 0, "in_doc": false}, {"token": "tergugat", "contribution": 0.0, "idf": 0.0, "tf": 0, "in_doc": false}], "doc_highlights": [{"start": 29, "end": 36, "token": "menolak", "intensity": 1.0, "score": 7.1326}, {"start": 97, "end": 101, "token": "ahli", "intensity": 0.844, "score": 6.0169}, {"start": 102, "end": 107, "token": "waris", "intensity": 0.904, "score": 6.4495}, {"start": 133, "end": 137, "token": "ahli", "intensity": 0.844, "score": 6.0169}, {"start": 138, "end": 143, "token": "waris", "intensity": 0.904, "score": 6.4495}, {"start": 178, "end": 182, "token": "ahli", "intensity": 0.844, "score": 6.0169}, {"start": 183, "end": 188, "token": "waris", "intensity": 0.904, "score": 6.4495}, {"start": 189, "end": 196, "token": "menolak", "intensity": 1.0, "score": 7.1326}, {"start": 239, "end": 243, "token": "ahli", "intensity": 0.844, "score": 6.0169}, {"start": 244, "end": 249, "token": "waris", "intensity": 0.904, "score": 6.4495}, {"start": 250, "end": 256, "token": "karena", "intensity": 0.445, "score": 3.1765}, {"start": 277, "end": 280, "token": "dan", "intensity": 0.229, "score": 1.6313}], "query_highlights": [{"start": 19, "end": 26, "token": "menolak", "intensity": 1.0, "score": 7.1326}, {"start": 47, "end": 53, "token": "karena", "intensity": 0.445, "score": 3.1765}, {"start": 81, "end": 85, "token": "ahli", "intensity": 0.844, "score": 6.0169}, {"start": 86, "end": 91, "token": "waris", "intensity": 0.904, "score": 6.4495}, {"start": 152, "end": 155, "token": "dan", "intensity": 0.229, "score": 1.6313}]}, {"rank": 4, "doc_id": "1692", "title": "Pasal 1692", "bm25_score": 16.6531, "is_relevant": false, "per_token": [{"token": "gugatan", "contribution": 8.5027, "idf": 4.8343, "tf": 5, "in_doc": true}, {"token": "waris", "contribution": 4.2312, "idf": 3.4756, "tf": 2, "in_doc": true}, {"token": "ahli", "contribution": 3.9474, "idf": 3.2424, "tf": 2, "in_doc": true}, {"token": "meninggal", "contribution": 3.1667, "idf": 3.9356, "tf": 1, "in_doc": true}, {"token": "dari", "contribution": 2.1046, "idf": 2.6156, "tf": 1, "in_doc": true}, {"token": "dan", "contribution": 1.2543, "idf": 1.5588, "tf": 1, "in_doc": true}, {"token": "mengapa", "contribution": 0.0, "idf": 0.0, "tf": 0, "in_doc": false}, {"token": "pengadilan", "contribution": 0.0, "idf": 0.0, "tf": 0, "in_doc": false}, {"token": "menolak", "contribution": 0.0, "idf": 0.0, "tf": 0, "in_doc": false}, {"token": "penggugat", "contribution": 0.0, "idf": 0.0, "tf": 0, "in_doc": false}, {"token": "karena", "contribution": 0.0, "idf": 0.0, "tf": 0, "in_doc": false}, {"token": "dianggap", "contribution": 0.0, "idf": 0.0, "tf": 0, "in_doc": false}, {"token": "kurang", "contribution": 0.0, "idf": 0.0, "tf": 0, "in_doc": false}, {"token": "melibatkan", "contribution": 0.0, "idf": 0.0, "tf": 0, "in_doc": false}, {"token": "lain", "contribution": 0.0, "idf": 0.0, "tf": 0, "in_doc": false}, {"token": "pemilik", "contribution": 0.0, "idf": 0.0, "tf": 0, "in_doc": false}, {"token": "tanah", "contribution": 0.0, "idf": 0.0, "tf": 0, "in_doc": false}, {"token": "yang", "contribution": 0.0, "idf": 0.0, "tf": 5, "in_doc": true}, {"token": "padahal", "contribution": 0.0, "idf": 0.0, "tf": 0, "in_doc": false}, {"token": "tergugat", "contribution": 0.0, "idf": 0.0, "tf": 0, "in_doc": false}], "doc_highlights": [{"start": 12, "end": 19, "token": "gugatan", "intensity": 1.0, "score": 8.5027}, {"start": 92, "end": 96, "token": "dari", "intensity": 0.248, "score": 2.1046}, {"start": 132, "end": 139, "token": "gugatan", "intensity": 1.0, "score": 8.5027}, {"start": 152, "end": 155, "token": "dan", "intensity": 0.148, "score": 1.2543}, {"start": 188, "end": 195, "token": "gugatan", "intensity": 1.0, "score": 8.5027}, {"start": 245, "end": 249, "token": "ahli", "intensity": 0.464, "score": 3.9474}, {"start": 250, "end": 255, "token": "waris", "intensity": 0.498, "score": 4.2312}, {"start": 299, "end": 303, "token": "ahli", "intensity": 0.464, "score": 3.9474}, {"start": 304, "end": 309, "token": "waris", "intensity": 0.498, "score": 4.2312}, {"start": 343, "end": 350, "token": "gugatan", "intensity": 1.0, "score": 8.5027}, {"start": 399, "end": 406, "token": "gugatan", "intensity": 1.0, "score": 8.5027}, {"start": 466, "end": 475, "token": "meninggal", "intensity": 0.372, "score": 3.1667}], "query_highlights": [{"start": 27, "end": 34, "token": "gugatan", "intensity": 1.0, "score": 8.5027}, {"start": 81, "end": 85, "token": "ahli", "intensity": 0.464, "score": 3.9474}, {"start": 86, "end": 91, "token": "waris", "intensity": 0.498, "score": 4.2312}, {"start": 97, "end": 101, "token": "dari", "intensity": 0.248, "score": 2.1046}, {"start": 121, "end": 130, "token": "meninggal", "intensity": 0.372, "score": 3.1667}, {"start": 152, "end": 155, "token": "dan", "intensity": 0.148, "score": 1.2543}]}, {"rank": 5, "doc_id": "1380", "title": "Pasal 1380", "bm25_score": 16.5138, "is_relevant": false, "per_token": [{"token": "tergugat", "contribution": 8.3554, "idf": 6.3604, "tf": 1, "in_doc": true}, {"token": "penggugat", "contribution": 8.1159, "idf": 6.178, "tf": 1, "in_doc": true}, {"token": "dari", "contribution": 3.436, "idf": 2.6156, "tf": 1, "in_doc": true}, {"token": "dan", "contribution": 2.0478, "idf": 1.5588, "tf": 1, "in_doc": true}, {"token": "mengapa", "contribution": 0.0, "idf": 0.0, "tf": 0, "in_doc": false}, {"token": "pengadilan", "contribution": 0.0, "idf": 0.0, "tf": 0, "in_doc": false}, {"token": "menolak", "contribution": 0.0, "idf": 0.0, "tf": 0, "in_doc": false}, {"token": "gugatan", "contribution": 0.0, "idf": 0.0, "tf": 0, "in_doc": false}, {"token": "karena", "contribution": 0.0, "idf": 0.0, "tf": 0, "in_doc": false}, {"token": "dianggap", "contribution": 0.0, "idf": 0.0, "tf": 0, "in_doc": false}, {"token": "kurang", "contribution": 0.0, "idf": 0.0, "tf": 0, "in_doc": false}, {"token": "melibatkan", "contribution": 0.0, "idf": 0.0, "tf": 0, "in_doc": false}, {"token": "ahli", "contribution": 0.0, "idf": 0.0, "tf": 0, "in_doc": false}, {"token": "waris", "contribution": 0.0, "idf": 0.0, "tf": 0, "in_doc": false}, {"token": "lain", "contribution": 0.0, "idf": 0.0, "tf": 0, "in_doc": false}, {"token": "pemilik", "contribution": 0.0, "idf": 0.0, "tf": 0, "in_doc": false}, {"token": "tanah", "contribution": 0.0, "idf": 0.0, "tf": 0, "in_doc": false}, {"token": "yang", "contribution": 0.0, "idf": 0.0, "tf": 0, "in_doc": false}, {"token": "meninggal", "contribution": 0.0, "idf": 0.0, "tf": 0, "in_doc": false}, {"token": "padahal", "contribution": 0.0, "idf": 0.0, "tf": 0, "in_doc": false}], "doc_highlights": [{"start": 102, "end": 106, "token": "dari", "intensity": 0.411, "score": 3.436}, {"start": 147, "end": 155, "token": "tergugat", "intensity": 1.0, "score": 8.3554}, {"start": 156, "end": 159, "token": "dan", "intensity": 0.245, "score": 2.0478}, {"start": 175, "end": 184, "token": "penggugat", "intensity": 0.971, "score": 8.1159}], "query_highlights": [{"start": 36, "end": 45, "token": "penggugat", "intensity": 0.971, "score": 8.1159}, {"start": 97, "end": 101, "token": "dari", "intensity": 0.411, "score": 3.436}, {"start": 141, "end": 150, "token": "penggugat", "intensity": 0.971, "score": 8.1159}, {"start": 152, "end": 155, "token": "dan", "intensity": 0.245, "score": 2.0478}, {"start": 157, "end": 165, "token": "tergugat", "intensity": 1.0, "score": 8.3554}]}, {"rank": 6, "doc_id": "1651", "title": "Pasal 1651", "bm25_score": 16.4434, "is_relevant": false, "per_token": [{"token": "meninggal", "contribution": 4.6947, "idf": 3.9356, "tf": 2, "in_doc": true}, {"token": "ahli", "contribution": 4.6842, "idf": 3.2424, "tf": 3, "in_doc": true}, {"token": "waris", "contribution": 4.1459, "idf": 3.4756, "tf": 2, "in_doc": true}, {"token": "perjanjian", "contribution": 4.0499, "idf": 3.3951, "tf": 2, "in_doc": true}, {"token": "sudah", "contribution": 3.5658, "idf": 4.5521, "tf": 1, "in_doc": true}, {"token": "dari", "contribution": 2.0488, "idf": 2.6156, "tf": 1, "in_doc": true}, {"token": "mengapa", "contribution": 0.0, "idf": 0.0, "tf": 0, "in_doc": false}, {"token": "pengadilan", "contribution": 0.0, "idf": 0.0, "tf": 0, "in_doc": false}, {"token": "menolak", "contribution": 0.0, "idf": 0.0, "tf": 0, "in_doc": false}, {"token": "gugatan", "contribution": 0.0, "idf": 0.0, "tf": 0, "in_doc": false}, {"token": "penggugat", "contribution": 0.0, "idf": 0.0, "tf": 0, "in_doc": false}, {"token": "karena", "contribution": 0.0, "idf": 0.0, "tf": 0, "in_doc": false}, {"token": "dianggap", "contribution": 0.0, "idf": 0.0, "tf": 0, "in_doc": false}, {"token": "kurang", "contribution": 0.0, "idf": 0.0, "tf": 0, "in_doc": false}, {"token": "melibatkan", "contribution": 0.0, "idf": 0.0, "tf": 0, "in_doc": false}, {"token": "lain", "contribution": 0.0, "idf": 0.0, "tf": 0, "in_doc": false}, {"token": "pemilik", "contribution": 0.0, "idf": 0.0, "tf": 0, "in_doc": false}, {"token": "tanah", "contribution": 0.0, "idf": 0.0, "tf": 0, "in_doc": false}, {"token": "yang", "contribution": 0.0, "idf": 0.0, "tf": 4, "in_doc": true}, {"token": "padahal", "contribution": 0.0, "idf": 0.0, "tf": 0, "in_doc": false}], "doc_highlights": [{"start": 70, "end": 79, "token": "meninggal", "intensity": 1.0, "score": 4.6947}, {"start": 120, "end": 124, "token": "ahli", "intensity": 0.998, "score": 4.6842}, {"start": 216, "end": 226, "token": "perjanjian", "intensity": 0.863, "score": 4.0499}, {"start": 261, "end": 271, "token": "perjanjian", "intensity": 0.863, "score": 4.0499}, {"start": 283, "end": 287, "token": "ahli", "intensity": 0.998, "score": 4.6842}, {"start": 288, "end": 293, "token": "waris", "intensity": 0.883, "score": 4.1459}, {"start": 313, "end": 322, "token": "meninggal", "intensity": 1.0, "score": 4.6947}, {"start": 478, "end": 482, "token": "dari", "intensity": 0.436, "score": 2.0488}, {"start": 544, "end": 549, "token": "sudah", "intensity": 0.76, "score": 3.5658}, {"start": 605, "end": 609, "token": "ahli", "intensity": 0.998, "score": 4.6842}, {"start": 610, "end": 615, "token": "waris", "intensity": 0.883, "score": 4.1459}], "query_highlights": [{"start": 81, "end": 85, "token": "ahli", "intensity": 0.998, "score": 4.6842}, {"start": 86, "end": 91, "token": "waris", "intensity": 0.883, "score": 4.1459}, {"start": 97, "end": 101, "token": "dari", "intensity": 0.436, "score": 2.0488}, {"start": 121, "end": 130, "token": "meninggal", "intensity": 1.0, "score": 4.6947}, {"start": 167, "end": 172, "token": "sudah", "intensity": 0.76, "score": 3.5658}, {"start": 188, "end": 198, "token": "perjanjian", "intensity": 0.863, "score": 4.0499}]}, {"rank": 7, "doc_id": "1591", "title": "Pasal 1591", "bm25_score": 16.1576, "is_relevant": false, "per_token": [{"token": "tanah", "contribution": 6.6428, "idf": 3.9808, "tf": 3, "in_doc": true}, {"token": "gugatan", "contribution": 4.845, "idf": 4.8343, "tf": 1, "in_doc": true}, {"token": "pemilik", "contribution": 3.8115, "idf": 3.8031, "tf": 1, "in_doc": true}, {"token": "pengadilan", "contribution": 3.2407, "idf": 3.2336, "tf": 1, "in_doc": true}, {"token": "dari", "contribution": 2.6214, "idf": 2.6156, "tf": 1, "in_doc": true}, {"token": "dan", "contribution": 1.5622, "idf": 1.5588, "tf": 1, "in_doc": true}, {"token": "mengapa", "contribution": 0.0, "idf": 0.0, "tf": 0, "in_doc": false}, {"token": "menolak", "contribution": 0.0, "idf": 0.0, "tf": 0, "in_doc": false}, {"token": "penggugat", "contribution": 0.0, "idf": 0.0, "tf": 0, "in_doc": false}, {"token": "karena", "contribution": 0.0, "idf": 0.0, "tf": 0, "in_doc": false}, {"token": "dianggap", "contribution": 0.0, "idf": 0.0, "tf": 0, "in_doc": false}, {"token": "kurang", "contribution": 0.0, "idf": 0.0, "tf": 0, "in_doc": false}, {"token": "melibatkan", "contribution": 0.0, "idf": 0.0, "tf": 0, "in_doc": false}, {"token": "ahli", "contribution": 0.0, "idf": 0.0, "tf": 0, "in_doc": false}, {"token": "waris", "contribution": 0.0, "idf": 0.0, "tf": 0, "in_doc": false}, {"token": "lain", "contribution": 0.0, "idf": 0.0, "tf": 0, "in_doc": false}, {"token": "yang", "contribution": 0.0, "idf": 0.0, "tf": 4, "in_doc": true}, {"token": "meninggal", "contribution": 0.0, "idf": 0.0, "tf": 0, "in_doc": false}, {"token": "padahal", "contribution": 0.0, "idf": 0.0, "tf": 0, "in_doc": false}, {"token": "tergugat", "contribution": 0.0, "idf": 0.0, "tf": 0, "in_doc": false}], "doc_highlights": [{"start": 20, "end": 25, "token": "tanah", "intensity": 1.0, "score": 6.6428}, {"start": 79, "end": 82, "token": "dan", "intensity": 0.235, "score": 1.5622}, {"start": 114, "end": 121, "token": "pemilik", "intensity": 0.574, "score": 3.8115}, {"start": 122, "end": 127, "token": "tanah", "intensity": 1.0, "score": 6.6428}, {"start": 182, "end": 187, "token": "tanah", "intensity": 1.0, "score": 6.6428}, {"start": 301, "end": 308, "token": "gugatan", "intensity": 0.729, "score": 4.845}, {"start": 309, "end": 313, "token": "dari", "intensity": 0.395, "score": 2.6214}, {"start": 344, "end": 354, "token": "pengadilan", "intensity": 0.488, "score": 3.2407}], "query_highlights": [{"start": 8, "end": 18, "token": "pengadilan", "intensity": 0.488, "score": 3.2407}, {"start": 27, "end": 34, "token": "gugatan", "intensity": 0.729, "score": 4.845}, {"start": 97, "end": 101, "token": "dari", "intensity": 0.395, "score": 2.6214}, {"start": 102, "end": 109, "token": "pemilik", "intensity": 0.574, "score": 3.8115}, {"start": 110, "end": 115, "token": "tanah", "intensity": 1.0, "score": 6.6428}, {"start": 152, "end": 155, "token": "dan", "intensity": 0.235, "score": 1.5622}]}, {"rank": 8, "doc_id": "599", "title": "Pasal 599", "bm25_score": 16.1008, "is_relevant": false, "per_token": [{"token": "tanah", "contribution": 7.6859, "idf": 3.9808, "tf": 6, "in_doc": true}, {"token": "pemilik", "contribution": 3.4336, "idf": 3.8031, "tf": 1, "in_doc": true}, {"token": "dianggap", "contribution": 3.3157, "idf": 3.6725, "tf": 1, "in_doc": true}, {"token": "karena", "contribution": 2.7404, "idf": 3.0353, "tf": 1, "in_doc": true}, {"token": "lain", "contribution": 2.4141, "idf": 2.674, "tf": 1, "in_doc": true}, {"token": "dari", "contribution": 2.3614, "idf": 2.6156, "tf": 1, "in_doc": true}, {"token": "dan", "contribution": 1.4073, "idf": 1.5588, "tf": 1, "in_doc": true}, {"token": "mengapa", "contribution": 0.0, "idf": 0.0, "tf": 0, "in_doc": false}, {"token": "pengadilan", "contribution": 0.0, "idf": 0.0, "tf": 0, "in_doc": false}, {"token": "menolak", "contribution": 0.0, "idf": 0.0, "tf": 0, "in_doc": false}, {"token": "gugatan", "contribution": 0.0, "idf": 0.0, "tf": 0, "in_doc": false}, {"token": "penggugat", "contribution": 0.0, "idf": 0.0, "tf": 0, "in_doc": false}, {"token": "kurang", "contribution": 0.0, "idf": 0.0, "tf": 0, "in_doc": false}, {"token": "melibatkan", "contribution": 0.0, "idf": 0.0, "tf": 0, "in_doc": false}, {"token": "ahli", "contribution": 0.0, "idf": 0.0, "tf": 0, "in_doc": false}, {"token": "waris", "contribution": 0.0, "idf": 0.0, "tf": 0, "in_doc": false}, {"token": "yang", "contribution": 0.0, "idf": 0.0, "tf": 5, "in_doc": true}, {"token": "meninggal", "contribution": 0.0, "idf": 0.0, "tf": 0, "in_doc": false}, {"token": "padahal", "contribution": 0.0, "idf": 0.0, "tf": 0, "in_doc": false}, {"token": "tergugat", "contribution": 0.0, "idf": 0.0, "tf": 0, "in_doc": false}], "doc_highlights": [{"start": 25, "end": 30, "token": "tanah", "intensity": 1.0, "score": 7.6859}, {"start": 32, "end": 38, "token": "karena", "intensity": 0.357, "score": 2.7404}, {"start": 80, "end": 84, "token": "dari", "intensity": 0.307, "score": 2.3614}, {"start": 85, "end": 90, "token": "tanah", "intensity": 1.0, "score": 7.6859}, {"start": 101, "end": 104, "token": "dan", "intensity": 0.183, "score": 1.4073}, {"start": 118, "end": 123, "token": "tanah", "intensity": 1.0, "score": 7.6859}, {"start": 129, "end": 133, "token": "lain", "intensity": 0.314, "score": 2.4141}, {"start": 165, "end": 173, "token": "dianggap", "intensity": 0.431, "score": 3.3157}, {"start": 194, "end": 199, "token": "tanah", "intensity": 1.0, "score": 7.6859}, {"start": 388, "end": 393, "token": "tanah", "intensity": 1.0, "score": 7.6859}, {"start": 430, "end": 437, "token": "pemilik", "intensity": 0.447, "score": 3.4336}, {"start": 438, "end": 443, "token": "tanah", "intensity": 1.0, "score": 7.6859}], "query_highlights": [{"start": 47, "end": 53, "token": "karena", "intensity": 0.357, "score": 2.7404}, {"start": 54, "end": 62, "token": "dianggap", "intensity": 0.431, "score": 3.3157}, {"start": 92, "end": 96, "token": "lain", "intensity": 0.314, "score": 2.4141}, {"start": 97, "end": 101, "token": "dari", "intensity": 0.307, "score": 2.3614}, {"start": 102, "end": 109, "token": "pemilik", "intensity": 0.447, "score": 3.4336}, {"start": 110, "end": 115, "token": "tanah", "intensity": 1.0, "score": 7.6859}, {"start": 152, "end": 155, "token": "dan", "intensity": 0.183, "score": 1.4073}]}, {"rank": 9, "doc_id": "1064", "title": "Pasal 1064", "bm25_score": 15.7168, "is_relevant": false, "per_token": [{"token": "menolak", "contribution": 7.458, "idf": 4.8343, "tf": 2, "in_doc": true}, {"token": "waris", "contribution": 5.3618, "idf": 3.4756, "tf": 2, "in_doc": true}, {"token": "ahli", "contribution": 5.0021, "idf": 3.2424, "tf": 2, "in_doc": true}, {"token": "dari", "contribution": 2.9178, "idf": 2.6156, "tf": 1, "in_doc": true}, {"token": "dan", "contribution": 1.7389, "idf": 1.5588, "tf": 1, "in_doc": true}, {"token": "mengapa", "contribution": 0.0, "idf": 0.0, "tf": 0, "in_doc": false}, {"token": "pengadilan", "contribution": 0.0, "idf": 0.0, "tf": 0, "in_doc": false}, {"token": "gugatan", "contribution": 0.0, "idf": 0.0, "tf": 0, "in_doc": false}, {"token": "penggugat", "contribution": 0.0, "idf": 0.0, "tf": 0, "in_doc": false}, {"token": "karena", "contribution": 0.0, "idf": 0.0, "tf": 0, "in_doc": false}, {"token": "dianggap", "contribution": 0.0, "idf": 0.0, "tf": 0, "in_doc": false}, {"token": "kurang", "contribution": 0.0, "idf": 0.0, "tf": 0, "in_doc": false}, {"token": "melibatkan", "contribution": 0.0, "idf": 0.0, "tf": 0, "in_doc": false}, {"token": "lain", "contribution": 0.0, "idf": 0.0, "tf": 0, "in_doc": false}, {"token": "pemilik", "contribution": 0.0, "idf": 0.0, "tf": 0, "in_doc": false}, {"token": "tanah", "contribution": 0.0, "idf": 0.0, "tf": 0, "in_doc": false}, {"token": "yang", "contribution": 0.0, "idf": 0.0, "tf": 3, "in_doc": true}, {"token": "meninggal", "contribution": 0.0, "idf": 0.0, "tf": 0, "in_doc": false}, {"token": "padahal", "contribution": 0.0, "idf": 0.0, "tf": 0, "in_doc": false}, {"token": "tergugat", "contribution": 0.0, "idf": 0.0, "tf": 0, "in_doc": false}], "doc_highlights": [{"start": 12, "end": 16, "token": "ahli", "intensity": 0.671, "score": 5.0021}, {"start": 17, "end": 22, "token": "waris", "intensity": 0.719, "score": 5.3618}, {"start": 135, "end": 142, "token": "menolak", "intensity": 1.0, "score": 7.458}, {"start": 172, "end": 176, "token": "ahli", "intensity": 0.671, "score": 5.0021}, {"start": 177, "end": 182, "token": "waris", "intensity": 0.719, "score": 5.3618}, {"start": 202, "end": 209, "token": "menolak", "intensity": 1.0, "score": 7.458}, {"start": 211, "end": 214, "token": "dan", "intensity": 0.233, "score": 1.7389}, {"start": 253, "end": 257, "token": "dari", "intensity": 0.391, "score": 2.9178}], "query_highlights": [{"start": 19, "end": 26, "token": "menolak", "intensity": 1.0, "score": 7.458}, {"start": 81, "end": 85, "token": "ahli", "intensity": 0.671, "score": 5.0021}, {"start": 86, "end": 91, "token": "waris", "intensity": 0.719, "score": 5.3618}, {"start": 97, "end": 101, "token": "dari", "intensity": 0.391, "score": 2.9178}, {"start": 152, "end": 155, "token": "dan", "intensity": 0.233, "score": 1.7389}]}, {"rank": 10, "doc_id": "258", "title": "Pasal 258", "bm25_score": 15.3649, "is_relevant": false, "per_token": [{"token": "padahal", "contribution": 7.3639, "idf": 7.9698, "tf": 1, "in_doc": true}, {"token": "gugatan", "contribution": 4.4668, "idf": 4.8343, "tf": 1, "in_doc": true}, {"token": "ahli", "contribution": 4.3749, "idf": 3.2424, "tf": 2, "in_doc": true}, {"token": "meninggal", "contribution": 3.6363, "idf": 3.9356, "tf": 1, "in_doc": true}, {"token": "mengapa", "contribution": 0.0, "idf": 0.0, "tf": 0, "in_doc": false}, {"token": "pengadilan", "contribution": 0.0, "idf": 0.0, "tf": 0, "in_doc": false}, {"token": "menolak", "contribution": 0.0, "idf": 0.0, "tf": 0, "in_doc": false}, {"token": "penggugat", "contribution": 0.0, "idf": 0.0, "tf": 0, "in_doc": false}, {"token": "karena", "contribution": 0.0, "idf": 0.0, "tf": 0, "in_doc": false}, {"token": "dianggap", "contribution": 0.0, "idf": 0.0, "tf": 0, "in_doc": false}, {"token": "kurang", "contribution": 0.0, "idf": 0.0, "tf": 0, "in_doc": false}, {"token": "melibatkan", "contribution": 0.0, "idf": 0.0, "tf": 0, "in_doc": false}, {"token": "waris", "contribution": 0.0, "idf": 0.0, "tf": 0, "in_doc": false}, {"token": "lain", "contribution": 0.0, "idf": 0.0, "tf": 0, "in_doc": false}, {"token": "dari", "contribution": 0.0, "idf": 0.0, "tf": 0, "in_doc": false}, {"token": "pemilik", "contribution": 0.0, "idf": 0.0, "tf": 0, "in_doc": false}, {"token": "tanah", "contribution": 0.0, "idf": 0.0, "tf": 0, "in_doc": false}, {"token": "yang", "contribution": 0.0, "idf": 0.0, "tf": 0, "in_doc": false}, {"token": "dan", "contribution": 0.0, "idf": 0.0, "tf": 0, "in_doc": false}, {"token": "tergugat", "contribution": 0.0, "idf": 0.0, "tf": 0, "in_doc": false}], "doc_highlights": [{"start": 22, "end": 31, "token": "meninggal", "intensity": 0.494, "score": 3.6363}, {"start": 69, "end": 76, "token": "padahal", "intensity": 1.0, "score": 7.3639}, {"start": 122, "end": 126, "token": "ahli", "intensity": 0.594, "score": 4.3749}, {"start": 216, "end": 223, "token": "gugatan", "intensity": 0.607, "score": 4.4668}, {"start": 364, "end": 368, "token": "ahli", "intensity": 0.594, "score": 4.3749}], "query_highlights": [{"start": 27, "end": 34, "token": "gugatan", "intensity": 0.607, "score": 4.4668}, {"start": 81, "end": 85, "token": "ahli", "intensity": 0.594, "score": 4.3749}, {"start": 121, "end": 130, "token": "meninggal", "intensity": 0.494, "score": 3.6363}, {"start": 132, "end": 139, "token": "padahal", "intensity": 1.0, "score": 7.3639}]}, {"rank": 11, "doc_id": "161", "title": "Pasal 161", "bm25_score": 15.2902, "is_relevant": false, "per_token": [{"token": "karena", "contribution": 4.9065, "idf": 3.0353, "tf": 2, "in_doc": true}, {"token": "tanah", "contribution": 4.7546, "idf": 3.9808, "tf": 1, "in_doc": true}, {"token": "pemilik", "contribution": 4.5423, "idf": 3.8031, "tf": 1, "in_doc": true}, {"token": "dianggap", "contribution": 4.3863, "idf": 3.6725, "tf": 1, "in_doc": true}, {"token": "lain", "contribution": 3.1937, "idf": 2.674, "tf": 1, "in_doc": true}, {"token": "mengapa", "contribution": 0.0, "idf": 0.0, "tf": 0, "in_doc": false}, {"token": "pengadilan", "contribution": 0.0, "idf": 0.0, "tf": 0, "in_doc": false}, {"token": "menolak", "contribution": 0.0, "idf": 0.0, "tf": 0, "in_doc": false}, {"token": "gugatan", "contribution": 0.0, "idf": 0.0, "tf": 0, "in_doc": false}, {"token": "penggugat", "contribution": 0.0, "idf": 0.0, "tf": 0, "in_doc": false}, {"token": "kurang", "contribution": 0.0, "idf": 0.0, "tf": 0, "in_doc": false}, {"token": "melibatkan", "contribution": 0.0, "idf": 0.0, "tf": 0, "in_doc": false}, {"token": "ahli", "contribution": 0.0, "idf": 0.0, "tf": 0, "in_doc": false}, {"token": "waris", "contribution": 0.0, "idf": 0.0, "tf": 0, "in_doc": false}, {"token": "dari", "contribution": 0.0, "idf": 0.0, "tf": 0, "in_doc": false}, {"token": "yang", "contribution": 0.0, "idf": 0.0, "tf": 1, "in_doc": true}, {"token": "meninggal", "contribution": 0.0, "idf": 0.0, "tf": 0, "in_doc": false}, {"token": "padahal", "contribution": 0.0, "idf": 0.0, "tf": 0, "in_doc": false}, {"token": "dan", "contribution": 0.0, "idf": 0.0, "tf": 0, "in_doc": false}, {"token": "tergugat", "contribution": 0.0, "idf": 0.0, "tf": 0, "in_doc": false}], "doc_highlights": [{"start": 55, "end": 61, "token": "karena", "intensity": 1.0, "score": 4.9065}, {"start": 74, "end": 79, "token": "tanah", "intensity": 0.969, "score": 4.7546}, {"start": 134, "end": 140, "token": "karena", "intensity": 1.0, "score": 4.9065}, {"start": 149, "end": 153, "token": "lain", "intensity": 0.651, "score": 3.1937}, {"start": 161, "end": 169, "token": "dianggap", "intensity": 0.894, "score": 4.3863}, {"start": 228, "end": 235, "token": "pemilik", "intensity": 0.926, "score": 4.5423}], "query_highlights": [{"start": 47, "end": 53, "token": "karena", "intensity": 1.0, "score": 4.9065}, {"start": 54, "end": 62, "token": "dianggap", "intensity": 0.894, "score": 4.3863}, {"start": 92, "end": 96, "token": "lain", "intensity": 0.651, "score": 3.1937}, {"start": 102, "end": 109, "token": "pemilik", "intensity": 0.926, "score": 4.5423}, {"start": 110, "end": 115, "token": "tanah", "intensity": 0.969, "score": 4.7546}]}, {"rank": 12, "doc_id": "212", "title": "Pasal 212", "bm25_score": 15.1488, "is_relevant": false, "per_token": [{"token": "tergugat", "contribution": 7.674, "idf": 6.3604, "tf": 1, "in_doc": true}, {"token": "penggugat", "contribution": 7.4541, "idf": 6.178, "tf": 1, "in_doc": true}, {"token": "pengadilan", "contribution": 3.9015, "idf": 3.2336, "tf": 1, "in_doc": true}, {"token": "mengapa", "contribution": 0.0, "idf": 0.0, "tf": 0, "in_doc": false}, {"token": "menolak", "contribution": 0.0, "idf": 0.0, "tf": 0, "in_doc": false}, {"token": "gugatan", "contribution": 0.0, "idf": 0.0, "tf": 0, "in_doc": false}, {"token": "karena", "contribution": 0.0, "idf": 0.0, "tf": 0, "in_doc": false}, {"token": "dianggap", "contribution": 0.0, "idf": 0.0, "tf": 0, "in_doc": false}, {"token": "kurang", "contribution": 0.0, "idf": 0.0, "tf": 0, "in_doc": false}, {"token": "melibatkan", "contribution": 0.0, "idf": 0.0, "tf": 0, "in_doc": false}, {"token": "ahli", "contribution": 0.0, "idf": 0.0, "tf": 0, "in_doc": false}, {"token": "waris", "contribution": 0.0, "idf": 0.0, "tf": 0, "in_doc": false}, {"token": "lain", "contribution": 0.0, "idf": 0.0, "tf": 0, "in_doc": false}, {"token": "dari", "contribution": 0.0, "idf": 0.0, "tf": 0, "in_doc": false}, {"token": "pemilik", "contribution": 0.0, "idf": 0.0, "tf": 0, "in_doc": false}, {"token": "tanah", "contribution": 0.0, "idf": 0.0, "tf": 0, "in_doc": false}, {"token": "yang", "contribution": 0.0, "idf": 0.0, "tf": 0, "in_doc": false}, {"token": "meninggal", "contribution": 0.0, "idf": 0.0, "tf": 0, "in_doc": false}, {"token": "padahal", "contribution": 0.0, "idf": 0.0, "tf": 0, "in_doc": false}, {"token": "dan", "contribution": 0.0, "idf": 0.0, "tf": 0, "in_doc": false}], "doc_highlights": [{"start": 36, "end": 45, "token": "penggugat", "intensity": 0.971, "score": 7.4541}, {"start": 78, "end": 86, "token": "tergugat", "intensity": 1.0, "score": 7.674}, {"start": 175, "end": 185, "token": "pengadilan", "intensity": 0.508, "score": 3.9015}], "query_highlights": [{"start": 8, "end": 18, "token": "pengadilan", "intensity": 0.508, "score": 3.9015}, {"start": 36, "end": 45, "token": "penggugat", "intensity": 0.971, "score": 7.4541}, {"start": 141, "end": 150, "token": "penggugat", "intensity": 0.971, "score": 7.4541}, {"start": 157, "end": 165, "token": "tergugat", "intensity": 1.0, "score": 7.674}]}, {"rank": 13, "doc_id": "803", "title": "Pasal 803", "bm25_score": 14.9965, "is_relevant": false, "per_token": [{"token": "tergugat", "contribution": 6.2165, "idf": 6.3604, "tf": 1, "in_doc": true}, {"token": "penggugat", "contribution": 6.0383, "idf": 6.178, "tf": 1, "in_doc": true}, {"token": "pemilik", "contribution": 5.3447, "idf": 3.8031, "tf": 2, "in_doc": true}, {"token": "dan", "contribution": 2.565, "idf": 1.5588, "tf": 3, "in_doc": true}, {"token": "mengapa", "contribution": 0.0, "idf": 0.0, "tf": 0, "in_doc": false}, {"token": "pengadilan", "contribution": 0.0, "idf": 0.0, "tf": 0, "in_doc": false}, {"token": "menolak", "contribution": 0.0, "idf": 0.0, "tf": 0, "in_doc": false}, {"token": "gugatan", "contribution": 0.0, "idf": 0.0, "tf": 0, "in_doc": false}, {"token": "karena", "contribution": 0.0, "idf": 0.0, "tf": 0, "in_doc": false}, {"token": "dianggap", "contribution": 0.0, "idf": 0.0, "tf": 0, "in_doc": false}, {"token": "kurang", "contribution": 0.0, "idf": 0.0, "tf": 0, "in_doc": false}, {"token": "melibatkan", "contribution": 0.0, "idf": 0.0, "tf": 0, "in_doc": false}, {"token": "ahli", "contribution": 0.0, "idf": 0.0, "tf": 0, "in_doc": false}, {"token": "waris", "contribution": 0.0, "idf": 0.0, "tf": 0, "in_doc": false}, {"token": "lain", "contribution": 0.0, "idf": 0.0, "tf": 0, "in_doc": false}, {"token": "dari", "contribution": 0.0, "idf": 0.0, "tf": 0, "in_doc": false}, {"token": "tanah", "contribution": 0.0, "idf": 0.0, "tf": 0, "in_doc": false}, {"token": "yang", "contribution": 0.0, "idf": 0.0, "tf": 2, "in_doc": true}, {"token": "meninggal", "contribution": 0.0, "idf": 0.0, "tf": 0, "in_doc": false}, {"token": "padahal", "contribution": 0.0, "idf": 0.0, "tf": 0, "in_doc": false}], "doc_highlights": [{"start": 125, "end": 132, "token": "pemilik", "intensity": 0.86, "score": 5.3447}, {"start": 133, "end": 136, "token": "dan", "intensity": 0.413, "score": 2.565}, {"start": 190, "end": 193, "token": "dan", "intensity": 0.413, "score": 2.565}, {"start": 227, "end": 230, "token": "dan", "intensity": 0.413, "score": 2.565}, {"start": 266, "end": 275, "token": "penggugat", "intensity": 0.971, "score": 6.0383}, {"start": 291, "end": 299, "token": "tergugat", "intensity": 1.0, "score": 6.2165}, {"start": 349, "end": 356, "token": "pemilik", "intensity": 0.86, "score": 5.3447}], "query_highlights": [{"start": 36, "end": 45, "token": "penggugat", "intensity": 0.971, "score": 6.0383}, {"start": 102, "end": 109, "token": "pemilik", "intensity": 0.86, "score": 5.3447}, {"start": 141, "end": 150, "token": "penggugat", "intensity": 0.971, "score": 6.0383}, {"start": 152, "end": 155, "token": "dan", "intensity": 0.413, "score": 2.565}, {"start": 157, "end": 165, "token": "tergugat", "intensity": 1.0, "score": 6.2165}]}, {"rank": 14, "doc_id": "1092", "title": "Pasal 1092", "bm25_score": 14.8515, "is_relevant": false, "per_token": [{"token": "kurang", "contribution": 7.067, "idf": 5.6184, "tf": 1, "in_doc": true}, {"token": "waris", "contribution": 4.3717, "idf": 3.4756, "tf": 1, "in_doc": true}, {"token": "ahli", "contribution": 4.0784, "idf": 3.2424, "tf": 1, "in_doc": true}, {"token": "lain", "contribution": 3.3634, "idf": 2.674, "tf": 1, "in_doc": true}, {"token": "dan", "contribution": 1.9607, "idf": 1.5588, "tf": 1, "in_doc": true}, {"token": "mengapa", "contribution": 0.0, "idf": 0.0, "tf": 0, "in_doc": false}, {"token": "pengadilan", "contribution": 0.0, "idf": 0.0, "tf": 0, "in_doc": false}, {"token": "menolak", "contribution": 0.0, "idf": 0.0, "tf": 0, "in_doc": false}, {"token": "gugatan", "contribution": 0.0, "idf": 0.0, "tf": 0, "in_doc": false}, {"token": "penggugat", "contribution": 0.0, "idf": 0.0, "tf": 0, "in_doc": false}, {"token": "karena", "contribution": 0.0, "idf": 0.0, "tf": 0, "in_doc": false}, {"token": "dianggap", "contribution": 0.0, "idf": 0.0, "tf": 0, "in_doc": false}, {"token": "melibatkan", "contribution": 0.0, "idf": 0.0, "tf": 0, "in_doc": false}, {"token": "dari", "contribution": 0.0, "idf": 0.0, "tf": 0, "in_doc": false}, {"token": "pemilik", "contribution": 0.0, "idf": 0.0, "tf": 0, "in_doc": false}, {"token": "tanah", "contribution": 0.0, "idf": 0.0, "tf": 0, "in_doc": false}, {"token": "yang", "contribution": 0.0, "idf": 0.0, "tf": 3, "in_doc": true}, {"token": "meninggal", "contribution": 0.0, "idf": 0.0, "tf": 0, "in_doc": false}, {"token": "padahal", "contribution": 0.0, "idf": 0.0, "tf": 0, "in_doc": false}, {"token": "tergugat", "contribution": 0.0, "idf": 0.0, "tf": 0, "in_doc": false}], "doc_highlights": [{"start": 158, "end": 164, "token": "kurang", "intensity": 1.0, "score": 7.067}, {"start": 165, "end": 168, "token": "dan", "intensity": 0.277, "score": 1.9607}, {"start": 174, "end": 178, "token": "ahli", "intensity": 0.577, "score": 4.0784}, {"start": 179, "end": 184, "token": "waris", "intensity": 0.619, "score": 4.3717}, {"start": 190, "end": 194, "token": "lain", "intensity": 0.476, "score": 3.3634}], "query_highlights": [{"start": 63, "end": 69, "token": "kurang", "intensity": 1.0, "score": 7.067}, {"start": 81, "end": 85, "token": "ahli", "intensity": 0.577, "score": 4.0784}, {"start": 86, "end": 91, "token": "waris", "intensity": 0.619, "score": 4.3717}, {"start": 92, "end": 96, "token": "lain", "intensity": 0.476, "score": 3.3634}, {"start": 152, "end": 155, "token": "dan", "intensity": 0.277, "score": 1.9607}]}, {"rank": 15, "doc_id": "1981", "title": "Pasal 1981", "bm25_score": 14.5491, "is_relevant": false, "per_token": [{"token": "penggugat", "contribution": 7.7709, "idf": 6.178, "tf": 1, "in_doc": true}, {"token": "gugatan", "contribution": 6.0807, "idf": 4.8343, "tf": 1, "in_doc": true}, {"token": "karena", "contribution": 5.08, "idf": 3.0353, "tf": 2, "in_doc": true}, {"token": "mengapa", "contribution": 0.0, "idf": 0.0, "tf": 0, "in_doc": false}, {"token": "pengadilan", "contribution": 0.0, "idf": 0.0, "tf": 0, "in_doc": false}, {"token": "menolak", "contribution": 0.0, "idf": 0.0, "tf": 0, "in_doc": false}, {"token": "dianggap", "contribution": 0.0, "idf": 0.0, "tf": 0, "in_doc": false}, {"token": "kurang", "contribution": 0.0, "idf": 0.0, "tf": 0, "in_doc": false}, {"token": "melibatkan", "contribution": 0.0, "idf": 0.0, "tf": 0, "in_doc": false}, {"token": "ahli", "contribution": 0.0, "idf": 0.0, "tf": 0, "in_doc": false}, {"token": "waris", "contribution": 0.0, "idf": 0.0, "tf": 0, "in_doc": false}, {"token": "lain", "contribution": 0.0, "idf": 0.0, "tf": 0, "in_doc": false}, {"token": "dari", "contribution": 0.0, "idf": 0.0, "tf": 0, "in_doc": false}, {"token": "pemilik", "contribution": 0.0, "idf": 0.0, "tf": 0, "in_doc": false}, {"token": "tanah", "contribution": 0.0, "idf": 0.0, "tf": 0, "in_doc": false}, {"token": "yang", "contribution": 0.0, "idf": 0.0, "tf": 0, "in_doc": false}, {"token": "meninggal", "contribution": 0.0, "idf": 0.0, "tf": 0, "in_doc": false}, {"token": "padahal", "contribution": 0.0, "idf": 0.0, "tf": 0, "in_doc": false}, {"token": "dan", "contribution": 0.0, "idf": 0.0, "tf": 0, "in_doc": false}, {"token": "tergugat", "contribution": 0.0, "idf": 0.0, "tf": 0, "in_doc": false}], "doc_highlights": [{"start": 66, "end": 73, "token": "gugatan", "intensity": 0.782, "score": 6.0807}, {"start": 111, "end": 117, "token": "karena", "intensity": 0.654, "score": 5.08}, {"start": 118, "end": 127, "token": "penggugat", "intensity": 1.0, "score": 7.7709}, {"start": 160, "end": 166, "token": "karena", "intensity": 0.654, "score": 5.08}], "query_highlights": [{"start": 27, "end": 34, "token": "gugatan", "intensity": 0.782, "score": 6.0807}, {"start": 36, "end": 45, "token": "penggugat", "intensity": 1.0, "score": 7.7709}, {"start": 47, "end": 53, "token": "karena", "intensity": 0.654, "score": 5.08}, {"start": 141, "end": 150, "token": "penggugat", "intensity": 1.0, "score": 7.7709}]}, {"rank": 16, "doc_id": "1531", "title": "Pasal 1531", "bm25_score": 14.3752, "is_relevant": false, "per_token": [{"token": "waris", "contribution": 5.7108, "idf": 3.4756, "tf": 4, "in_doc": true}, {"token": "sudah", "contribution": 5.5705, "idf": 4.5521, "tf": 2, "in_doc": true}, {"token": "ahli", "contribution": 5.3277, "idf": 3.2424, "tf": 4, "in_doc": true}, {"token": "dari", "contribution": 3.2007, "idf": 2.6156, "tf": 2, "in_doc": true}, {"token": "dan", "contribution": 1.2628, "idf": 1.5588, "tf": 1, "in_doc": true}, {"token": "mengapa", "contribution": 0.0, "idf": 0.0, "tf": 0, "in_doc": false}, {"token": "pengadilan", "contribution": 0.0, "idf": 0.0, "tf": 0, "in_doc": false}, {"token": "menolak", "contribution": 0.0, "idf": 0.0, "tf": 0, "in_doc": false}, {"token": "gugatan", "contribution": 0.0, "idf": 0.0, "tf": 0, "in_doc": false}, {"token": "penggugat", "contribution": 0.0, "idf": 0.0, "tf": 0, "in_doc": false}, {"token": "karena", "contribution": 0.0, "idf": 0.0, "tf": 0, "in_doc": false}, {"token": "dianggap", "contribution": 0.0, "idf": 0.0, "tf": 0, "in_doc": false}, {"token": "kurang", "contribution": 0.0, "idf": 0.0, "tf": 0, "in_doc": false}, {"token": "melibatkan", "contribution": 0.0, "idf": 0.0, "tf": 0, "in_doc": false}, {"token": "lain", "contribution": 0.0, "idf": 0.0, "tf": 0, "in_doc": false}, {"token": "pemilik", "contribution": 0.0, "idf": 0.0, "tf": 0, "in_doc": false}, {"token": "tanah", "contribution": 0.0, "idf": 0.0, "tf": 0, "in_doc": false}, {"token": "yang", "contribution": 0.0, "idf": 0.0, "tf": 3, "in_doc": true}, {"token": "meninggal", "contribution": 0.0, "idf": 0.0, "tf": 0, "in_doc": false}, {"token": "padahal", "contribution": 0.0, "idf": 0.0, "tf": 0, "in_doc": false}], "doc_highlights": [{"start": 53, "end": 57, "token": "ahli", "intensity": 0.933, "score": 5.3277}, {"start": 58, "end": 63, "token": "waris", "intensity": 1.0, "score": 5.7108}, {"start": 138, "end": 142, "token": "dari", "intensity": 0.56, "score": 3.2007}, {"start": 276, "end": 281, "token": "sudah", "intensity": 0.975, "score": 5.5705}, {"start": 304, "end": 308, "token": "ahli", "intensity": 0.933, "score": 5.3277}, {"start": 309, "end": 314, "token": "waris", "intensity": 1.0, "score": 5.7108}, {"start": 349, "end": 354, "token": "sudah", "intensity": 0.975, "score": 5.5705}, {"start": 362, "end": 365, "token": "dan", "intensity": 0.221, "score": 1.2628}, {"start": 419, "end": 423, "token": "dari", "intensity": 0.56, "score": 3.2007}, {"start": 429, "end": 433, "token": "ahli", "intensity": 0.933, "score": 5.3277}, {"start": 434, "end": 439, "token": "waris", "intensity": 1.0, "score": 5.7108}, {"start": 505, "end": 509, "token": "ahli", "intensity": 0.933, "score": 5.3277}, {"start": 510, "end": 515, "token": "waris", "intensity": 1.0, "score": 5.7108}], "query_highlights": [{"start": 81, "end": 85, "token": "ahli", "intensity": 0.933, "score": 5.3277}, {"start": 86, "end": 91, "token": "waris", "intensity": 1.0, "score": 5.7108}, {"start": 97, "end": 101, "token": "dari", "intensity": 0.56, "score": 3.2007}, {"start": 152, "end": 155, "token": "dan", "intensity": 0.221, "score": 1.2628}, {"start": 167, "end": 172, "token": "sudah", "intensity": 0.975, "score": 5.5705}]}, {"rank": 17, "doc_id": "270", "title": "Pasal 270", "bm25_score": 13.9283, "is_relevant": false, "per_token": [{"token": "gugatan", "contribution": 5.8929, "idf": 4.8343, "tf": 1, "in_doc": true}, {"token": "meninggal", "contribution": 4.7973, "idf": 3.9356, "tf": 1, "in_doc": true}, {"token": "waris", "contribution": 4.2366, "idf": 3.4756, "tf": 1, "in_doc": true}, {"token": "ahli", "contribution": 3.9524, "idf": 3.2424, "tf": 1, "in_doc": true}, {"token": "mengapa", "contribution": 0.0, "idf": 0.0, "tf": 0, "in_doc": false}, {"token": "pengadilan", "contribution": 0.0, "idf": 0.0, "tf": 0, "in_doc": false}, {"token": "menolak", "contribution": 0.0, "idf": 0.0, "tf": 0, "in_doc": false}, {"token": "penggugat", "contribution": 0.0, "idf": 0.0, "tf": 0, "in_doc": false}, {"token": "karena", "contribution": 0.0, "idf": 0.0, "tf": 0, "in_doc": false}, {"token": "dianggap", "contribution": 0.0, "idf": 0.0, "tf": 0, "in_doc": false}, {"token": "kurang", "contribution": 0.0, "idf": 0.0, "tf": 0, "in_doc": false}, {"token": "melibatkan", "contribution": 0.0, "idf": 0.0, "tf": 0, "in_doc": false}, {"token": "lain", "contribution": 0.0, "idf": 0.0, "tf": 0, "in_doc": false}, {"token": "dari", "contribution": 0.0, "idf": 0.0, "tf": 0, "in_doc": false}, {"token": "pemilik", "contribution": 0.0, "idf": 0.0, "tf": 0, "in_doc": false}, {"token": "tanah", "contribution": 0.0, "idf": 0.0, "tf": 0, "in_doc": false}, {"token": "yang", "contribution": 0.0, "idf": 0.0, "tf": 1, "in_doc": true}, {"token": "padahal", "contribution": 0.0, "idf": 0.0, "tf": 0, "in_doc": false}, {"token": "dan", "contribution": 0.0, "idf": 0.0, "tf": 0, "in_doc": false}, {"token": "tergugat", "contribution": 0.0, "idf": 0.0, "tf": 0, "in_doc": false}], "doc_highlights": [{"start": 16, "end": 20, "token": "ahli", "intensity": 0.671, "score": 3.9524}, {"start": 21, "end": 26, "token": "waris", "intensity": 0.719, "score": 4.2366}, {"start": 96, "end": 103, "token": "gugatan", "intensity": 1.0, "score": 5.8929}, {"start": 135, "end": 144, "token": "meninggal", "intensity": 0.814, "score": 4.7973}], "query_highlights": [{"start": 27, "end": 34, "token": "gugatan", "intensity": 1.0, "score": 5.8929}, {"start": 81, "end": 85, "token": "ahli", "intensity": 0.671, "score": 3.9524}, {"start": 86, "end": 91, "token": "waris", "intensity": 0.719, "score": 4.2366}, {"start": 121, "end": 130, "token": "meninggal", "intensity": 0.814, "score": 4.7973}]}, {"rank": 18, "doc_id": "1594", "title": "Pasal 1594", "bm25_score": 13.8498, "is_relevant": false, "per_token": [{"token": "sudah", "contribution": 6.1772, "idf": 4.5521, "tf": 2, "in_doc": true}, {"token": "pemilik", "contribution": 5.1609, "idf": 3.8031, "tf": 2, "in_doc": true}, {"token": "tanah", "contribution": 3.7071, "idf": 3.9808, "tf": 1, "in_doc": true}, {"token": "dari", "contribution": 3.5493, "idf": 2.6156, "tf": 2, "in_doc": true}, {"token": "dan", "contribution": 1.4516, "idf": 1.5588, "tf": 1, "in_doc": true}, {"token": "mengapa", "contribution": 0.0, "idf": 0.0, "tf": 0, "in_doc": false}, {"token": "pengadilan", "contribution": 0.0, "idf": 0.0, "tf": 0, "in_doc": false}, {"token": "menolak", "contribution": 0.0, "idf": 0.0, "tf": 0, "in_doc": false}, {"token": "gugatan", "contribution": 0.0, "idf": 0.0, "tf": 0, "in_doc": false}, {"token": "penggugat", "contribution": 0.0, "idf": 0.0, "tf": 0, "in_doc": false}, {"token": "karena", "contribution": 0.0, "idf": 0.0, "tf": 0, "in_doc": false}, {"token": "dianggap", "contribution": 0.0, "idf": 0.0, "tf": 0, "in_doc": false}, {"token": "kurang", "contribution": 0.0, "idf": 0.0, "tf": 0, "in_doc": false}, {"token": "melibatkan", "contribution": 0.0, "idf": 0.0, "tf": 0, "in_doc": false}, {"token": "ahli", "contribution": 0.0, "idf": 0.0, "tf": 0, "in_doc": false}, {"token": "waris", "contribution": 0.0, "idf": 0.0, "tf": 0, "in_doc": false}, {"token": "lain", "contribution": 0.0, "idf": 0.0, "tf": 0, "in_doc": false}, {"token": "yang", "contribution": 0.0, "idf": 0.0, "tf": 1, "in_doc": true}, {"token": "meninggal", "contribution": 0.0, "idf": 0.0, "tf": 0, "in_doc": false}, {"token": "padahal", "contribution": 0.0, "idf": 0.0, "tf": 0, "in_doc": false}], "doc_highlights": [{"start": 111, "end": 115, "token": "dari", "intensity": 0.575, "score": 3.5493}, {"start": 116, "end": 121, "token": "tanah", "intensity": 0.6, "score": 3.7071}, {"start": 176, "end": 183, "token": "pemilik", "intensity": 0.835, "score": 5.1609}, {"start": 268, "end": 275, "token": "pemilik", "intensity": 0.835, "score": 5.1609}, {"start": 290, "end": 294, "token": "dari", "intensity": 0.575, "score": 3.5493}, {"start": 403, "end": 408, "token": "sudah", "intensity": 1.0, "score": 6.1772}, {"start": 413, "end": 416, "token": "dan", "intensity": 0.235, "score": 1.4516}, {"start": 417, "end": 422, "token": "sudah", "intensity": 1.0, "score": 6.1772}], "query_highlights": [{"start": 97, "end": 101, "token": "dari", "intensity": 0.575, "score": 3.5493}, {"start": 102, "end": 109, "token": "pemilik", "intensity": 0.835, "score": 5.1609}, {"start": 110, "end": 115, "token": "tanah", "intensity": 0.6, "score": 3.7071}, {"start": 152, "end": 155, "token": "dan", "intensity": 0.235, "score": 1.4516}, {"start": 167, "end": 172, "token": "sudah", "intensity": 1.0, "score": 6.1772}]}, {"rank": 19, "doc_id": "731", "title": "Pasal 731", "bm25_score": 13.7511, "is_relevant": false, "per_token": [{"token": "kurang", "contribution": 5.8283, "idf": 5.6184, "tf": 1, "in_doc": true}, {"token": "tanah", "contribution": 4.1295, "idf": 3.9808, "tf": 1, "in_doc": true}, {"token": "pemilik", "contribution": 3.9452, "idf": 3.8031, "tf": 1, "in_doc": true}, {"token": "karena", "contribution": 3.1487, "idf": 3.0353, "tf": 1, "in_doc": true}, {"token": "dan", "contribution": 2.651, "idf": 1.5588, "tf": 3, "in_doc": true}, {"token": "mengapa", "contribution": 0.0, "idf": 0.0, "tf": 0, "in_doc": false}, {"token": "pengadilan", "contribution": 0.0, "idf": 0.0, "tf": 0, "in_doc": false}, {"token": "menolak", "contribution": 0.0, "idf": 0.0, "tf": 0, "in_doc": false}, {"token": "gugatan", "contribution": 0.0, "idf": 0.0, "tf": 0, "in_doc": false}, {"token": "penggugat", "contribution": 0.0, "idf": 0.0, "tf": 0, "in_doc": false}, {"token": "dianggap", "contribution": 0.0, "idf": 0.0, "tf": 0, "in_doc": false}, {"token": "melibatkan", "contribution": 0.0, "idf": 0.0, "tf": 0, "in_doc": false}, {"token": "ahli", "contribution": 0.0, "idf": 0.0, "tf": 0, "in_doc": false}, {"token": "waris", "contribution": 0.0, "idf": 0.0, "tf": 0, "in_doc": false}, {"token": "lain", "contribution": 0.0, "idf": 0.0, "tf": 0, "in_doc": false}, {"token": "dari", "contribution": 0.0, "idf": 0.0, "tf": 0, "in_doc": false}, {"token": "yang", "contribution": 0.0, "idf": 0.0, "tf": 2, "in_doc": true}, {"token": "meninggal", "contribution": 0.0, "idf": 0.0, "tf": 0, "in_doc": false}, {"token": "padahal", "contribution": 0.0, "idf": 0.0, "tf": 0, "in_doc": false}, {"token": "tergugat", "contribution": 0.0, "idf": 0.0, "tf": 0, "in_doc": false}], "doc_highlights": [{"start": 46, "end": 53, "token": "pemilik", "intensity": 0.677, "score": 3.9452}, {"start": 54, "end": 59, "token": "tanah", "intensity": 0.709, "score": 4.1295}, {"start": 152, "end": 155, "token": "dan", "intensity": 0.455, "score": 2.651}, {"start": 208, "end": 211, "token": "dan", "intensity": 0.455, "score": 2.651}, {"start": 212, "end": 218, "token": "kurang", "intensity": 1.0, "score": 5.8283}, {"start": 241, "end": 244, "token": "dan", "intensity": 0.455, "score": 2.651}, {"start": 317, "end": 323, "token": "karena", "intensity": 0.54, "score": 3.1487}], "query_highlights": [{"start": 47, "end": 53, "token": "karena", "intensity": 0.54, "score": 3.1487}, {"start": 63, "end": 69, "token": "kurang", "intensity": 1.0, "score": 5.8283}, {"start": 102, "end": 109, "token": "pemilik", "intensity": 0.677, "score": 3.9452}, {"start": 110, "end": 115, "token": "tanah", "intensity": 0.709, "score": 4.1295}, {"start": 152, "end": 155, "token": "dan", "intensity": 0.455, "score": 2.651}]}, {"rank": 20, "doc_id": "565", "title": "Pasal 565", "bm25_score": 13.6765, "is_relevant": false, "per_token": [{"token": "gugatan", "contribution": 8.4727, "idf": 4.8343, "tf": 4, "in_doc": true}, {"token": "penggugat", "contribution": 5.7083, "idf": 6.178, "tf": 1, "in_doc": true}, {"token": "dari", "contribution": 2.4167, "idf": 2.6156, "tf": 1, "in_doc": true}, {"token": "dan", "contribution": 2.1032, "idf": 1.5588, "tf": 2, "in_doc": true}, {"token": "mengapa", "contribution": 0.0, "idf": 0.0, "tf": 0, "in_doc": false}, {"token": "pengadilan", "contribution": 0.0, "idf": 0.0, "tf": 0, "in_doc": false}, {"token": "menolak", "contribution": 0.0, "idf": 0.0, "tf": 0, "in_doc": false}, {"token": "karena", "contribution": 0.0, "idf": 0.0, "tf": 0, "in_doc": false}, {"token": "dianggap", "contribution": 0.0, "idf": 0.0, "tf": 0, "in_doc": false}, {"token": "kurang", "contribution": 0.0, "idf": 0.0, "tf": 0, "in_doc": false}, {"token": "melibatkan", "contribution": 0.0, "idf": 0.0, "tf": 0, "in_doc": false}, {"token": "ahli", "contribution": 0.0, "idf": 0.0, "tf": 0, "in_doc": false}, {"token": "waris", "contribution": 0.0, "idf": 0.0, "tf": 0, "in_doc": false}, {"token": "lain", "contribution": 0.0, "idf": 0.0, "tf": 0, "in_doc": false}, {"token": "pemilik", "contribution": 0.0, "idf": 0.0, "tf": 0, "in_doc": false}, {"token": "tanah", "contribution": 0.0, "idf": 0.0, "tf": 0, "in_doc": false}, {"token": "yang", "contribution": 0.0, "idf": 0.0, "tf": 2, "in_doc": true}, {"token": "meninggal", "contribution": 0.0, "idf": 0.0, "tf": 0, "in_doc": false}, {"token": "padahal", "contribution": 0.0, "idf": 0.0, "tf": 0, "in_doc": false}, {"token": "tergugat", "contribution": 0.0, "idf": 0.0, "tf": 0, "in_doc": false}], "doc_highlights": [{"start": 11, "end": 18, "token": "gugatan", "intensity": 1.0, "score": 8.4727}, {"start": 43, "end": 46, "token": "dan", "intensity": 0.248, "score": 2.1032}, {"start": 154, "end": 158, "token": "dari", "intensity": 0.285, "score": 2.4167}, {"start": 164, "end": 173, "token": "penggugat", "intensity": 0.674, "score": 5.7083}, {"start": 213, "end": 216, "token": "dan", "intensity": 0.248, "score": 2.1032}, {"start": 256, "end": 263, "token": "gugatan", "intensity": 1.0, "score": 8.4727}, {"start": 383, "end": 390, "token": "gugatan", "intensity": 1.0, "score": 8.4727}, {"start": 437, "end": 444, "token": "gugatan", "intensity": 1.0, "score": 8.4727}], "query_highlights": [{"start": 27, "end": 34, "token": "gugatan", "intensity": 1.0, "score": 8.4727}, {"start": 36, "end": 45, "token": "penggugat", "intensity": 0.674, "score": 5.7083}, {"start": 97, "end": 101, "token": "dari", "intensity": 0.285, "score": 2.4167}, {"start": 141, "end": 150, "token": "penggugat", "intensity": 0.674, "score": 5.7083}, {"start": 152, "end": 155, "token": "dan", "intensity": 0.248, "score": 2.1032}]}, {"rank": 21, "doc_id": "1126", "title": "Pasal 1126", "bm25_score": 13.4599, "is_relevant": false, "per_token": [{"token": "menolak", "contribution": 5.7739, "idf": 4.8343, "tf": 1, "in_doc": true}, {"token": "dianggap", "contribution": 4.3863, "idf": 3.6725, "tf": 1, "in_doc": true}, {"token": "waris", "contribution": 4.1511, "idf": 3.4756, "tf": 1, "in_doc": true}, {"token": "ahli", "contribution": 3.8726, "idf": 3.2424, "tf": 1, "in_doc": true}, {"token": "mengapa", "contribution": 0.0, "idf": 0.0, "tf": 0, "in_doc": false}, {"token": "pengadilan", "contribution": 0.0, "idf": 0.0, "tf": 0, "in_doc": false}, {"token": "gugatan", "contribution": 0.0, "idf": 0.0, "tf": 0, "in_doc": false}, {"token": "penggugat", "contribution": 0.0, "idf": 0.0, "tf": 0, "in_doc": false}, {"token": "karena", "contribution": 0.0, "idf": 0.0, "tf": 0, "in_doc": false}, {"token": "kurang", "contribution": 0.0, "idf": 0.0, "tf": 0, "in_doc": false}, {"token": "melibatkan", "contribution": 0.0, "idf": 0.0, "tf": 0, "in_doc": false}, {"token": "lain", "contribution": 0.0, "idf": 0.0, "tf": 0, "in_doc": false}, {"token": "dari", "contribution": 0.0, "idf": 0.0, "tf": 0, "in_doc": false}, {"token": "pemilik", "contribution": 0.0, "idf": 0.0, "tf": 0, "in_doc": false}, {"token": "tanah", "contribution": 0.0, "idf": 0.0, "tf": 0, "in_doc": false}, {"token": "yang", "contribution": 0.0, "idf": 0.0, "tf": 2, "in_doc": true}, {"token": "meninggal", "contribution": 0.0, "idf": 0.0, "tf": 0, "in_doc": false}, {"token": "padahal", "contribution": 0.0, "idf": 0.0, "tf": 0, "in_doc": false}, {"token": "dan", "contribution": 0.0, "idf": 0.0, "tf": 0, "in_doc": false}, {"token": "tergugat", "contribution": 0.0, "idf": 0.0, "tf": 0, "in_doc": false}], "doc_highlights": [{"start": 125, "end": 129, "token": "ahli", "intensity": 0.671, "score": 3.8726}, {"start": 130, "end": 135, "token": "waris", "intensity": 0.719, "score": 4.1511}, {"start": 149, "end": 156, "token": "menolak", "intensity": 1.0, "score": 5.7739}, {"start": 197, "end": 205, "token": "dianggap", "intensity": 0.76, "score": 4.3863}], "query_highlights": [{"start": 19, "end": 26, "token": "menolak", "intensity": 1.0, "score": 5.7739}, {"start": 54, "end": 62, "token": "dianggap", "intensity": 0.76, "score": 4.3863}, {"start": 81, "end": 85, "token": "ahli", "intensity": 0.671, "score": 3.8726}, {"start": 86, "end": 91, "token": "waris", "intensity": 0.719, "score": 4.1511}]}, {"rank": 22, "doc_id": "834", "title": "Pasal 834", "bm25_score": 13.4244, "is_relevant": false, "per_token": [{"token": "gugatan", "contribution": 6.7372, "idf": 4.8343, "tf": 3, "in_doc": true}, {"token": "waris", "contribution": 4.8436, "idf": 3.4756, "tf": 3, "in_doc": true}, {"token": "ahli", "contribution": 4.5187, "idf": 3.2424, "tf": 3, "in_doc": true}, {"token": "lain", "contribution": 1.9769, "idf": 2.674, "tf": 1, "in_doc": true}, {"token": "dan", "contribution": 1.1524, "idf": 1.5588, "tf": 1, "in_doc": true}, {"token": "mengapa", "contribution": 0.0, "idf": 0.0, "tf": 0, "in_doc": false}, {"token": "pengadilan", "contribution": 0.0, "idf": 0.0, "tf": 0, "in_doc": false}, {"token": "menolak", "contribution": 0.0, "idf": 0.0, "tf": 0, "in_doc": false}, {"token": "penggugat", "contribution": 0.0, "idf": 0.0, "tf": 0, "in_doc": false}, {"token": "karena", "contribution": 0.0, "idf": 0.0, "tf": 0, "in_doc": false}, {"token": "dianggap", "contribution": 0.0, "idf": 0.0, "tf": 0, "in_doc": false}, {"token": "kurang", "contribution": 0.0, "idf": 0.0, "tf": 0, "in_doc": false}, {"token": "melibatkan", "contribution": 0.0, "idf": 0.0, "tf": 0, "in_doc": false}, {"token": "dari", "contribution": 0.0, "idf": 0.0, "tf": 0, "in_doc": false}, {"token": "pemilik", "contribution": 0.0, "idf": 0.0, "tf": 0, "in_doc": false}, {"token": "tanah", "contribution": 0.0, "idf": 0.0, "tf": 0, "in_doc": false}, {"token": "yang", "contribution": 0.0, "idf": 0.0, "tf": 4, "in_doc": true}, {"token": "meninggal", "contribution": 0.0, "idf": 0.0, "tf": 0, "in_doc": false}, {"token": "padahal", "contribution": 0.0, "idf": 0.0, "tf": 0, "in_doc": false}, {"token": "tergugat", "contribution": 0.0, "idf": 0.0, "tf": 0, "in_doc": false}], "doc_highlights": [{"start": 11, "end": 15, "token": "ahli", "intensity": 0.671, "score": 4.5187}, {"start": 16, "end": 21, "token": "waris", "intensity": 0.719, "score": 4.8436}, {"start": 40, "end": 47, "token": "gugatan", "intensity": 1.0, "score": 6.7372}, {"start": 294, "end": 301, "token": "gugatan", "intensity": 1.0, "score": 6.7372}, {"start": 356, "end": 360, "token": "ahli", "intensity": 0.671, "score": 4.5187}, {"start": 361, "end": 366, "token": "waris", "intensity": 0.719, "score": 4.8436}, {"start": 403, "end": 407, "token": "ahli", "intensity": 0.671, "score": 4.5187}, {"start": 408, "end": 413, "token": "waris", "intensity": 0.719, "score": 4.8436}, {"start": 414, "end": 418, "token": "lain", "intensity": 0.293, "score": 1.9769}, {"start": 420, "end": 427, "token": "gugatan", "intensity": 1.0, "score": 6.7372}, {"start": 575, "end": 578, "token": "dan", "intensity": 0.171, "score": 1.1524}], "query_highlights": [{"start": 27, "end": 34, "token": "gugatan", "intensity": 1.0, "score": 6.7372}, {"start": 81, "end": 85, "token": "ahli", "intensity": 0.671, "score": 4.5187}, {"start": 86, "end": 91, "token": "waris", "intensity": 0.719, "score": 4.8436}, {"start": 92, "end": 96, "token": "lain", "intensity": 0.293, "score": 1.9769}, {"start": 152, "end": 155, "token": "dan", "intensity": 0.171, "score": 1.1524}]}, {"rank": 23, "doc_id": "1674", "title": "Pasal 1674", "bm25_score": 13.3588, "is_relevant": false, "per_token": [{"token": "gugatan", "contribution": 6.422, "idf": 4.8343, "tf": 1, "in_doc": true}, {"token": "pengadilan", "contribution": 5.6101, "idf": 3.2336, "tf": 2, "in_doc": true}, {"token": "lain", "contribution": 3.5522, "idf": 2.674, "tf": 1, "in_doc": true}, {"token": "dari", "contribution": 3.4746, "idf": 2.6156, "tf": 1, "in_doc": true}, {"token": "mengapa", "contribution": 0.0, "idf": 0.0, "tf": 0, "in_doc": false}, {"token": "menolak", "contribution": 0.0, "idf": 0.0, "tf": 0, "in_doc": false}, {"token": "penggugat", "contribution": 0.0, "idf": 0.0, "tf": 0, "in_doc": false}, {"token": "karena", "contribution": 0.0, "idf": 0.0, "tf": 0, "in_doc": false}, {"token": "dianggap", "contribution": 0.0, "idf": 0.0, "tf": 0, "in_doc": false}, {"token": "kurang", "contribution": 0.0, "idf": 0.0, "tf": 0, "in_doc": false}, {"token": "melibatkan", "contribution": 0.0, "idf": 0.0, "tf": 0, "in_doc": false}, {"token": "ahli", "contribution": 0.0, "idf": 0.0, "tf": 0, "in_doc": false}, {"token": "waris", "contribution": 0.0, "idf": 0.0, "tf": 0, "in_doc": false}, {"token": "pemilik", "contribution": 0.0, "idf": 0.0, "tf": 0, "in_doc": false}, {"token": "tanah", "contribution": 0.0, "idf": 0.0, "tf": 0, "in_doc": false}, {"token": "yang", "contribution": 0.0, "idf": 0.0, "tf": 1, "in_doc": true}, {"token": "meninggal", "contribution": 0.0, "idf": 0.0, "tf": 0, "in_doc": false}, {"token": "padahal", "contribution": 0.0, "idf": 0.0, "tf": 0, "in_doc": false}, {"token": "dan", "contribution": 0.0, "idf": 0.0, "tf": 0, "in_doc": false}, {"token": "tergugat", "contribution": 0.0, "idf": 0.0, "tf": 0, "in_doc": false}], "doc_highlights": [{"start": 55, "end": 59, "token": "dari", "intensity": 0.541, "score": 3.4746}, {"start": 60, "end": 67, "token": "gugatan", "intensity": 1.0, "score": 6.422}, {"start": 68, "end": 78, "token": "pengadilan", "intensity": 0.874, "score": 5.6101}, {"start": 140, "end": 144, "token": "lain", "intensity": 0.553, "score": 3.5522}, {"start": 167, "end": 177, "token": "pengadilan", "intensity": 0.874, "score": 5.6101}], "query_highlights": [{"start": 8, "end": 18, "token": "pengadilan", "intensity": 0.874, "score": 5.6101}, {"start": 27, "end": 34, "token": "gugatan", "intensity": 1.0, "score": 6.422}, {"start": 92, "end": 96, "token": "lain", "intensity": 0.553, "score": 3.5522}, {"start": 97, "end": 101, "token": "dari", "intensity": 0.541, "score": 3.4746}]}, {"rank": 24, "doc_id": "894", "title": "Pasal 894", "bm25_score": 13.3253, "is_relevant": false, "per_token": [{"token": "meninggal", "contribution": 6.5673, "idf": 3.9356, "tf": 3, "in_doc": true}, {"token": "dianggap", "contribution": 3.6806, "idf": 3.6725, "tf": 1, "in_doc": true}, {"token": "waris", "contribution": 3.4832, "idf": 3.4756, "tf": 1, "in_doc": true}, {"token": "ahli", "contribution": 3.2496, "idf": 3.2424, "tf": 1, "in_doc": true}, {"token": "dan", "contribution": 2.6012, "idf": 1.5588, "tf": 3, "in_doc": true}, {"token": "mengapa", "contribution": 0.0, "idf": 0.0, "tf": 0, "in_doc": false}, {"token": "pengadilan", "contribution": 0.0, "idf": 0.0, "tf": 0, "in_doc": false}, {"token": "menolak", "contribution": 0.0, "idf": 0.0, "tf": 0, "in_doc": false}, {"token": "gugatan", "contribution": 0.0, "idf": 0.0, "tf": 0, "in_doc": false}, {"token": "penggugat", "contribution": 0.0, "idf": 0.0, "tf": 0, "in_doc": false}, {"token": "karena", "contribution": 0.0, "idf": 0.0, "tf": 0, "in_doc": false}, {"token": "kurang", "contribution": 0.0, "idf": 0.0, "tf": 0, "in_doc": false}, {"token": "melibatkan", "contribution": 0.0, "idf": 0.0, "tf": 0, "in_doc": false}, {"token": "lain", "contribution": 0.0, "idf": 0.0, "tf": 0, "in_doc": false}, {"token": "dari", "contribution": 0.0, "idf": 0.0, "tf": 0, "in_doc": false}, {"token": "pemilik", "contribution": 0.0, "idf": 0.0, "tf": 0, "in_doc": false}, {"token": "tanah", "contribution": 0.0, "idf": 0.0, "tf": 0, "in_doc": false}, {"token": "yang", "contribution": 0.0, "idf": 0.0, "tf": 4, "in_doc": true}, {"token": "padahal", "contribution": 0.0, "idf": 0.0, "tf": 0, "in_doc": false}, {"token": "tergugat", "contribution": 0.0, "idf": 0.0, "tf": 0, "in_doc": false}], "doc_highlights": [{"start": 72, "end": 75, "token": "dan", "intensity": 0.396, "score": 2.6012}, {"start": 76, "end": 80, "token": "ahli", "intensity": 0.495, "score": 3.2496}, {"start": 81, "end": 86, "token": "waris", "intensity": 0.53, "score": 3.4832}, {"start": 160, "end": 169, "token": "meninggal", "intensity": 1.0, "score": 6.5673}, {"start": 193, "end": 196, "token": "dan", "intensity": 0.396, "score": 2.6012}, {"start": 209, "end": 218, "token": "meninggal", "intensity": 1.0, "score": 6.5673}, {"start": 243, "end": 251, "token": "dianggap", "intensity": 0.56, "score": 3.6806}, {"start": 258, "end": 267, "token": "meninggal", "intensity": 1.0, "score": 6.5673}, {"start": 289, "end": 292, "token": "dan", "intensity": 0.396, "score": 2.6012}], "query_highlights": [{"start": 54, "end": 62, "token": "dianggap", "intensity": 0.56, "score": 3.6806}, {"start": 81, "end": 85, "token": "ahli", "intensity": 0.495, "score": 3.2496}, {"start": 86, "end": 91, "token": "waris", "intensity": 0.53, "score": 3.4832}, {"start": 121, "end": 130, "token": "meninggal", "intensity": 1.0, "score": 6.5673}, {"start": 152, "end": 155, "token": "dan", "intensity": 0.396, "score": 2.6012}]}, {"rank": 25, "doc_id": "1083", "title": "Pasal 1083", "bm25_score": 13.1715, "is_relevant": false, "per_token": [{"token": "dianggap", "contribution": 5.3849, "idf": 3.6725, "tf": 2, "in_doc": true}, {"token": "waris", "contribution": 5.0961, "idf": 3.4756, "tf": 2, "in_doc": true}, {"token": "ahli", "contribution": 4.7543, "idf": 3.2424, "tf": 2, "in_doc": true}, {"token": "lain", "contribution": 2.7738, "idf": 2.674, "tf": 1, "in_doc": true}, {"token": "dan", "contribution": 1.617, "idf": 1.5588, "tf": 1, "in_doc": true}, {"token": "mengapa", "contribution": 0.0, "idf": 0.0, "tf": 0, "in_doc": false}, {"token": "pengadilan", "contribution": 0.0, "idf": 0.0, "tf": 0, "in_doc": false}, {"token": "menolak", "contribution": 0.0, "idf": 0.0, "tf": 0, "in_doc": false}, {"token": "gugatan", "contribution": 0.0, "idf": 0.0, "tf": 0, "in_doc": false}, {"token": "penggugat", "contribution": 0.0, "idf": 0.0, "tf": 0, "in_doc": false}, {"token": "karena", "contribution": 0.0, "idf": 0.0, "tf": 0, "in_doc": false}, {"token": "kurang", "contribution": 0.0, "idf": 0.0, "tf": 0, "in_doc": false}, {"token": "melibatkan", "contribution": 0.0, "idf": 0.0, "tf": 0, "in_doc": false}, {"token": "dari", "contribution": 0.0, "idf": 0.0, "tf": 0, "in_doc": false}, {"token": "pemilik", "contribution": 0.0, "idf": 0.0, "tf": 0, "in_doc": false}, {"token": "tanah", "contribution": 0.0, "idf": 0.0, "tf": 0, "in_doc": false}, {"token": "yang", "contribution": 0.0, "idf": 0.0, "tf": 2, "in_doc": true}, {"token": "meninggal", "contribution": 0.0, "idf": 0.0, "tf": 0, "in_doc": false}, {"token": "padahal", "contribution": 0.0, "idf": 0.0, "tf": 0, "in_doc": false}, {"token": "tergugat", "contribution": 0.0, "idf": 0.0, "tf": 0, "in_doc": false}], "doc_highlights": [{"start": 22, "end": 26, "token": "ahli", "intensity": 0.883, "score": 4.7543}, {"start": 27, "end": 32, "token": "waris", "intensity": 0.946, "score": 5.0961}, {"start": 33, "end": 41, "token": "dianggap", "intensity": 1.0, "score": 5.3849}, {"start": 246, "end": 250, "token": "ahli", "intensity": 0.883, "score": 4.7543}, {"start": 251, "end": 256, "token": "waris", "intensity": 0.946, "score": 5.0961}, {"start": 257, "end": 265, "token": "dianggap", "intensity": 1.0, "score": 5.3849}, {"start": 312, "end": 316, "token": "lain", "intensity": 0.515, "score": 2.7738}, {"start": 317, "end": 320, "token": "dan", "intensity": 0.3, "score": 1.617}], "query_highlights": [{"start": 54, "end": 62, "token": "dianggap", "intensity": 1.0, "score": 5.3849}, {"start": 81, "end": 85, "token": "ahli", "intensity": 0.883, "score": 4.7543}, {"start": 86, "end": 91, "token": "waris", "intensity": 0.946, "score": 5.0961}, {"start": 92, "end": 96, "token": "lain", "intensity": 0.515, "score": 2.7738}, {"start": 152, "end": 155, "token": "dan", "intensity": 0.3, "score": 1.617}]}, {"rank": 246, "doc_id": "832", "title": "Pasal 832", "bm25_score": 7.5226, "is_relevant": true, "per_token": [{"token": "meninggal", "contribution": 3.4226, "idf": 3.9356, "tf": 1, "in_doc": true}, {"token": "waris", "contribution": 3.0226, "idf": 3.4756, "tf": 1, "in_doc": true}, {"token": "ahli", "contribution": 2.8198, "idf": 3.2424, "tf": 1, "in_doc": true}, {"token": "dan", "contribution": 2.0115, "idf": 1.5588, "tf": 2, "in_doc": true}, {"token": "mengapa", "contribution": 0.0, "idf": 0.0, "tf": 0, "in_doc": false}, {"token": "pengadilan", "contribution": 0.0, "idf": 0.0, "tf": 0, "in_doc": false}, {"token": "menolak", "contribution": 0.0, "idf": 0.0, "tf": 0, "in_doc": false}, {"token": "gugatan", "contribution": 0.0, "idf": 0.0, "tf": 0, "in_doc": false}, {"token": "penggugat", "contribution": 0.0, "idf": 0.0, "tf": 0, "in_doc": false}, {"token": "karena", "contribution": 0.0, "idf": 0.0, "tf": 0, "in_doc": false}, {"token": "dianggap", "contribution": 0.0, "idf": 0.0, "tf": 0, "in_doc": false}, {"token": "kurang", "contribution": 0.0, "idf": 0.0, "tf": 0, "in_doc": false}, {"token": "melibatkan", "contribution": 0.0, "idf": 0.0, "tf": 0, "in_doc": false}, {"token": "lain", "contribution": 0.0, "idf": 0.0, "tf": 0, "in_doc": false}, {"token": "dari", "contribution": 0.0, "idf": 0.0, "tf": 0, "in_doc": false}, {"token": "pemilik", "contribution": 0.0, "idf": 0.0, "tf": 0, "in_doc": false}, {"token": "tanah", "contribution": 0.0, "idf": 0.0, "tf": 0, "in_doc": false}, {"token": "yang", "contribution": 0.0, "idf": 0.0, "tf": 7, "in_doc": true}, {"token": "padahal", "contribution": 0.0, "idf": 0.0, "tf": 0, "in_doc": false}, {"token": "tergugat", "contribution": 0.0, "idf": 0.0, "tf": 0, "in_doc": false}], "doc_highlights": [{"start": 54, "end": 58, "token": "ahli", "intensity": 0.824, "score": 2.8198}, {"start": 59, "end": 64, "token": "waris", "intensity": 0.883, "score": 3.0226}, {"start": 157, "end": 160, "token": "dan", "intensity": 0.588, "score": 2.0115}, {"start": 262, "end": 265, "token": "dan", "intensity": 0.588, "score": 2.0115}, {"start": 408, "end": 417, "token": "meninggal", "intensity": 1.0, "score": 3.4226}], "query_highlights": [{"start": 81, "end": 85, "token": "ahli", "intensity": 0.824, "score": 2.8198}, {"start": 86, "end": 91, "token": "waris", "intensity": 0.883, "score": 3.0226}, {"start": 121, "end": 130, "token": "meninggal", "intensity": 1.0, "score": 3.4226}, {"start": 152, "end": 155, "token": "dan", "intensity": 0.588, "score": 2.0115}], "beyond_topk": true}, {"rank": 629, "doc_id": "852", "title": "Pasal 852", "bm25_score": 4.7115, "is_relevant": true, "per_token": [{"token": "meninggal", "contribution": 3.1453, "idf": 3.9356, "tf": 1, "in_doc": true}, {"token": "karena", "contribution": 2.4258, "idf": 3.0353, "tf": 1, "in_doc": true}, {"token": "dan", "contribution": 2.2798, "idf": 1.5588, "tf": 3, "in_doc": true}, {"token": "mengapa", "contribution": 0.0, "idf": 0.0, "tf": 0, "in_doc": false}, {"token": "pengadilan", "contribution": 0.0, "idf": 0.0, "tf": 0, "in_doc": false}, {"token": "menolak", "contribution": 0.0, "idf": 0.0, "tf": 0, "in_doc": false}, {"token": "gugatan", "contribution": 0.0, "idf": 0.0, "tf": 0, "in_doc": false}, {"token": "penggugat", "contribution": 0.0, "idf": 0.0, "tf": 0, "in_doc": false}, {"token": "dianggap", "contribution": 0.0, "idf": 0.0, "tf": 0, "in_doc": false}, {"token": "kurang", "contribution": 0.0, "idf": 0.0, "tf": 0, "in_doc": false}, {"token": "melibatkan", "contribution": 0.0, "idf": 0.0, "tf": 0, "in_doc": false}, {"token": "ahli", "contribution": 0.0, "idf": 0.0, "tf": 0, "in_doc": false}, {"token": "waris", "contribution": 0.0, "idf": 0.0, "tf": 0, "in_doc": false}, {"token": "lain", "contribution": 0.0, "idf": 0.0, "tf": 0, "in_doc": false}, {"token": "dari", "contribution": 0.0, "idf": 0.0, "tf": 0, "in_doc": false}, {"token": "pemilik", "contribution": 0.0, "idf": 0.0, "tf": 0, "in_doc": false}, {"token": "tanah", "contribution": 0.0, "idf": 0.0, "tf": 0, "in_doc": false}, {"token": "yang", "contribution": 0.0, "idf": 0.0, "tf": 3, "in_doc": true}, {"token": "padahal", "contribution": 0.0, "idf": 0.0, "tf": 0, "in_doc": false}, {"token": "tergugat", "contribution": 0.0, "idf": 0.0, "tf": 0, "in_doc": false}], "doc_highlights": [{"start": 68, "end": 71, "token": "dan", "intensity": 0.725, "score": 2.2798}, {"start": 148, "end": 151, "token": "dan", "intensity": 0.725, "score": 2.2798}, {"start": 392, "end": 401, "token": "meninggal", "intensity": 1.0, "score": 3.1453}, {"start": 456, "end": 459, "token": "dan", "intensity": 0.725, "score": 2.2798}, {"start": 481, "end": 487, "token": "karena", "intensity": 0.771, "score": 2.4258}], "query_highlights": [{"start": 47, "end": 53, "token": "karena", "intensity": 0.771, "score": 2.4258}, {"start": 121, "end": 130, "token": "meninggal", "intensity": 1.0, "score": 3.1453}, {"start": 152, "end": 155, "token": "dan", "intensity": 0.725, "score": 2.2798}], "beyond_topk": true}, {"rank": 670, "doc_id": "2", "title": "Pasal 2", "bm25_score": 4.5336, "is_relevant": true, "per_token": [{"token": "dianggap", "contribution": 6.1901, "idf": 3.6725, "tf": 2, "in_doc": true}, {"token": "mengapa", "contribution": 0.0, "idf": 0.0, "tf": 0, "in_doc": false}, {"token": "pengadilan", "contribution": 0.0, "idf": 0.0, "tf": 0, "in_doc": false}, {"token": "menolak", "contribution": 0.0, "idf": 0.0, "tf": 0, "in_doc": false}, {"token": "gugatan", "contribution": 0.0, "idf": 0.0, "tf": 0, "in_doc": false}, {"token": "penggugat", "contribution": 0.0, "idf": 0.0, "tf": 0, "in_doc": false}, {"token": "karena", "contribution": 0.0, "idf": 0.0, "tf": 0, "in_doc": false}, {"token": "kurang", "contribution": 0.0, "idf": 0.0, "tf": 0, "in_doc": false}, {"token": "melibatkan", "contribution": 0.0, "idf": 0.0, "tf": 0, "in_doc": false}, {"token": "ahli", "contribution": 0.0, "idf": 0.0, "tf": 0, "in_doc": false}, {"token": "waris", "contribution": 0.0, "idf": 0.0, "tf": 0, "in_doc": false}, {"token": "lain", "contribution": 0.0, "idf": 0.0, "tf": 0, "in_doc": false}, {"token": "dari", "contribution": 0.0, "idf": 0.0, "tf": 0, "in_doc": false}, {"token": "pemilik", "contribution": 0.0, "idf": 0.0, "tf": 0, "in_doc": false}, {"token": "tanah", "contribution": 0.0, "idf": 0.0, "tf": 0, "in_doc": false}, {"token": "yang", "contribution": 0.0, "idf": 0.0, "tf": 1, "in_doc": true}, {"token": "meninggal", "contribution": 0.0, "idf": 0.0, "tf": 0, "in_doc": false}, {"token": "padahal", "contribution": 0.0, "idf": 0.0, "tf": 0, "in_doc": false}, {"token": "dan", "contribution": 0.0, "idf": 0.0, "tf": 0, "in_doc": false}, {"token": "tergugat", "contribution": 0.0, "idf": 0.0, "tf": 0, "in_doc": false}], "doc_highlights": [{"start": 57, "end": 65, "token": "dianggap", "intensity": 1.0, "score": 6.1901}, {"start": 167, "end": 175, "token": "dianggap", "intensity": 1.0, "score": 6.1901}], "query_highlights": [{"start": 54, "end": 62, "token": "dianggap", "intensity": 1.0, "score": 6.1901}], "beyond_topk": true}, {"rank": 1275, "doc_id": "1338", "title": "Pasal 1338", "bm25_score": 2.221, "is_relevant": true, "per_token": [{"token": "karena", "contribution": 3.293, "idf": 3.0353, "tf": 1, "in_doc": true}, {"token": "mengapa", "contribution": 0.0, "idf": 0.0, "tf": 0, "in_doc": false}, {"token": "pengadilan", "contribution": 0.0, "idf": 0.0, "tf": 0, "in_doc": false}, {"token": "menolak", "contribution": 0.0, "idf": 0.0, "tf": 0, "in_doc": false}, {"token": "gugatan", "contribution": 0.0, "idf": 0.0, "tf": 0, "in_doc": false}, {"token": "penggugat", "contribution": 0.0, "idf": 0.0, "tf": 0, "in_doc": false}, {"token": "dianggap", "contribution": 0.0, "idf": 0.0, "tf": 0, "in_doc": false}, {"token": "kurang", "contribution": 0.0, "idf": 0.0, "tf": 0, "in_doc": false}, {"token": "melibatkan", "contribution": 0.0, "idf": 0.0, "tf": 0, "in_doc": false}, {"token": "ahli", "contribution": 0.0, "idf": 0.0, "tf": 0, "in_doc": false}, {"token": "waris", "contribution": 0.0, "idf": 0.0, "tf": 0, "in_doc": false}, {"token": "lain", "contribution": 0.0, "idf": 0.0, "tf": 0, "in_doc": false}, {"token": "dari", "contribution": 0.0, "idf": 0.0, "tf": 0, "in_doc": false}, {"token": "pemilik", "contribution": 0.0, "idf": 0.0, "tf": 0, "in_doc": false}, {"token": "tanah", "contribution": 0.0, "idf": 0.0, "tf": 0, "in_doc": false}, {"token": "yang", "contribution": 0.0, "idf": 0.0, "tf": 3, "in_doc": true}, {"token": "meninggal", "contribution": 0.0, "idf": 0.0, "tf": 0, "in_doc": false}, {"token": "padahal", "contribution": 0.0, "idf": 0.0, "tf": 0, "in_doc": false}, {"token": "dan", "contribution": 0.0, "idf": 0.0, "tf": 0, "in_doc": false}, {"token": "tergugat", "contribution": 0.0, "idf": 0.0, "tf": 0, "in_doc": false}], "doc_highlights": [{"start": 223, "end": 229, "token": "karena", "intensity": 1.0, "score": 3.293}], "query_highlights": [{"start": 47, "end": 53, "token": "karena", "intensity": 1.0, "score": 3.293}], "beyond_topk": true}, {"rank": 1881, "doc_id": "1320", "title": "Pasal 1320", "bm25_score": 0.0, "is_relevant": true, "per_token": [{"token": "mengapa", "contribution": 0.0, "idf": 0.0, "tf": 0, "in_doc": false}, {"token": "pengadilan", "contribution": 0.0, "idf": 0.0, "tf": 0, "in_doc": false}, {"token": "menolak", "contribution": 0.0, "idf": 0.0, "tf": 0, "in_doc": false}, {"token": "gugatan", "contribution": 0.0, "idf": 0.0, "tf": 0, "in_doc": false}, {"token": "penggugat", "contribution": 0.0, "idf": 0.0, "tf": 0, "in_doc": false}, {"token": "karena", "contribution": 0.0, "idf": 0.0, "tf": 0, "in_doc": false}, {"token": "dianggap", "contribution": 0.0, "idf": 0.0, "tf": 0, "in_doc": false}, {"token": "kurang", "contribution": 0.0, "idf": 0.0, "tf": 0, "in_doc": false}, {"token": "melibatkan", "contribution": 0.0, "idf": 0.0, "tf": 0, "in_doc": false}, {"token": "ahli", "contribution": 0.0, "idf": 0.0, "tf": 0, "in_doc": false}, {"token": "waris", "contribution": 0.0, "idf": 0.0, "tf": 0, "in_doc": false}, {"token": "lain", "contribution": 0.0, "idf": 0.0, "tf": 0, "in_doc": false}, {"token": "dari", "contribution": 0.0, "idf": 0.0, "tf": 0, "in_doc": false}, {"token": "pemilik", "contribution": 0.0, "idf": 0.0, "tf": 0, "in_doc": false}, {"token": "tanah", "contribution": 0.0, "idf": 0.0, "tf": 0, "in_doc": false}, {"token": "yang", "contribution": 0.0, "idf": 0.0, "tf": 3, "in_doc": true}, {"token": "meninggal", "contribution": 0.0, "idf": 0.0, "tf": 0, "in_doc": false}, {"token": "padahal", "contribution": 0.0, "idf": 0.0, "tf": 0, "in_doc": false}, {"token": "dan", "contribution": 0.0, "idf": 0.0, "tf": 0, "in_doc": false}, {"token": "tergugat", "contribution": 0.0, "idf": 0.0, "tf": 0, "in_doc": false}], "doc_highlights": [], "query_highlights": [], "beyond_topk": true}]}